Workbook

Sheet RAT
B2: RAT - RELATÓRIO DE ATENDIMENTO
B3: EXECUÇÃO DOS SERVIÇOS
B4: Número da solicitação | D4: Data/hora Abertura | G4: Contrato de Manutenção | J4: Contratada
G5: 2024.7421.2057 | J5: MAFFENG ENGENHARIA E MANUTENÇÃO
B6: Sinistro | D6: Prazo de atendimento | G6: Tipo de Manutenção | J6: Nível de Ocorrência
B7: (Sim/Não) | G7: (Preventiva/Corretiva) | J7: (Emergencial/Urgente/Normal)
B8: Não | G8: Preventiva | J8: Normal
B9: Prefixo / SB - Dependência Beneficiada | G9: Endereço - Cidade
C10: =UPPER(VLOOKUP(B10,Prefixos!$A$1:$D$71,2,0)) -> #N/A | G10: =UPPER(VLOOKUP(B10,Prefixos!$A$1:$D$71,4,0)) -> #N/A
B11: Informações de Contato | G11: Matrícula / Nome - Funcionário Solicitante
B12: Responsável | G12: F2268209 - SISTEMA
B13: SERVIÇOS SOLICITADOS - Portal de Manutenção
B14: Descrição do serviço, Tipo, Quantidade, Local de Atendimento e Prioridade* | K14: Situação (Código**)
B15: Levantamento Preventivo | K15: 4
B16: * Preencher com as informações do Portal de Manutenção da DISEC. ** Preencher o campo situação com os códigos a seguir: 1. Serviço concluído sem pendências; 2. Serviço cancelado pelo demandante; 3. Atendimento Parcial; 4. Confecção de orçamento, para execução do serviço demanda autorização por parte do CESUP Suprimentos; 5. Não Atendido. 6. Mitigação de Riscos ou primeiro atendimento
B17: ORÇAMENTO DOS SERVIÇOS REALIZADOS
B18: ITEM | C18: DESCRIÇÃO | I18: QTD. | J18: UND. | K18: VALOR UNITÁRIO | M18: MAT UNIT | N18: MAO. UNIT | O18: MAT TOTAL | P18: MAO TOTAL | Q18: VALOR TOTAL
C19: =VLOOKUP(B19,'Valores Unitários'!$A$7:$J$516,2,0) -> #N/A | J19: =VLOOKUP(B19,'Valores Unitários'!$A$7:$J$516,4,0) -> #N/A | K19: =IFERROR(UPPER((VLOOKUP(B19,'Valores Unitários'!$A$7:$J$516,7,0))),"") | M19: =VLOOKUP(B19,'Valores Unitários'!$A$7:$J$516,5,0) -> #N/A | N19: =VLOOKUP(B19,'Valores Unitários'!$A$7:$J$516,6,0) -> #N/A | O19: =M19*I19 -> #N/A | P19: =N19*I19 -> #N/A | Q19: =K19*I19 -> #VALUE!
C20: =VLOOKUP(B20,'Valores Unitários'!$A$7:$J$516,2,0) -> #N/A | J20: =VLOOKUP(B20,'Valores Unitários'!$A$7:$J$516,4,0) -> #N/A | K20: =IFERROR(UPPER((VLOOKUP(B20,'Valores Unitários'!$A$7:$J$516,7,0))),"") | M20: =VLOOKUP(B20,'Valores Unitários'!$A$7:$J$516,5,0) -> #N/A | N20: =VLOOKUP(B20,'Valores Unitários'!$A$7:$J$516,6,0) -> #N/A | O20: =M20*I20 -> #N/A | P20: =N20*I20 -> #N/A | Q20: =K20*I20 -> #VALUE!
C21: =VLOOKUP(B21,'Valores Unitários'!$A$7:$J$516,2,0) -> #N/A | J21: =VLOOKUP(B21,'Valores Unitários'!$A$7:$J$516,4,0) -> #N/A | K21: =IFERROR(UPPER((VLOOKUP(B21,'Valores Unitários'!$A$7:$J$516,7,0))),"") | M21: =VLOOKUP(B21,'Valores Unitários'!$A$7:$J$516,5,0) -> #N/A | N21: =VLOOKUP(B21,'Valores Unitários'!$A$7:$J$516,6,0) -> #N/A | O21: =M21*I21 -> #N/A | P21: =N21*I21 -> #N/A | Q21: =K21*I21 -> #VALUE!
C22: =VLOOKUP(B22,'Valores Unitários'!$A$7:$J$516,2,0) -> #N/A | J22: =VLOOKUP(B22,'Valores Unitários'!$A$7:$J$516,4,0) -> #N/A | K22: =IFERROR(UPPER((VLOOKUP(B22,'Valores Unitários'!$A$7:$J$516,7,0))),"") | M22: =VLOOKUP(B22,'Valores Unitários'!$A$7:$J$516,5,0) -> #N/A | N22: =VLOOKUP(B22,'Valores Unitários'!$A$7:$J$516,6,0) -> #N/A | O22: =M22*I22 -> #N/A | P22: =N22*I22 -> #N/A | Q22: =K22*I22 -> #VALUE!
C23: =VLOOKUP(B23,'Valores Unitários'!$A$7:$J$516,2,0) -> #N/A | J23: =VLOOKUP(B23,'Valores Unitários'!$A$7:$J$516,4,0) -> #N/A | K23: =IFERROR(UPPER((VLOOKUP(B23,'Valores Unitários'!$A$7:$J$516,7,0))),"") | M23: =VLOOKUP(B23,'Valores Unitários'!$A$7:$J$516,5,0) -> #N/A | N23: =VLOOKUP(B23,'Valores Unitários'!$A$7:$J$516,6,0) -> #N/A | O23: =M23*I23 -> #N/A | P23: =N23*I23 -> #N/A | Q23: =K23*I23 -> #VALUE!
C24: =VLOOKUP(B24,'Valores Unitários'!$A$7:$J$516,2,0) -> #N/A | J24: =VLOOKUP(B24,'Valores Unitários'!$A$7:$J$516,4,0) -> #N/A | K24: =IFERROR(UPPER((VLOOKUP(B24,'Valores Unitários'!$A$7:$J$516,7,0))),"") | M24: =VLOOKUP(B24,'Valores Unitários'!$A$7:$J$516,5,0) -> #N/A | N24: =VLOOKUP(B24,'Valores Unitários'!$A$7:$J$516,6,0) -> #N/A | O24: =M24*I24 -> #N/A | P24: =N24*I24 -> #N/A | Q24: =K24*I24 -> #VALUE!
C25: =VLOOKUP(B25,'Valores Unitários'!$A$7:$J$516,2,0) -> #N/A | J25: =VLOOKUP(B25,'Valores Unitários'!$A$7:$J$516,4,0) -> #N/A | K25: =IFERROR(UPPER((VLOOKUP(B25,'Valores Unitários'!$A$7:$J$516,7,0))),"") | M25: =VLOOKUP(B25,'Valores Unitários'!$A$7:$J$516,5,0) -> #N/A | N25: =VLOOKUP(B25,'Valores Unitários'!$A$7:$J$516,6,0) -> #N/A | O25: =M25*I25 -> #N/A | P25: =N25*I25 -> #N/A | Q25: =K25*I25 -> #VALUE!
C26: =VLOOKUP(B26,'Valores Unitários'!$A$7:$J$516,2,0) -> #N/A | J26: =VLOOKUP(B26,'Valores Unitários'!$A$7:$J$516,4,0) -> #N/A | K26: =IFERROR(UPPER((VLOOKUP(B26,'Valores Unitários'!$A$7:$J$516,7,0))),"") | M26: =VLOOKUP(B26,'Valores Unitários'!$A$7:$J$516,5,0) -> #N/A | N26: =VLOOKUP(B26,'Valores Unitários'!$A$7:$J$516,6,0) -> #N/A | O26: =M26*I26 -> #N/A | P26: =N26*I26 -> #N/A | Q26: =K26*I26 -> #VALUE!
C27: =VLOOKUP(B27,'Valores Unitários'!$A$7:$J$516,2,0) -> #N/A | J27: =VLOOKUP(B27,'Valores Unitários'!$A$7:$J$516,4,0) -> #N/A | K27: =IFERROR(UPPER((VLOOKUP(B27,'Valores Unitários'!$A$7:$J$516,7,0))),"") | M27: =VLOOKUP(B27,'Valores Unitários'!$A$7:$J$516,5,0) -> #N/A | N27: =VLOOKUP(B27,'Valores Unitários'!$A$7:$J$516,6,0) -> #N/A | O27: =M27*I27 -> #N/A | P27: =N27*I27 -> #N/A | Q27: =K27*I27 -> #VALUE!
C28: =VLOOKUP(B28,'Valores Unitários'!$A$7:$J$516,2,0) -> #N/A | J28: =VLOOKUP(B28,'Valores Unitários'!$A$7:$J$516,4,0) -> #N/A | K28: =IFERROR(UPPER((VLOOKUP(B28,'Valores Unitários'!$A$7:$J$516,7,0))),"") | M28: =VLOOKUP(B28,'Valores Unitários'!$A$7:$J$516,5,0) -> #N/A | N28: =VLOOKUP(B28,'Valores Unitários'!$A$7:$J$516,6,0) -> #N/A | O28: =M28*I28 -> #N/A | P28: =N28*I28 -> #N/A | Q28: =K28*I28 -> #VALUE!
C29: =VLOOKUP(B29,'Valores Unitários'!$A$7:$J$516,2,0) -> #N/A | J29: =VLOOKUP(B29,'Valores Unitários'!$A$7:$J$516,4,0) -> #N/A | K29: =IFERROR(UPPER((VLOOKUP(B29,'Valores Unitários'!$A$7:$J$516,7,0))),"") | M29: =VLOOKUP(B29,'Valores Unitários'!$A$7:$J$516,5,0) -> #N/A | N29: =VLOOKUP(B29,'Valores Unitários'!$A$7:$J$516,6,0) -> #N/A | O29: =M29*I29 -> #N/A | P29: =N29*I29 -> #N/A | Q29: =K29*I29 -> #VALUE!
C30: =VLOOKUP(B30,'Valores Unitários'!$A$7:$J$516,2,0) -> #N/A | J30: =VLOOKUP(B30,'Valores Unitários'!$A$7:$J$516,4,0) -> #N/A | K30: =IFERROR(UPPER((VLOOKUP(B30,'Valores Unitários'!$A$7:$J$516,7,0))),"") | M30: =VLOOKUP(B30,'Valores Unitários'!$A$7:$J$516,5,0) -> #N/A | N30: =VLOOKUP(B30,'Valores Unitários'!$A$7:$J$516,6,0) -> #N/A | O30: =M30*I30 -> #N/A | P30: =N30*I30 -> #N/A | Q30: =K30*I30 -> #VALUE!
... C32: =VLOOKUP(B32,'Valores Unitários'!$A$7:$J$516,2,0) -> #N/A | J32: =VLOOKUP(B32,'Valores Unitários'!$A$7:$J$516,4,0) -> #N/A | K32: =IFERROR(UPPER((VLOOKUP(B32,'Valores Unitários'!$A$7:$J$516,7,0))),"") | M32: =VLOOKUP(B32,'Valores Unitários'!$A$7:$J$516,5,0) -> #N/A | N32: =VLOOKUP(B32,'Valores Unitários'!$A$7:$J$516,6,0) -> #N/A | O32: =M32*I32 -> #N/A | P32: =N32*I32 -> #N/A | Q32: =K32*I32 -> #VALUE!
B33: RESUMO DO ORÇAMENTO DOS SERVIÇOS SOLICITADOS
B34: Data / Hora Conclusão | G34: Valor de Materiais + Mão de Obra | J34: Valor Total
B35: =F49 -> 0 | G35: =SUM(O19:O32) -> #N/A | H35: + | I35: =SUM(P19:P32) -> #N/A | J35: =I35+G35 -> #N/A
B36: Observações
B41: ___________________________________________________ | H41: ___________________________________________________________________________________
B43: VISTO REPRESENTANTE DA EMPRESA CONTRATADA | H43: CARIMBO E VISTO DA DEPENDÊNCIA
B45: TÉCNICO | J45: ENGENHEIRO
J46: ______________________________________
B47: AUXILIAR
B49: Data e hora | E49: Data e hora | J49: RESPONSÁVEL TÉCNICO
B50: CHEGADA | E50: SAÍDA | J50: CARIMBO - NÚMERO / VISTO DO CREA
B51: O RAT deverá ser emitido em 3 vias sendo, a 1º para a dependência beneficiada, a 2º para a empresa contratada e a 3º CESUP Suprimentos

Sheet Conformidade
B2: RAT - RELATÓRIO DE ATENDIMENTO
B3: Conformidade do atendimento no local dos serviços
B4: Número da solicitação | D4: Data/hora Abertura | G4: Contrato de Manutenção | J4: Contratada
B5: =RAT!B5 -> 0 | D5: =RAT!D5 -> 0 | G5: 2024.7421.2057 | J5: MAFFENG ENGENHARIA E MANUTENÇÃO
B6: Sinistro | D6: Prazo de atendimento | G6: Tipo de Manutenção | J6: Nível de Ocorrência
B7: (Sim/Não) | G7: (Preventiva/Corretiva) | J7: (Emergencial/Urgente/Normal)
B8: =RAT!B8 -> Não | D8: =RAT!D8 -> 0 | G8: =RAT!G8 -> Preventiva | J8: =RAT!J8 -> Normal
B9: Prefixo / SB - Dependência Beneficiada | G9: Endereço - Cidade
B10: =RAT!B10 -> 0 | C10: =RAT!C10 -> #N/A | G10: =RAT!G10 -> #N/A
B11: Informações de Contato | G11: Matrícula / Nome - Funcionário Solicitante
B12: =RAT!B12 -> Responsável | G12: =RAT!G12 -> F2268209 - SISTEMA
B13: MÓDULO DEMANDANTE / BENEFICIÁRIO / CONTRATANTE PREENCHIMENTO PELO PREPOSTO DO BANCO DO BRASIL
B14: Matrícula | D14: Nome Funcionário Preposto
B16: Questionário | J16: Atendeu | L16: Não Atendeu
B17: Prazo de Atendimento
B18: Qualidade dos serviços executados
B19: Discrição e Presteza dos funcionários
B20: RESUMO DO ORÇAMENTO DOS SERVIÇOS EXECUTADOS
B21: Data / Hora Conclusão | G21: Valor de Materiais + Mão de Obra | J21: Valor Total
B22: =RAT!F49 -> 0 | G22: =RAT!G35 -> #N/A | H22: + | I22: =RAT!I35 -> #N/A | J22: =RAT!J35 -> #N/A
B23: Observações
B25: Sr. ADMINISTRADOR PREDIAL, antes de assinar o RAT (Relatório de Atendimento), deve-se observar que:
B26: 1. A Situação (código, em "Serviços Solicitados") foi preenchida adequadamente para cada serviço solicitado e que os serviços
B27: registrados como concluídos, ficaram sem pendências;
B28: 2. Os serviços solicitados, porém não executados ou executados parcialmente, tiveram um valor descontado no campo "Resumo do Orçamento dos
B29: Serviços Executados".
B30: 3. O documento deverá ser totalmente preenchido, em todos os campos e sem rasuras. Inutilizar os espaços em branco;
B31: 4. A segunda via do RAT deverá ficar arquivada na dependência beneficiária para consultas futuras;
B32: 5. Deve-se registrar no Portal de Manutenção da DISEC as informações contidas no RAT.
B33: Dúvidas quanto aos itens, quantitativos e valores aplicados aos serviços, deverão ser sanadas com a CONTRATADA durante o atendimento. Caso não
B34: ocorra o esclarecimento, consultar o CESUP SUPRIMENTOS.
B35: Lembramos que o ADMINISTRADOR PREDIAL é o responsável pela fiscalização dos serviços executados na dependência e que a
... B37: dos serviços
C39: ________________________________________________ | I39: ___________________________________________________________________________________
C40: VISTO REPRESENTANTE DA EMPRESA CONTRATADA | I40: CARIMBO E VISTO DA DEPENDÊNCIA
B42: Parecer do Responsável Técnico / Contratada | J42: ENGENHEIRO
J48: CARIMBO - NÚMERO / VISTO DO CREA
B49: O RAT deverá ser emitido em 3 vias, sendo: a 1° Depêndencia Beneficiária, 2° Empresa Contratada, e em 3° CESUP Suprimentos

Sheet Valores Unitários
B1: A interessada deverá prrencher os campos em amarelo abaixo.
C3: CONSERVAÇÃO PREDIAL | M3: Informar nos campos em amarelo abaixo o desconto para MA e MO. Poderá ser informado desconto diferente ou igual para MA e MO de forma a ajustar o desconto global ao desconto ofertado na licitação. O campo em verde, após o preenchimento do MA, MO e BDI (em sua respectiva aba), deverá refletir o valor de desconto ofertado na Licitação. O valor efetivo de desconto de MA e MO considerando BDI aparecerá nos campos em Azul.
B4: PROPONENTE : | G4: LOTE: | H4: 04 | M4: Material sem BDI | N4: Mão de obra sem BDI
B5: MAFFENG ENGENHARIA E MANUTENCAO EIRELI | C5: CNPJ: | D5: 33.624.704/0001-94 | I5: DESCONTO: | J5: =N7 -> 0.31006343 | M5: 0.3601 | N5: 0.3601 | V5: Não mexer nos dados abaixo. Dados Sem BDI. | AB5: Não mexer nos dados abaixo. Dados com BDI. | AH5: Descontos Calculados
A7: ITEM | C7: QTDE | D7: UN. | E7: UNITÁRIO MATERIAL | F7: UNITÁRIO MÃO DE OBRA | G7: TOTAL UNITÁRIO DO ITEM | H7: TOTAL MATERIAL ROTEIRO | I7: TOTAL MÃO DE OBRA ROTEIRO | J7: TOTAL GERAL ROTEIRO | M7: Desconto Global Calculado com BDI | N7: =1-(J516/AF516) -> 0.31006343 | V7: QTDE | W7: UN. | X7: UNITÁRIO MATERIAL Referência | Y7: UNITÁRIO MÃO DE OBRA Referência | Z7: TOTAL UNITÁRIO DO ITEM Referência | AB7: QTDE | AC7: UN. | AD7: UNITÁRIO MATERIAL Referência | AE7: UNITÁRIO MÃO DE OBRA Referência | AF7: TOTAL UNITÁRIO DO ITEM Referência | AH7: UNITÁRIO MATERIAL Referência | AI7: UNITÁRIO MÃO DE OBRA Referência | AJ7: TOTAL UNITÁRIO DO ITEM Referência
A8: 1 | B8: PRELIMINARES | H8: =SUM(H9:H15) -> 534671.56 | I8: =SUM(I9:I15) -> 324422.94 | J8: =SUM(J9:J15) -> 859094.5 | M8: O valor do campo em verde deverá ser igual ao da proposta apresentada.
A9: 1.1 | B9: Chamado | C9: =V9 -> 1272 | D9: =W9 -> un | E9: 0 | F9: 92.13 | G9: =F9+E9 -> 92.13 | H9: =C9*E9 -> 0 | I9: =C9*F9 -> 117189.36 | J9: =SUM(E9:F9)*C9 -> 117189.36 | V9: 1272 | W9: un | X9: 0 | Y9: 91.79 | Z9: =SUM(X9:Y9) -> 91.79 | AB9: 1272 | AC9: un | AD9: 0 | AE9: 118.24 | AF9: =SUM(AD9:AE9) -> 118.24 | AH9: =IF(E9=0,0,(E9/AD9)-1) -> 0 | AI9: =IF(F9=0,0,(F9/AE9)-1) -> -0.22082206 | AJ9: =IF(G9=0,0,(G9/AF9)-1) -> -0.22082206
A10: 1.2 | B10: Deslocamento | C10: =V10 -> 159470 | D10: =W10 -> km | E10: 1.58 | F10: 0.83 | G10: =F10+E10 -> 2.41 | H10: =C10*E10 -> 251962.6 | I10: =C10*F10 -> 132360.1 | J10: =SUM(E10:F10)*C10 -> 384322.7 | V10: 159470 | W10: km | X10: 1.88 | Y10: 0.82 | Z10: =SUM(X10:Y10) -> 2.7 | AB10: 159470 | AC10: km | AD10: 2.42 | AE10: 1.06 | AF10: =SUM(AD10:AE10) -> 3.48 | AH10: =IF(E10=0,0,(E10/AD10)-1) -> -0.34710744 | AI10: =IF(F10=0,0,(F10/AE10)-1) -> -0.21698113 | AJ10: =IF(G10=0,0,(G10/AF10)-1) -> -0.30747126
A11: 1.3 | B11: Revisão de instalações | C11: =V11 -> 160 | D11: =W11 -> un | E11: 61.47 | F11: 364.58 | G11: =F11+E11 -> 426.05 | H11: =C11*E11 -> 9835.2 | I11: =C11*F11 -> 58332.8 | J11: =SUM(E11:F11)*C11 -> 68168 | V11: 160 | W11: un | X11: 88.78 | Y11: 377.3 | Z11: =SUM(X11:Y11) -> 466.08 | AB11: 160 | AC11: un | AD11: 114.37 | AE11: 486.04 | AF11: =SUM(AD11:AE11) -> 600.41 | AH11: =IF(E11=0,0,(E11/AD11)-1) -> -0.46253388 | AI11: =IF(F11=0,0,(F11/AE11)-1) -> -0.24989713 | AJ11: =IF(G11=0,0,(G11/AF11)-1) -> -0.29040156
A12: 1.4 | B12: Acompanhamento técnico em Segurança do Trabalho | C12: =V12 -> 69 | D12: =W12 -> un | E12: 0 | F12: 230.37 | G12: =F12+E12 -> 230.37 | H12: =C12*E12 -> 0 | I12: =C12*F12 -> 15895.53 | J12: =SUM(E12:F12)*C12 -> 15895.53 | V12: 69 | W12: un | X12: 0 | Y12: 274.56 | Z12: =SUM(X12:Y12) -> 274.56 | AB12: 69 | AC12: un | AD12: 0 | AE12: 353.69 | AF12: =SUM(AD12:AE12) -> 353.69 | AH12: =IF(E12=0,0,(E12/AD12)-1) -> 0 | AI12: =IF(F12=0,0,(F12/AE12)-1) -> -0.34866691 | AJ12: =IF(G12=0,0,(G12/AF12)-1) -> -0.34866691
A13: 1.5 | B13: Chamado Preventivo | C13: =V13 -> 160 | D13: =W13 -> un | E13: 1705.44 | F13: 0 | G13: =F13+E13 -> 1705.44 | H13: =C13*E13 -> 272870.4 | I13: =C13*F13 -> 0 | J13: =SUM(E13:F13)*C13 -> 272870.4 | V13: 160 | W13: un | X13: 2145.26 | Y13: 0 | Z13: =SUM(X13:Y13) -> 2145.26 | AB13: 160 | AC13: un | AD13: 2763.52 | AE13: 0 | AF13: =SUM(AD13:AE13) -> 2763.52 | AH13: =IF(E13=0,0,(E13/AD13)-1) -> -0.38287402 | AI13: =IF(F13=0,0,(F13/AE13)-1) -> 0 | AJ13: =IF(G13=0,0,(G13/AF13)-1) -> -0.38287402
A14: 1.6 | B14: Deslocamento Fluvial | C14: =V14 -> 1 | D14: =W14 -> Km | E14: 0.68 | F14: 1.65 | G14: =F14+E14 -> 2.33 | H14: =C14*E14 -> 0.68 | I14: =C14*F14 -> 1.65 | J14: =SUM(E14:F14)*C14 -> 2.33 | M14: Desconto Calculado Material Efetivo | N14: =IF(M5=0,0,ROUND(AH519,4)) -> -0.3492 | V14: 1 | W14: Km | X14: 0.78 | Y14: 1.67 | Z14: =SUM(X14:Y14) -> 2.45 | AB14: 1 | AC14: Km | AD14: 1 | AE14: 2.15 | AF14: =SUM(AD14:AE14) -> 3.15 | AH14: =IF(E14=0,0,(E14/AD14)-1) -> -0.32 | AI14: =IF(F14=0,0,(F14/AE14)-1) -> -0.23255814 | AJ14: =IF(G14=0,0,(G14/AF14)-1) -> -0.26031746
A15: 1.7 | B15: Laudo técncio fotográfico - Elementos de Sinalização - Padrão BB | C15: =V15 -> 1 | D15: =W15 -> UN | E15: 2.68 | F15: 643.5 | G15: =F15+E15 -> 646.18 | H15: =C15*E15 -> 2.68 | I15: =C15*F15 -> 643.5 | J15: =SUM(E15:F15)*C15 -> 646.18 | M15: Desconto Calculado Mão de Obra Efetivo | N15: =IF(N5=0,0,ROUND(AI519,4)) -> -0.263 | V15: 1 | W15: UN | X15: 92.28 | Y15: 646.9 | Z15: =SUM(X15:Y15) -> 739.18 | AB15: 1 | AC15: UN | AD15: 118.88 | AE15: 833.34 | AF15: =SUM(AD15:AE15) -> 952.22 | AH15: =IF(E15=0,0,(E15/AD15)-1) -> -0.97745626 | AI15: =IF(F15=0,0,(F15/AE15)-1) -> -0.22780618 | AJ15: =IF(G15=0,0,(G15/AF15)-1) -> -0.32139632
A16: 2 | B16: IMPLANTAÇÃO / ADMINISTRAÇÃO | E16: 0 | F16: 0 | H16: =SUM(H17:H52) -> 249041.51 | I16: =SUM(I17:I52) -> 345856.34 | J16: =SUM(J17:J52) -> 594897.85 | M16: Os valores acima consideram o valor informado na aba BDI. | AH16: =IF(E16=0,0,(E16/AD16)-1) -> 0 | AI16: =IF(F16=0,0,(F16/AE16)-1) -> 0 | AJ16: =IF(G16=0,0,(G16/AF16)-1) -> 0
A17: 2.1 | B17: Demolição manual de concreto simples | C17: =V17 -> 12 | D17: =W17 -> m³ | E17: 0 | F17: 252.25 | G17: =F17+E17 -> 252.25 | H17: =C17*E17 -> 0 | I17: =C17*F17 -> 3027 | J17: =SUM(E17:F17)*C17 -> 3027 | V17: 12 | W17: m³ | X17: 0 | Y17: 267.23 | Z17: =SUM(X17:Y17) -> 267.23 | AB17: 12 | AC17: m³ | AD17: 0 | AE17: 344.25 | AF17: =SUM(AD17:AE17) -> 344.25 | AH17: =IF(E17=0,0,(E17/AD17)-1) -> 0 | AI17: =IF(F17=0,0,(F17/AE17)-1) -> -0.26724764 | AJ17: =IF(G17=0,0,(G17/AF17)-1) -> -0.26724764
A18: 2.2 | B18: Demolição manual de alvenaria de elevação ou elemento vazado, incluindo revestimento | C18: =V18 -> 41 | D18: =W18 -> m³ | E18: 0 | F18: 58.21 | G18: =F18+E18 -> 58.21 | H18: =C18*E18 -> 0 | I18: =C18*F18 -> 2386.61 | J18: =SUM(E18:F18)*C18 -> 2386.61 | M18: A interessada pode alterar o BDI na respectiva aba da planilha eletrônica. A alteração do BDI afeta o desconto calculado efetivo de material e de mão de obra. O valor do BDI deverá ser igual ao da proposta a ser apresentada. | V18: 41 | W18: m³ | X18: 0 | Y18: 61.67 | Z18: =SUM(X18:Y18) -> 61.67 | AB18: 41 | AC18: m³ | AD18: 0 | AE18: 79.44 | AF18: =SUM(AD18:AE18) -> 79.44 | AH18: =IF(E18=0,0,(E18/AD18)-1) -> 0 | AI18: =IF(F18=0,0,(F18/AE18)-1) -> -0.26724572 | AJ18: =IF(G18=0,0,(G18/AF18)-1) -> -0.26724572
A19: 2.3 | B19: Demolição manual de revestimento em massa de parede ou teto ou Dry-Wall | C19: =V19 -> 204 | D19: =W19 -> m³ | E19: 0 | F19: 6.41 | G19: =F19+E19 -> 6.41 | H19: =C19*E19 -> 0 | I19: =C19*F19 -> 1307.64 | J19: =SUM(E19:F19)*C19 -> 1307.64 | V19: 204 | W19: m³ | X19: 0 | Y19: 6.89 | Z19: =SUM(X19:Y19) -> 6.89 | AB19: 204 | AC19: m³ | AD19: 0 | AE19: 8.88 | AF19: =SUM(AD19:AE19) -> 8.88 | AH19: =IF(E19=0,0,(E19/AD19)-1) -> 0 | AI19: =IF(F19=0,0,(F19/AE19)-1) -> -0.27815315 | AJ19: =IF(G19=0,0,(G19/AF19)-1) -> -0.27815315
A20: 2.4 | B20: Demolição de pisos em geral (ladrilho hidráulico, camada de enchimento, cerâmica, porcelanato, mármore, granito, pedra e madeira) - Manual | C20: =V20 -> 62 | D20: =W20 -> m² | E20: 0 | F20: 27.16 | G20: =F20+E20 -> 27.16 | H20: =C20*E20 -> 0 | I20: =C20*F20 -> 1683.92 | J20: =SUM(E20:F20)*C20 -> 1683.92 | V20: 62 | W20: m² | X20: 0 | Y20: 28.78 | Z20: =SUM(X20:Y20) -> 28.78 | AB20: 62 | AC20: m² | AD20: 0 | AE20: 37.07 | AF20: =SUM(AD20:AE20) -> 37.07 | AH20: =IF(E20=0,0,(E20/AD20)-1) -> 0 | AI20: =IF(F20=0,0,(F20/AE20)-1) -> -0.26733207 | AJ20: =IF(G20=0,0,(G20/AF20)-1) -> -0.26733207
A21: 2.5 | B21: Demolição de pisos em geral (ladrilho hidráulico, camada de enchimento, cerâmica, porcelanato, mármore, granito, pedra e madeira) - Mecanizado | C21: =V21 -> 128 | D21: =W21 -> m² | E21: 22.28 | F21: 13.58 | G21: =F21+E21 -> 35.86 | H21: =C21*E21 -> 2851.84 | I21: =C21*F21 -> 1738.24 | J21: =SUM(E21:F21)*C21 -> 4590.08 | V21: 128 | W21: m² | X21: 26.35 | Y21: 14.39 | Z21: =SUM(X21:Y21) -> 40.74 | AB21: 128 | AC21: m² | AD21: 33.94 | AE21: 18.54 | AF21: =SUM(AD21:AE21) -> 52.48 | AH21: =IF(E21=0,0,(E21/AD21)-1) -> -0.34354744 | AI21: =IF(F21=0,0,(F21/AE21)-1) -> -0.26752967 | AJ21: =IF(G21=0,0,(G21/AF21)-1) -> -0.31669207
A22: 2.6 | B22: Demolição de pavimentação com pré-moldado de concreto ou intertravado | C22: =V22 -> 1 | D22: =W22 -> m² | E22: 0 | F22: 13.58 | G22: =F22+E22 -> 13.58 | H22: =C22*E22 -> 0 | I22: =C22*F22 -> 13.58 | J22: =SUM(E22:F22)*C22 -> 13.58 | V22: 1 | W22: m² | X22: 0 | Y22: 14.39 | Z22: =SUM(X22:Y22) -> 14.39 | AB22: 1 | AC22: m² | AD22: 0 | AE22: 18.54 | AF22: =SUM(AD22:AE22) -> 18.54 | AH22: =IF(E22=0,0,(E22/AD22)-1) -> 0 | AI22: =IF(F22=0,0,(F22/AE22)-1) -> -0.26752967 | AJ22: =IF(G22=0,0,(G22/AF22)-1) -> -0.26752967
A23: 2.7 | B23: Demolição de piso cimentado sobre lastro de concreto | C23: =V23 -> 1 | D23: =W23 -> m² | E23: 0 | F23: 25.22 | G23: =F23+E23 -> 25.22 | H23: =C23*E23 -> 0 | I23: =C23*F23 -> 25.22 | J23: =SUM(E23:F23)*C23 -> 25.22 | V23: 1 | W23: m² | X23: 0 | Y23: 26.72 | Z23: =SUM(X23:Y23) -> 26.72 | AB23: 1 | AC23: m² | AD23: 0 | AE23: 34.42 | AF23: =SUM(AD23:AE23) -> 34.42 | AH23: =IF(E23=0,0,(E23/AD23)-1) -> 0 | AI23: =IF(F23=0,0,(F23/AE23)-1) -> -0.26728646 | AJ23: =IF(G23=0,0,(G23/AF23)-1) -> -0.26728646
A24: 2.8 | B24: Demolição manual de forro, inclusive sistema de fixação/tarugamento | C24: =V24 -> 1500 | D24: =W24 -> m² | E24: 0 | F24: 7.76 | G24: =F24+E24 -> 7.76 | H24: =C24*E24 -> 0 | I24: =C24*F24 -> 11640 | J24: =SUM(E24:F24)*C24 -> 11640 | M24: A interessada pode utilizar modelo próprio de planilha para cálculo,entretanto,a planilha final a ser apresentada juntamente com a proposta, deverá ter a mesma formatação do orçamento estimado que compõe a licitação. | V24: 1500 | W24: m² | X24: 0 | Y24: 8.22 | Z24: =SUM(X24:Y24) -> 8.22 | AB24: 1500 | AC24: m² | AD24: 0 | AE24: 10.59 | AF24: =SUM(AD24:AE24) -> 10.59 | AH24: =IF(E24=0,0,(E24/AD24)-1) -> 0 | AI24: =IF(F24=0,0,(F24/AE24)-1) -> -0.26723324 | AJ24: =IF(G24=0,0,(G24/AF24)-1) -> -0.26723324
A25: 2.9 | B25: Demolição de contrapiso/argamassa regularizante, isolante ou protetora | C25: =V25 -> 9 | D25: =W25 -> m² | E25: 0 | F25: 9.7 | G25: =F25+E25 -> 9.7 | H25: =C25*E25 -> 0 | I25: =C25*F25 -> 87.3 | J25: =SUM(E25:F25)*C25 -> 87.3 | V25: 9 | W25: m² | X25: 0 | Y25: 10.28 | Z25: =SUM(X25:Y25) -> 10.28 | AB25: 9 | AC25: m² | AD25: 0 | AE25: 13.24 | AF25: =SUM(AD25:AE25) -> 13.24 | AH25: =IF(E25=0,0,(E25/AD25)-1) -> 0 | AI25: =IF(F25=0,0,(F25/AE25)-1) -> -0.2673716 | AJ25: =IF(G25=0,0,(G25/AF25)-1) -> -0.2673716
A26: 2.10 | B26: Demolição de estrutura em madeira para telhado | C26: =V26 -> 1 | D26: =W26 -> m² | E26: 0 | F26: 27.27 | G26: =F26+E26 -> 27.27 | H26: =C26*E26 -> 0 | I26: =C26*F26 -> 27.27 | J26: =SUM(E26:F26)*C26 -> 27.27 | V26: 1 | W26: m² | X26: 0 | Y26: 28.94 | Z26: =SUM(X26:Y26) -> 28.94 | AB26: 1 | AC26: m² | AD26: 0 | AE26: 37.28 | AF26: =SUM(AD26:AE26) -> 37.28 | AH26: =IF(E26=0,0,(E26/AD26)-1) -> 0 | AI26: =IF(F26=0,0,(F26/AE26)-1) -> -0.26850858 | AJ26: =IF(G26=0,0,(G26/AF26)-1) -> -0.26850858
A27: 2.11 | B27: Retirada de cumeeira, espigão, rufo, calha ou chapim, perfil qualquer | C27: =V27 -> 357 | D27: =W27 -> m | E27: 0 | F27: 13.47 | G27: =F27+E27 -> 13.47 | H27: =C27*E27 -> 0 | I27: =C27*F27 -> 4808.79 | J27: =SUM(E27:F27)*C27 -> 4808.79 | V27: 357 | W27: m | X27: 0 | Y27: 14.21 | Z27: =SUM(X27:Y27) -> 14.21 | AB27: 357 | AC27: m | AD27: 0 | AE27: 18.31 | AF27: =SUM(AD27:AE27) -> 18.31 | AH27: =IF(E27=0,0,(E27/AD27)-1) -> 0 | AI27: =IF(F27=0,0,(F27/AE27)-1) -> -0.26433643 | AJ27: =IF(G27=0,0,(G27/AF27)-1) -> -0.26433643
A28: 2.12 | B28: Retirada de piso tátil com limpeza | C28: =V28 -> 6000 | D28: =W28 -> m² | E28: 14.97 | F28: 21.9 | G28: =F28+E28 -> 36.87 | H28: =C28*E28 -> 89820 | I28: =C28*F28 -> 131400 | J28: =SUM(E28:F28)*C28 -> 221220 | V28: 6000 | W28: m² | X28: 17.69 | Y28: 23.05 | Z28: =SUM(X28:Y28) -> 40.74 | AB28: 6000 | AC28: m² | AD28: 22.79 | AE28: 29.69 | AF28: =SUM(AD28:AE28) -> 52.48 | AH28: =IF(E28=0,0,(E28/AD28)-1) -> -0.34313295 | AI28: =IF(F28=0,0,(F28/AE28)-1) -> -0.26237791 | AJ28: =IF(G28=0,0,(G28/AF28)-1) -> -0.29744665
A29: 2.13 | B29: Remoção de revestimento de piso de carpete ou manta vinílica | C29: =V29 -> 3375 | D29: =W29 -> m² | E29: 14.97 | F29: 11.27 | G29: =F29+E29 -> 26.24 | H29: =C29*E29 -> 50523.75 | I29: =C29*F29 -> 38036.25 | J29: =SUM(E29:F29)*C29 -> 88560 | V29: 3375 | W29: m² | X29: 17.69 | Y29: 11.84 | Z29: =SUM(X29:Y29) -> 29.53 | AB29: 3375 | AC29: m² | AD29: 22.79 | AE29: 15.25 | AF29: =SUM(AD29:AE29) -> 38.04 | AH29: =IF(E29=0,0,(E29/AD29)-1) -> -0.34313295 | AI29: =IF(F29=0,0,(F29/AE29)-1) -> -0.26098361 | AJ29: =IF(G29=0,0,(G29/AF29)-1) -> -0.31019979
A30: 2.14 | B30: Ajuste de Piso Elevado (remoção e recolocação de revestimentos e placas do piso inclusive) | C30: =V30 -> 661 | D30: =W30 -> m² | E30: 8.58 | F30: 58.16 | G30: =F30+E30 -> 66.74 | H30: =C30*E30 -> 5671.38 | I30: =C30*F30 -> 38443.76 | J30: =SUM(E30:F30)*C30 -> 44115.14 | V30: 661 | W30: m² | X30: 9.34 | Y30: 61.12 | Z30: =SUM(X30:Y30) -> 70.46 | AB30: 661 | AC30: m² | AD30: 12.03 | AE30: 78.73 | AF30: =SUM(AD30:AE30) -> 90.76 | AH30: =IF(E30=0,0,(E30/AD30)-1) -> -0.28678304 | AI30: =IF(F30=0,0,(F30/AE30)-1) -> -0.2612727 | AJ30: =IF(G30=0,0,(G30/AF30)-1) -> -0.26465403
A31: 2.15 | B31: Retirada de piso elevado, inclusive estrutura de sustentação | C31: =V31 -> 724 | D31: =W31 -> m² | E31: 0 | F31: 25.18 | G31: =F31+E31 -> 25.18 | H31: =C31*E31 -> 0 | I31: =C31*F31 -> 18230.32 | J31: =SUM(E31:F31)*C31 -> 18230.32 | V31: 724 | W31: m² | X31: 0 | Y31: 26.71 | Z31: =SUM(X31:Y31) -> 26.71 | AB31: 724 | AC31: m² | AD31: 0 | AE31: 34.41 | AF31: =SUM(AD31:AE31) -> 34.41 | AH31: =IF(E31=0,0,(E31/AD31)-1) -> 0 | AI31: =IF(F31=0,0,(F31/AE31)-1) -> -0.26823598 | AJ31: =IF(G31=0,0,(G31/AF31)-1) -> -0.26823598
A32: 2.16 | B32: Reinstalação de piso elevado proveniente de reaproveitamento, incluso material | C32: =V32 -> 1 | D32: =W32 -> m² | E32: 1.43 | F32: 62.97 | G32: =F32+E32 -> 64.4 | H32: =C32*E32 -> 1.43 | I32: =C32*F32 -> 62.97 | J32: =SUM(E32:F32)*C32 -> 64.4 | V32: 1 | W32: m² | X32: 1.62 | Y32: 66.17 | Z32: =SUM(X32:Y32) -> 67.79 | AB32: 1 | AC32: m² | AD32: 2.09 | AE32: 85.24 | AF32: =SUM(AD32:AE32) -> 87.33 | AH32: =IF(E32=0,0,(E32/AD32)-1) -> -0.31578947 | AI32: =IF(F32=0,0,(F32/AE32)-1) -> -0.26126232 | AJ32: =IF(G32=0,0,(G32/AF32)-1) -> -0.26256727
A33: 2.17 | B33: Retirada ou recolocação de vidro | C33: =V33 -> 415 | D33: =W33 -> m² | E33: 13.29 | F33: 14.36 | G33: =F33+E33 -> 27.65 | H33: =C33*E33 -> 5515.35 | I33: =C33*F33 -> 5959.4 | J33: =SUM(E33:F33)*C33 -> 11474.75 | V33: 415 | W33: m² | X33: 12.9 | Y33: 15.15 | Z33: =SUM(X33:Y33) -> 28.05 | AB33: 415 | AC33: m² | AD33: 16.62 | AE33: 19.52 | AF33: =SUM(AD33:AE33) -> 36.14 | AH33: =IF(E33=0,0,(E33/AD33)-1) -> -0.20036101 | AI33: =IF(F33=0,0,(F33/AE33)-1) -> -0.26434426 | AJ33: =IF(G33=0,0,(G33/AF33)-1) -> -0.23491976
A34: 2.18 | B34: Remoção de entulho com caçamba metálica, inclusive limpeza, transporte, carga, descarga e descarte conforme legislação ambiental - Material de descarte (alvenaria, estruturas metálicas, madeiramento, revestimentos cerâmicos, gesso, dry-wall, entre outros) | C34: =V34 -> 30 | D34: =W34 -> m³ | E34: 48.55 | F34: 11.94 | G34: =F34+E34 -> 60.49 | H34: =C34*E34 -> 1456.5 | I34: =C34*F34 -> 358.2 | J34: =SUM(E34:F34)*C34 -> 1814.7 | V34: 30 | W34: m³ | X34: 61.2 | Y34: 12.68 | Z34: =SUM(X34:Y34) -> 73.88 | AB34: 30 | AC34: m³ | AD34: 78.84 | AE34: 16.33 | AF34: =SUM(AD34:AE34) -> 95.17 | AH34: =IF(E34=0,0,(E34/AD34)-1) -> -0.38419584 | AI34: =IF(F34=0,0,(F34/AE34)-1) -> -0.26883037 | AJ34: =IF(G34=0,0,(G34/AF34)-1) -> -0.36440055
A35: 2.19 | B35: Remoção / Remanejamento de placa aérea | C35: =V35 -> 126 | D35: =W35 -> un | E35: 5.61 | F35: 37.73 | G35: =F35+E35 -> 43.34 | H35: =C35*E35 -> 706.86 | I35: =C35*F35 -> 4753.98 | J35: =SUM(E35:F35)*C35 -> 5460.84 | V35: 126 | W35: un | X35: 5.84 | Y35: 40 | Z35: =SUM(X35:Y35) -> 45.84 | AB35: 126 | AC35: un | AD35: 7.52 | AE35: 51.53 | AF35: =SUM(AD35:AE35) -> 59.05 | AH35: =IF(E35=0,0,(E35/AD35)-1) -> -0.25398936 | AI35: =IF(F35=0,0,(F35/AE35)-1) -> -0.26780516 | AJ35: =IF(G35=0,0,(G35/AF35)-1) -> -0.26604572
A36: 2.20 | B36: Andaime tubular fachadeiro | C36: =V36 -> 1822 | D36: =W36 -> m²/mês | E36: 12.6 | F36: 6.82 | G36: =F36+E36 -> 19.42 | H36: =C36*E36 -> 22957.2 | I36: =C36*F36 -> 12426.04 | J36: =SUM(E36:F36)*C36 -> 35383.24 | V36: 1822 | W36: m²/mês | X36: 15.45 | Y36: 7.43 | Z36: =SUM(X36:Y36) -> 22.88 | AB36: 1822 | AC36: m²/mês | AD36: 19.9 | AE36: 9.57 | AF36: =SUM(AD36:AE36) -> 29.47 | AH36: =IF(E36=0,0,(E36/AD36)-1) -> -0.36683417 | AI36: =IF(F36=0,0,(F36/AE36)-1) -> -0.28735632 | AJ36: =IF(G36=0,0,(G36/AF36)-1) -> -0.34102477
... A52: 2.36 | B52: Tela para Andaime | C52: =V52 -> 1 | D52: =W52 -> m² | E52: 2.51 | F52: 2.99 | G52: =F52+E52 -> 5.5 | H52: =C52*E52 -> 2.51 | I52: =C52*F52 -> 2.99 | J52: =SUM(E52:F52)*C52 -> 5.5 | V52: 1 | W52: m² | X52: 3.63 | Y52: 3.15 | Z52: =SUM(X52:Y52) -> 6.78 | AB52: 1 | AC52: m² | AD52: 4.68 | AE52: 4.06 | AF52: =SUM(AD52:AE52) -> 8.74 | AH52: =IF(E52=0,0,(E52/AD52)-1) -> -0.46367521 | AI52: =IF(F52=0,0,(F52/AE52)-1) -> -0.2635468 | AJ52: =IF(G52=0,0,(G52/AF52)-1) -> -0.37070938
A53: 3 | B53: MOVIMENTO DE TERRA | E53: 0 | F53: 0 | H53: 0 | I53: 0 | J53: 0 | AH53: =IF(E53=0,0,(E53/AD53)-1) -> 0 | AI53: =IF(F53=0,0,(F53/AE53)-1) -> 0 | AJ53: =IF(G53=0,0,(G53/AF53)-1) -> 0
A54: 4 | B54: FUNDAÇÃO | E54: 0 | F54: 0 | H54: 0 | I54: 0 | J54: 0 | AH54: =IF(E54=0,0,(E54/AD54)-1) -> 0 | AI54: =IF(F54=0,0,(F54/AE54)-1) -> 0 | AJ54: =IF(G54=0,0,(G54/AF54)-1) -> 0
A55: 5 | B55: ESTRUTURA | E55: 0 | F55: 0 | H55: =SUM(H56:H59) -> 1650.25 | I55: =SUM(I56:I59) -> 450.1 | J55: =SUM(J56:J59) -> 2100.35 | AH55: =IF(E55=0,0,(E55/AD55)-1) -> 0 | AI55: =IF(F55=0,0,(F55/AE55)-1) -> 0 | AJ55: =IF(G55=0,0,(G55/AF55)-1) -> 0
A56: 5.1 | B56: Base de concreto para fixação de TAA/TTE | C56: =V56 -> 1 | D56: =W56 -> m³ | E56: 729.79 | F56: 48.52 | G56: =F56+E56 -> 778.31 | H56: =C56*E56 -> 729.79 | I56: =C56*F56 -> 48.52 | J56: =SUM(E56:F56)*C56 -> 778.31 | V56: 1 | W56: m³ | X56: 933.69 | Y56: 51.34 | Z56: =SUM(X56:Y56) -> 985.03 | AB56: 1 | AC56: m³ | AD56: 1202.78 | AE56: 66.14 | AF56: =SUM(AD56:AE56) -> 1268.92 | AH56: =IF(E56=0,0,(E56/AD56)-1) -> -0.39324731 | AI56: =IF(F56=0,0,(F56/AE56)-1) -> -0.2664046 | AJ56: =IF(G56=0,0,(G56/AF56)-1) -> -0.38663588
A57: 5.2 | B57: Montagem e Desmontagem de escoramento em madeira. | C57: =V57 -> 1 | D57: =W57 -> m² | E57: 141.62 | F57: 54.03 | G57: =F57+E57 -> 195.65 | H57: =C57*E57 -> 141.62 | I57: =C57*F57 -> 54.03 | J57: =SUM(E57:F57)*C57 -> 195.65 | V57: 1 | W57: m² | X57: 179.43 | Y57: 56.59 | Z57: =SUM(X57:Y57) -> 236.02 | AB57: 1 | AC57: m² | AD57: 231.14 | AE57: 72.9 | AF57: =SUM(AD57:AE57) -> 304.04 | AH57: =IF(E57=0,0,(E57/AD57)-1) -> -0.38729774 | AI57: =IF(F57=0,0,(F57/AE57)-1) -> -0.25884774 | AJ57: =IF(G57=0,0,(G57/AF57)-1) -> -0.35649914
A58: 5.3 | B58: Montagem e Desmontagem de escoramento metálico. | C58: =V58 -> 1 | D58: =W58 -> m² | E58: 91.96 | F58: 46.71 | G58: =F58+E58 -> 138.67 | H58: =C58*E58 -> 91.96 | I58: =C58*F58 -> 46.71 | J58: =SUM(E58:F58)*C58 -> 138.67 | V58: 1 | W58: m² | X58: 106.01 | Y58: 48.93 | Z58: =SUM(X58:Y58) -> 154.94 | AB58: 1 | AC58: m² | AD58: 136.56 | AE58: 63.03 | AF58: =SUM(AD58:AE58) -> 199.59 | AH58: =IF(E58=0,0,(E58/AD58)-1) -> -0.32659637 | AI58: =IF(F58=0,0,(F58/AE58)-1) -> -0.25892432 | AJ58: =IF(G58=0,0,(G58/AF58)-1) -> -0.30522571
A59: 5.4 | B59: Concreto fck = 15 MPa, controle tipo "B", e = 10 cm, e armado com tela de aço CA-60 | C59: =V59 -> 12 | D59: =W59 -> m² | E59: 57.24 | F59: 25.07 | G59: =F59+E59 -> 82.31 | H59: =C59*E59 -> 686.88 | I59: =C59*F59 -> 300.84 | J59: =SUM(E59:F59)*C59 -> 987.72 | V59: 12 | W59: m² | X59: 82.68 | Y59: 26.51 | Z59: =SUM(X59:Y59) -> 109.19 | AB59: 12 | AC59: m² | AD59: 106.51 | AE59: 34.15 | AF59: =SUM(AD59:AE59) -> 140.66 | AH59: =IF(E59=0,0,(E59/AD59)-1) -> -0.46258567 | AI59: =IF(F59=0,0,(F59/AE59)-1) -> -0.2658858 | AJ59: =IF(G59=0,0,(G59/AF59)-1) -> -0.41483009
A60: 6 | B60: ALVENARIAS E OUTRAS VEDAÇÕES | E60: 0 | F60: 0 | H60: =SUM(H61:H63) -> 15581.41 | I60: =SUM(I61:I63) -> 4169.79 | J60: =SUM(J61:J63) -> 19751.2 | AH60: =IF(E60=0,0,(E60/AD60)-1) -> 0 | AI60: =IF(F60=0,0,(F60/AE60)-1) -> 0 | AJ60: =IF(G60=0,0,(G60/AF60)-1) -> 0
A61: 6.1 | B61: Alvenaria com tijolo cerâmico furado | C61: =V61 -> 76 | D61: =W61 -> m² | E61: 18.61 | F61: 24.09 | G61: =F61+E61 -> 42.7 | H61: =C61*E61 -> 1414.36 | I61: =C61*F61 -> 1830.84 | J61: =SUM(E61:F61)*C61 -> 3245.2 | V61: 76 | W61: m² | X61: 26.88 | Y61: 39.53 | Z61: =SUM(X61:Y61) -> 66.41 | AB61: 76 | AC61: m² | AD61: 34.63 | AE61: 50.92 | AF61: =SUM(AD61:AE61) -> 85.55 | AH61: =IF(E61=0,0,(E61/AD61)-1) -> -0.46260468 | AI61: =IF(F61=0,0,(F61/AE61)-1) -> -0.52690495 | AJ61: =IF(G61=0,0,(G61/AF61)-1) -> -0.50087668
A62: 6.2 | B62: Parede de gesso em placas duplas acartonado dry wall - inclusive para ambientes úmidos - RU | C62: =V62 -> 123 | D62: =W62 -> m² | E62: 103.31 | F62: 7.57 | G62: =F62+E62 -> 110.88 | H62: =C62*E62 -> 12707.13 | I62: =C62*F62 -> 931.11 | J62: =SUM(E62:F62)*C62 -> 13638.24 | V62: 123 | W62: m² | X62: 149.2 | Y62: 12.87 | Z62: =SUM(X62:Y62) -> 162.07 | AB62: 123 | AC62: m² | AD62: 192.2 | AE62: 16.58 | AF62: =SUM(AD62:AE62) -> 208.78 | AH62: =IF(E62=0,0,(E62/AD62)-1) -> -0.46248699 | AI62: =IF(F62=0,0,(F62/AE62)-1) -> -0.54342581 | AJ62: =IF(G62=0,0,(G62/AF62)-1) -> -0.46891465
A63: 6.3 | B63: Rasgo e fechamento em alvenaria e piso | C63: =V63 -> 84 | D63: =W63 -> m | E63: 17.38 | F63: 16.76 | G63: =F63+E63 -> 34.14 | H63: =C63*E63 -> 1459.92 | I63: =C63*F63 -> 1407.84 | J63: =SUM(E63:F63)*C63 -> 2867.76 | V63: 84 | W63: m | X63: 25.11 | Y63: 27.59 | Z63: =SUM(X63:Y63) -> 52.7 | AB63: 84 | AC63: m | AD63: 32.35 | AE63: 35.54 | AF63: =SUM(AD63:AE63) -> 67.89 | AH63: =IF(E63=0,0,(E63/AD63)-1) -> -0.46275116 | AI63: =IF(F63=0,0,(F63/AE63)-1) -> -0.52841868 | AJ63: =IF(G63=0,0,(G63/AF63)-1) -> -0.49712771
A64: 7 | B64: COBERTURA | E64: 0 | F64: 0 | H64: =SUM(H65:H79) -> 64196.3 | I64: =SUM(I65:I79) -> 12220.51 | J64: =SUM(J65:J79) -> 76416.81 | AH64: =IF(E64=0,0,(E64/AD64)-1) -> 0 | AI64: =IF(F64=0,0,(F64/AE64)-1) -> 0 | AJ64: =IF(G64=0,0,(G64/AF64)-1) -> 0
A65: 7.1 | B65: Cobertura com telha de alumínio envernizada ou pintada, e=0,5 mm | C65: =V65 -> 70 | D65: =W65 -> m² | E65: 106.17 | F65: 11.86 | G65: =F65+E65 -> 118.03 | H65: =C65*E65 -> 7431.9 | I65: =C65*F65 -> 830.2 | J65: =SUM(E65:F65)*C65 -> 8262.1 | V65: 70 | W65: m² | X65: 124.52 | Y65: 12.76 | Z65: =SUM(X65:Y65) -> 137.28 | AB65: 70 | AC65: m² | AD65: 160.41 | AE65: 16.44 | AF65: =SUM(AD65:AE65) -> 176.85 | AH65: =IF(E65=0,0,(E65/AD65)-1) -> -0.33813353 | AI65: =IF(F65=0,0,(F65/AE65)-1) -> -0.27858881 | AJ65: =IF(G65=0,0,(G65/AF65)-1) -> -0.33259825
A66: 7.2 | B66: Cobertura em telha com isolamento termoacustico em espuma rígida de poliuretano (PU) injetado | C66: =V66 -> 67 | D66: =W66 -> m² | E66: 124.33 | F66: 9.12 | G66: =F66+E66 -> 133.45 | H66: =C66*E66 -> 8330.11 | I66: =C66*F66 -> 611.04 | J66: =SUM(E66:F66)*C66 -> 8941.15 | V66: 67 | W66: m² | X66: 130.27 | Y66: 9.61 | Z66: =SUM(X66:Y66) -> 139.88 | AB66: 67 | AC66: m² | AD66: 167.81 | AE66: 12.38 | AF66: =SUM(AD66:AE66) -> 180.19 | AH66: =IF(E66=0,0,(E66/AD66)-1) -> -0.25910256 | AI66: =IF(F66=0,0,(F66/AE66)-1) -> -0.26332795 | AJ66: =IF(G66=0,0,(G66/AF66)-1) -> -0.25939286
A67: 7.3 | B67: Cumeeira em chapa metálica | C67: =V67 -> 1 | D67: =W67 -> m | E67: 107.74 | F67: 4.97 | G67: =F67+E67 -> 112.71 | H67: =C67*E67 -> 107.74 | I67: =C67*F67 -> 4.97 | J67: =SUM(E67:F67)*C67 -> 112.71 | V67: 1 | W67: m | X67: 125.69 | Y67: 5.24 | Z67: =SUM(X67:Y67) -> 130.93 | AB67: 1 | AC67: m | AD67: 161.91 | AE67: 6.75 | AF67: =SUM(AD67:AE67) -> 168.66 | AH67: =IF(E67=0,0,(E67/AD67)-1) -> -0.33456859 | AI67: =IF(F67=0,0,(F67/AE67)-1) -> -0.2637037 | AJ67: =IF(G67=0,0,(G67/AF67)-1) -> -0.33173248
A68: 7.4 | B68: Cobertura com telha cerâmica, incluso transporte vertical | C68: =V68 -> 126 | D68: =W68 -> m² | E68: 37.58 | F68: 9.55 | G68: =F68+E68 -> 47.13 | H68: =C68*E68 -> 4735.08 | I68: =C68*F68 -> 1203.3 | J68: =SUM(E68:F68)*C68 -> 5938.38 | V68: 126 | W68: m² | X68: 36.47 | Y68: 10.1 | Z68: =SUM(X68:Y68) -> 46.57 | AB68: 126 | AC68: m² | AD68: 46.98 | AE68: 13.01 | AF68: =SUM(AD68:AE68) -> 59.99 | AH68: =IF(E68=0,0,(E68/AD68)-1) -> -0.20008514 | AI68: =IF(F68=0,0,(F68/AE68)-1) -> -0.26594927 | AJ68: =IF(G68=0,0,(G68/AF68)-1) -> -0.21436906
A69: 7.5 | B69: Cumeeira para telha cerâmica emboçada com argamassa | C69: =V69 -> 36 | D69: =W69 -> m | E69: 16.23 | F69: 21.1 | G69: =F69+E69 -> 37.33 | H69: =C69*E69 -> 584.28 | I69: =C69*F69 -> 759.6 | J69: =SUM(E69:F69)*C69 -> 1343.88 | V69: 36 | W69: m | X69: 15.75 | Y69: 22.23 | Z69: =SUM(X69:Y69) -> 37.98 | AB69: 36 | AC69: m | AD69: 20.29 | AE69: 28.64 | AF69: =SUM(AD69:AE69) -> 48.93 | AH69: =IF(E69=0,0,(E69/AD69)-1) -> -0.20009857 | AI69: =IF(F69=0,0,(F69/AE69)-1) -> -0.26326816 | AJ69: =IF(G69=0,0,(G69/AF69)-1) -> -0.23707337
A70: 7.6 | B70: Cumeeira universal para telhado de fibrocimento, e=6mm | C70: =V70 -> 100 | D70: =W70 -> m | E70: 62.29 | F70: 22.34 | G70: =F70+E70 -> 84.63 | H70: =C70*E70 -> 6229 | I70: =C70*F70 -> 2234 | J70: =SUM(E70:F70)*C70 -> 8463 | V70: 100 | W70: m | X70: 70.51 | Y70: 23.71 | Z70: =SUM(X70:Y70) -> 94.22 | AB70: 100 | AC70: m | AD70: 90.83 | AE70: 30.54 | AF70: =SUM(AD70:AE70) -> 121.37 | AH70: =IF(E70=0,0,(E70/AD70)-1) -> -0.31421337 | AI70: =IF(F70=0,0,(F70/AE70)-1) -> -0.26850033 | AJ70: =IF(G70=0,0,(G70/AF70)-1) -> -0.30271072
A71: 7.7 | B71: Cobertura com telha de fibrocimento, e = 6 mm, | C71: =V71 -> 479 | D71: =W71 -> m² | E71: 32.8 | F71: 6.01 | G71: =F71+E71 -> 38.81 | H71: =C71*E71 -> 15711.2 | I71: =C71*F71 -> 2878.79 | J71: =SUM(E71:F71)*C71 -> 18589.99 | V71: 479 | W71: m² | X71: 37.53 | Y71: 6.34 | Z71: =SUM(X71:Y71) -> 43.87 | AB71: 479 | AC71: m² | AD71: 48.35 | AE71: 8.17 | AF71: =SUM(AD71:AE71) -> 56.52 | AH71: =IF(E71=0,0,(E71/AD71)-1) -> -0.32161324 | AI71: =IF(F71=0,0,(F71/AE71)-1) -> -0.26438188 | AJ71: =IF(G71=0,0,(G71/AF71)-1) -> -0.31334041
A72: 7.8 | B72: Calha de chapa galvanizada nº 24 desenvolvimento 33 cm | C72: =V72 -> 120 | D72: =W72 -> m | E72: 49.06 | F72: 9.54 | G72: =F72+E72 -> 58.6 | H72: =C72*E72 -> 5887.2 | I72: =C72*F72 -> 1144.8 | J72: =SUM(E72:F72)*C72 -> 7032 | V72: 120 | W72: m | X72: 54.23 | Y72: 10.07 | Z72: =SUM(X72:Y72) -> 64.3 | AB72: 120 | AC72: m | AD72: 69.86 | AE72: 12.97 | AF72: =SUM(AD72:AE72) -> 82.83 | AH72: =IF(E72=0,0,(E72/AD72)-1) -> -0.29773833 | AI72: =IF(F72=0,0,(F72/AE72)-1) -> -0.26445644 | AJ72: =IF(G72=0,0,(G72/AF72)-1) -> -0.29252686
A73: 7.9 | B73: Rufo de chapa de aço galvanizado com desenvolvimento até 50 cm | C73: =V73 -> 324 | D73: =W73 -> m | E73: 42.73 | F73: 6.41 | G73: =F73+E73 -> 49.14 | H73: =C73*E73 -> 13844.52 | I73: =C73*F73 -> 2076.84 | J73: =SUM(E73:F73)*C73 -> 15921.36 | V73: 324 | W73: m | X73: 47.25 | Y73: 6.78 | Z73: =SUM(X73:Y73) -> 54.03 | AB73: 324 | AC73: m | AD73: 60.87 | AE73: 8.73 | AF73: =SUM(AD73:AE73) -> 69.6 | AH73: =IF(E73=0,0,(E73/AD73)-1) -> -0.29801216 | AI73: =IF(F73=0,0,(F73/AE73)-1) -> -0.26575029 | AJ73: =IF(G73=0,0,(G73/AF73)-1) -> -0.29396552
A74: 7.10 | B74: Chapim de chapa de aço galvanizado nº 24 desenvolvimento 33 cm | C74: =V74 -> 1 | D74: =W74 -> m | E74: 55.33 | F74: 9.08 | G74: =F74+E74 -> 64.41 | H74: =C74*E74 -> 55.33 | I74: =C74*F74 -> 9.08 | J74: =SUM(E74:F74)*C74 -> 64.41 | V74: 1 | W74: m | X74: 60.9 | Y74: 9.58 | Z74: =SUM(X74:Y74) -> 70.48 | AB74: 1 | AC74: m | AD74: 78.45 | AE74: 12.34 | AF74: =SUM(AD74:AE74) -> 90.79 | AH74: =IF(E74=0,0,(E74/AD74)-1) -> -0.29471001 | AI74: =IF(F74=0,0,(F74/AE74)-1) -> -0.26418152 | AJ74: =IF(G74=0,0,(G74/AF74)-1) -> -0.29056063
A75: 7.11 | B75: Cobertura com telha de fibrocimento estrutural, com recobrimento longitudinal | C75: =V75 -> 14 | D75: =W75 -> m² | E75: 74.74 | F75: 23.64 | G75: =F75+E75 -> 98.38 | H75: =C75*E75 -> 1046.36 | I75: =C75*F75 -> 330.96 | J75: =SUM(E75:F75)*C75 -> 1377.32 | V75: 14 | W75: m² | X75: 86.55 | Y75: 25.01 | Z75: =SUM(X75:Y75) -> 111.56 | AB75: 14 | AC75: m² | AD75: 111.49 | AE75: 32.22 | AF75: =SUM(AD75:AE75) -> 143.71 | AH75: =IF(E75=0,0,(E75/AD75)-1) -> -0.32962598 | AI75: =IF(F75=0,0,(F75/AE75)-1) -> -0.26629423 | AJ75: =IF(G75=0,0,(G75/AF75)-1) -> -0.3154269
A76: 7.12 | B76: Estrutura de madeira para telha cerâmica, fibrocimento ou de concreto | C76: =V76 -> 1 | D76: =W76 -> m² | E76: 72.33 | F76: 96.26 | G76: =F76+E76 -> 168.59 | H76: =C76*E76 -> 72.33 | I76: =C76*F76 -> 96.26 | J76: =SUM(E76:F76)*C76 -> 168.59 | V76: 1 | W76: m² | X76: 90.83 | Y76: 101.36 | Z76: =SUM(X76:Y76) -> 192.19 | AB76: 1 | AC76: m² | AD76: 117.01 | AE76: 130.57 | AF76: =SUM(AD76:AE76) -> 247.58 | AH76: =IF(E76=0,0,(E76/AD76)-1) -> -0.38184771 | AI76: =IF(F76=0,0,(F76/AE76)-1) -> -0.26277093 | AJ76: =IF(G76=0,0,(G76/AF76)-1) -> -0.31904839
... A79: 7.15 | B79: Reparo emergencial de telhado e calhas | C79: =V79 -> 1 | D79: =W79 -> un | E79: 10.77 | F79: 6.01 | G79: =F79+E79 -> 16.78 | H79: =C79*E79 -> 10.77 | I79: =C79*F79 -> 6.01 | J79: =SUM(E79:F79)*C79 -> 16.78 | V79: 1 | W79: un | X79: 11.39 | Y79: 6.34 | Z79: =SUM(X79:Y79) -> 17.73 | AB79: 1 | AC79: un | AD79: 14.67 | AE79: 8.17 | AF79: =SUM(AD79:AE79) -> 22.84 | AH79: =IF(E79=0,0,(E79/AD79)-1) -> -0.26584867 | AI79: =IF(F79=0,0,(F79/AE79)-1) -> -0.26438188 | AJ79: =IF(G79=0,0,(G79/AF79)-1) -> -0.26532399
A80: 8 | B80: IMPERMEABILIZAÇÃO | E80: 0 | F80: 0 | H80: =SUM(H81:H87) -> 37886.61 | I80: =SUM(I81:I87) -> 21125.78 | J80: =SUM(J81:J87) -> 59012.39 | AH80: =IF(E80=0,0,(E80/AD80)-1) -> 0 | AI80: =IF(F80=0,0,(F80/AE80)-1) -> 0 | AJ80: =IF(G80=0,0,(G80/AF80)-1) -> 0
A81: 8.1 | B81: Proteção mecânica de superfície com argamassa de cimento e areia | C81: =V81 -> 94 | D81: =W81 -> m² | E81: 23.15 | F81: 17.65 | G81: =F81+E81 -> 40.8 | H81: =C81*E81 -> 2176.1 | I81: =C81*F81 -> 1659.1 | J81: =SUM(E81:F81)*C81 -> 3835.2 | V81: 94 | W81: m² | X81: 25.13 | Y81: 18.46 | Z81: =SUM(X81:Y81) -> 43.59 | AB81: 94 | AC81: m² | AD81: 32.37 | AE81: 23.78 | AF81: =SUM(AD81:AE81) -> 56.15 | AH81: =IF(E81=0,0,(E81/AD81)-1) -> -0.28483163 | AI81: =IF(F81=0,0,(F81/AE81)-1) -> -0.25777965 | AJ81: =IF(G81=0,0,(G81/AF81)-1) -> -0.27337489
A82: 8.2 | B82: Impermeabilização com manta asfáltica modificada com polímeros aluminizada | C82: =V82 -> 13 | D82: =W82 -> m² | E82: 55.64 | F82: 16.93 | G82: =F82+E82 -> 72.57 | H82: =C82*E82 -> 723.32 | I82: =C82*F82 -> 220.09 | J82: =SUM(E82:F82)*C82 -> 943.41 | V82: 13 | W82: m² | X82: 66.07 | Y82: 17.8 | Z82: =SUM(X82:Y82) -> 83.87 | AB82: 13 | AC82: m² | AD82: 85.11 | AE82: 22.93 | AF82: =SUM(AD82:AE82) -> 108.04 | AH82: =IF(E82=0,0,(E82/AD82)-1) -> -0.34625778 | AI82: =IF(F82=0,0,(F82/AE82)-1) -> -0.26166594 | AJ82: =IF(G82=0,0,(G82/AF82)-1) -> -0.32830433
A83: 8.3 | B83: Impermeabilização utilizando manta asfáltica polimérica (cobertura, lajes, banheiros, jardins, Reservatórios e similares) | C83: =V83 -> 459 | D83: =W83 -> m² | E83: 63.16 | F83: 25.93 | G83: =F83+E83 -> 89.09 | H83: =C83*E83 -> 28990.44 | I83: =C83*F83 -> 11901.87 | J83: =SUM(E83:F83)*C83 -> 40892.31 | V83: 459 | W83: m² | X83: 75.11 | Y83: 27.12 | Z83: =SUM(X83:Y83) -> 102.23 | AB83: 459 | AC83: m² | AD83: 96.76 | AE83: 34.94 | AF83: =SUM(AD83:AE83) -> 131.7 | AH83: =IF(E83=0,0,(E83/AD83)-1) -> -0.34725093 | AI83: =IF(F83=0,0,(F83/AE83)-1) -> -0.25787064 | AJ83: =IF(G83=0,0,(G83/AF83)-1) -> -0.32353834
A84: 8.4 | B84: Impermeabilização de calha ou lajes descobertas com emulsão asfáltica com elastômeros, 3 demãos, com tela de poliéster | C84: =V84 -> 36 | D84: =W84 -> m² | E84: 39.13 | F84: 16.94 | G84: =F84+E84 -> 56.07 | H84: =C84*E84 -> 1408.68 | I84: =C84*F84 -> 609.84 | J84: =SUM(E84:F84)*C84 -> 2018.52 | V84: 36 | W84: m² | X84: 46.34 | Y84: 17.73 | Z84: =SUM(X84:Y84) -> 64.07 | AB84: 36 | AC84: m² | AD84: 59.7 | AE84: 22.84 | AF84: =SUM(AD84:AE84) -> 82.54 | AH84: =IF(E84=0,0,(E84/AD84)-1) -> -0.34455611 | AI84: =IF(F84=0,0,(F84/AE84)-1) -> -0.25831874 | AJ84: =IF(G84=0,0,(G84/AF84)-1) -> -0.320693
A85: 8.5 | B85: Impermeabilização de superfície com impermeabilizante flexível à base acrílica | C85: =V85 -> 58 | D85: =W85 -> m² | E85: 38.92 | F85: 44.62 | G85: =F85+E85 -> 83.54 | H85: =C85*E85 -> 2257.36 | I85: =C85*F85 -> 2587.96 | J85: =SUM(E85:F85)*C85 -> 4845.32 | V85: 58 | W85: m² | X85: 52.1 | Y85: 46.79 | Z85: =SUM(X85:Y85) -> 98.89 | AB85: 58 | AC85: m² | AD85: 67.12 | AE85: 60.27 | AF85: =SUM(AD85:AE85) -> 127.39 | AH85: =IF(E85=0,0,(E85/AD85)-1) -> -0.42014303 | AI85: =IF(F85=0,0,(F85/AE85)-1) -> -0.25966484 | AJ85: =IF(G85=0,0,(G85/AF85)-1) -> -0.34421854
A86: 8.6 | B86: Impermeabilização com argamassa polimérica impermeabilizante | C86: =V86 -> 324 | D86: =W86 -> m² | E86: 6.88 | F86: 12.74 | G86: =F86+E86 -> 19.62 | H86: =C86*E86 -> 2229.12 | I86: =C86*F86 -> 4127.76 | J86: =SUM(E86:F86)*C86 -> 6356.88 | V86: 324 | W86: m² | X86: 9.42 | Y86: 13.37 | Z86: =SUM(X86:Y86) -> 22.79 | AB86: 324 | AC86: m² | AD86: 12.13 | AE86: 17.22 | AF86: =SUM(AD86:AE86) -> 29.35 | AH86: =IF(E86=0,0,(E86/AD86)-1) -> -0.43281121 | AI86: =IF(F86=0,0,(F86/AE86)-1) -> -0.2601626 | AJ86: =IF(G86=0,0,(G86/AF86)-1) -> -0.33151618
A87: 8.7 | B87: Impermeabilização com membrana de poliuretano (PU) | C87: =V87 -> 1 | D87: =W87 -> m² | E87: 101.59 | F87: 19.16 | G87: =F87+E87 -> 120.75 | H87: =C87*E87 -> 101.59 | I87: =C87*F87 -> 19.16 | J87: =SUM(E87:F87)*C87 -> 120.75 | V87: 1 | W87: m² | X87: 139.1 | Y87: 20.06 | Z87: =SUM(X87:Y87) -> 159.16 | AB87: 1 | AC87: m² | AD87: 179.19 | AE87: 25.84 | AF87: =SUM(AD87:AE87) -> 205.03 | AH87: =IF(E87=0,0,(E87/AD87)-1) -> -0.43305988 | AI87: =IF(F87=0,0,(F87/AE87)-1) -> -0.25851393 | AJ87: =IF(G87=0,0,(G87/AF87)-1) -> -0.4110618
A88: 9 | B88: TRATAMENTO TÉRMICO E ACÚSTICO | E88: 0 | F88: 0 | H88: 0 | I88: 0 | J88: 0 | AH88: =IF(E88=0,0,(E88/AD88)-1) -> 0 | AI88: =IF(F88=0,0,(F88/AE88)-1) -> 0 | AJ88: =IF(G88=0,0,(G88/AF88)-1) -> 0
A89: 10 | B89: PAVIMENTAÇÃO | E89: 0 | F89: 0 | H89: =SUM(H90:H112) -> 822445.86 | I89: =SUM(I90:I112) -> 25436.23 | J89: =SUM(J90:J112) -> 847882.09 | AH89: =IF(E89=0,0,(E89/AD89)-1) -> 0 | AI89: =IF(F89=0,0,(F89/AE89)-1) -> 0 | AJ89: =IF(G89=0,0,(G89/AF89)-1) -> 0
A90: 10.1 | B90: Regularização de base ou contrapiso | C90: =V90 -> 244 | D90: =W90 -> m² | E90: 14.41 | F90: 10.09 | G90: =F90+E90 -> 24.5 | H90: =C90*E90 -> 3516.04 | I90: =C90*F90 -> 2461.96 | J90: =SUM(E90:F90)*C90 -> 5978 | V90: 244 | W90: m² | X90: 15.53 | Y90: 10.62 | Z90: =SUM(X90:Y90) -> 26.15 | AB90: 244 | AC90: m² | AD90: 20.01 | AE90: 13.68 | AF90: =SUM(AD90:AE90) -> 33.69 | AH90: =IF(E90=0,0,(E90/AD90)-1) -> -0.27986007 | AI90: =IF(F90=0,0,(F90/AE90)-1) -> -0.2624269 | AJ90: =IF(G90=0,0,(G90/AF90)-1) -> -0.27278124
A91: 10.2 | B91: Regularização de piso para piso vinílico ou tátil em borracha | C91: =V91 -> 9 | D91: =W91 -> m² | E91: 17.53 | F91: 16.16 | G91: =F91+E91 -> 33.69 | H91: =C91*E91 -> 157.77 | I91: =C91*F91 -> 145.44 | J91: =SUM(E91:F91)*C91 -> 303.21 | V91: 9 | W91: m² | X91: 18.8 | Y91: 16.99 | Z91: =SUM(X91:Y91) -> 35.79 | AB91: 9 | AC91: m² | AD91: 24.22 | AE91: 21.89 | AF91: =SUM(AD91:AE91) -> 46.11 | AH91: =IF(E91=0,0,(E91/AD91)-1) -> -0.276218 | AI91: =IF(F91=0,0,(F91/AE91)-1) -> -0.26176336 | AJ91: =IF(G91=0,0,(G91/AF91)-1) -> -0.26935589
A92: 10.3 | B92: Granito para revestimento (piso ou parede) Cinza Andorinha, assente com argamassa | C92: =V92 -> 14 | D92: =W92 -> m² | E92: 243.31 | F92: 38.98 | G92: =F92+E92 -> 282.29 | H92: =C92*E92 -> 3406.34 | I92: =C92*F92 -> 545.72 | J92: =SUM(E92:F92)*C92 -> 3952.06 | V92: 14 | W92: m² | X92: 297.07 | Y92: 40.82 | Z92: =SUM(X92:Y92) -> 337.89 | AB92: 14 | AC92: m² | AD92: 382.69 | AE92: 52.58 | AF92: =SUM(AD92:AE92) -> 435.27 | AH92: =IF(E92=0,0,(E92/AD92)-1) -> -0.36421124 | AI92: =IF(F92=0,0,(F92/AE92)-1) -> -0.25865348 | AJ92: =IF(G92=0,0,(G92/AF92)-1) -> -0.35146001
A93: 10.4 | B93: Rodapé em granito Cinza Andorinha, assentado e rejuntado | C93: =V93 -> 72 | D93: =W93 -> m | E93: 40.05 | F93: 9.82 | G93: =F93+E93 -> 49.87 | H93: =C93*E93 -> 2883.6 | I93: =C93*F93 -> 707.04 | J93: =SUM(E93:F93)*C93 -> 3590.64 | V93: 72 | W93: m | X93: 48.95 | Y93: 10.28 | Z93: =SUM(X93:Y93) -> 59.23 | AB93: 72 | AC93: m | AD93: 63.06 | AE93: 13.24 | AF93: =SUM(AD93:AE93) -> 76.3 | AH93: =IF(E93=0,0,(E93/AD93)-1) -> -0.36489058 | AI93: =IF(F93=0,0,(F93/AE93)-1) -> -0.25830816 | AJ93: =IF(G93=0,0,(G93/AF93)-1) -> -0.34639581
A94: 10.5 | B94: Peitoril ou soleira de granito, assentado e rejuntado | C94: =V94 -> 17 | D94: =W94 -> m | E94: 54.5 | F94: 17.94 | G94: =F94+E94 -> 72.44 | H94: =C94*E94 -> 926.5 | I94: =C94*F94 -> 304.98 | J94: =SUM(E94:F94)*C94 -> 1231.48 | V94: 17 | W94: m | X94: 66.62 | Y94: 18.79 | Z94: =SUM(X94:Y94) -> 85.41 | AB94: 17 | AC94: m | AD94: 85.82 | AE94: 24.21 | AF94: =SUM(AD94:AE94) -> 110.03 | AH94: =IF(E94=0,0,(E94/AD94)-1) -> -0.3649499 | AI94: =IF(F94=0,0,(F94/AE94)-1) -> -0.25898389 | AJ94: =IF(G94=0,0,(G94/AF94)-1) -> -0.3416341
A95: 10.6 | B95: Granito branco para revestimento (piso ou parede), assente com argamassa | C95: =V95 -> 1 | D95: =W95 -> m² | E95: 447.07 | F95: 38.98 | G95: =F95+E95 -> 486.05 | H95: =C95*E95 -> 447.07 | I95: =C95*F95 -> 38.98 | J95: =SUM(E95:F95)*C95 -> 486.05 | V95: 1 | W95: m² | X95: 546.73 | Y95: 40.82 | Z95: =SUM(X95:Y95) -> 587.55 | AB95: 1 | AC95: m² | AD95: 704.3 | AE95: 52.58 | AF95: =SUM(AD95:AE95) -> 756.88 | AH95: =IF(E95=0,0,(E95/AD95)-1) -> -0.36522789 | AI95: =IF(F95=0,0,(F95/AE95)-1) -> -0.25865348 | AJ95: =IF(G95=0,0,(G95/AF95)-1) -> -0.35782423
A96: 10.7 | B96: Rodapé em granito branco, assentado e rejuntado | C96: =V96 -> 1 | D96: =W96 -> m | E96: 42.82 | F96: 9.82 | G96: =F96+E96 -> 52.64 | H96: =C96*E96 -> 42.82 | I96: =C96*F96 -> 9.82 | J96: =SUM(E96:F96)*C96 -> 52.64 | V96: 1 | W96: m | X96: 52.35 | Y96: 10.28 | Z96: =SUM(X96:Y96) -> 62.63 | AB96: 1 | AC96: m | AD96: 67.44 | AE96: 13.24 | AF96: =SUM(AD96:AE96) -> 80.68 | AH96: =IF(E96=0,0,(E96/AD96)-1) -> -0.36506524 | AI96: =IF(F96=0,0,(F96/AE96)-1) -> -0.25830816 | AJ96: =IF(G96=0,0,(G96/AF96)-1) -> -0.34754586
A97: 10.8 | B97: Bloco de concreto intertravado | C97: =V97 -> 1 | D97: =W97 -> m² | E97: 58.07 | F97: 5.6 | G97: =F97+E97 -> 63.67 | H97: =C97*E97 -> 58.07 | I97: =C97*F97 -> 5.6 | J97: =SUM(E97:F97)*C97 -> 63.67 | V97: 1 | W97: m² | X97: 57.27 | Y97: 5.91 | Z97: =SUM(X97:Y97) -> 63.18 | AB97: 1 | AC97: m² | AD97: 73.78 | AE97: 7.61 | AF97: =SUM(AD97:AE97) -> 81.39 | AH97: =IF(E97=0,0,(E97/AD97)-1) -> -0.21293033 | AI97: =IF(F97=0,0,(F97/AE97)-1) -> -0.26412615 | AJ97: =IF(G97=0,0,(G97/AF97)-1) -> -0.21771716
A98: 10.9 | B98: Piso em pedra portuguesa, basalto, calcário ou granito sem polimento. | C98: =V98 -> 20 | D98: =W98 -> m² | E98: 144.14 | F98: 35.13 | G98: =F98+E98 -> 179.27 | H98: =C98*E98 -> 2882.8 | I98: =C98*F98 -> 702.6 | J98: =SUM(E98:F98)*C98 -> 3585.4 | V98: 20 | W98: m² | X98: 139.89 | Y98: 37.08 | Z98: =SUM(X98:Y98) -> 176.97 | AB98: 20 | AC98: m² | AD98: 180.21 | AE98: 47.77 | AF98: =SUM(AD98:AE98) -> 227.98 | AH98: =IF(E98=0,0,(E98/AD98)-1) -> -0.20015537 | AI98: =IF(F98=0,0,(F98/AE98)-1) -> -0.26460121 | AJ98: =IF(G98=0,0,(G98/AF98)-1) -> -0.21365909
A99: 10.10 | B99: Piso mármore branco, assentado e rejuntado | C99: =V99 -> 1 | D99: =W99 -> m² | E99: 328.21 | F99: 38.98 | G99: =F99+E99 -> 367.19 | H99: =C99*E99 -> 328.21 | I99: =C99*F99 -> 38.98 | J99: =SUM(E99:F99)*C99 -> 367.19 | V99: 1 | W99: m² | X99: 361.67 | Y99: 40.82 | Z99: =SUM(X99:Y99) -> 402.49 | AB99: 1 | AC99: m² | AD99: 465.9 | AE99: 52.58 | AF99: =SUM(AD99:AE99) -> 518.48 | AH99: =IF(E99=0,0,(E99/AD99)-1) -> -0.29553552 | AI99: =IF(F99=0,0,(F99/AE99)-1) -> -0.25865348 | AJ99: =IF(G99=0,0,(G99/AF99)-1) -> -0.29179525
A100: 10.11 | B100: Piso em ladrilho hidráulico, assentado com argamassa | C100: =V100 -> 8 | D100: =W100 -> m² | E100: 77.55 | F100: 73.13 | G100: =F100+E100 -> 150.68 | H100: =C100*E100 -> 620.4 | I100: =C100*F100 -> 585.04 | J100: =SUM(E100:F100)*C100 -> 1205.44 | V100: 8 | W100: m² | X100: 75.26 | Y100: 76.6 | Z100: =SUM(X100:Y100) -> 151.86 | AB100: 8 | AC100: m² | AD100: 96.95 | AE100: 98.68 | AF100: =SUM(AD100:AE100) -> 195.63 | AH100: =IF(E100=0,0,(E100/AD100)-1) -> -0.20010315 | AI100: =IF(F100=0,0,(F100/AE100)-1) -> -0.25891771 | AJ100: =IF(G100=0,0,(G100/AF100)-1) -> -0.22977049
A101: 10.12 | B101: Piso cimentado com argamassa e com junta plástica para dilatação. | C101: =V101 -> 47 | D101: =W101 -> m² | E101: 31.7 | F101: 12.4 | G101: =F101+E101 -> 44.1 | H101: =C101*E101 -> 1489.9 | I101: =C101*F101 -> 582.8 | J101: =SUM(E101:F101)*C101 -> 2072.7 | V101: 47 | W101: m² | X101: 30.76 | Y101: 13.01 | Z101: =SUM(X101:Y101) -> 43.77 | AB101: 47 | AC101: m² | AD101: 39.63 | AE101: 16.76 | AF101: =SUM(AD101:AE101) -> 56.39 | AH101: =IF(E101=0,0,(E101/AD101)-1) -> -0.20010093 | AI101: =IF(F101=0,0,(F101/AE101)-1) -> -0.2601432 | AJ101: =IF(G101=0,0,(G101/AF101)-1) -> -0.21794644
... A112: 10.23 | B112: Regularização de piso carpete | C112: =V112 -> 1 | D112: =W112 -> m² | E112: 17.53 | F112: 8.07 | G112: =F112+E112 -> 25.6 | H112: =C112*E112 -> 17.53 | I112: =C112*F112 -> 8.07 | J112: =SUM(E112:F112)*C112 -> 25.6 | V112: 1 | W112: m² | X112: 18.8 | Y112: 8.5 | Z112: =SUM(X112:Y112) -> 27.3 | AB112: 1 | AC112: m² | AD112: 24.22 | AE112: 10.95 | AF112: =SUM(AD112:AE112) -> 35.17 | AH112: =IF(E112=0,0,(E112/AD112)-1) -> -0.276218 | AI112: =IF(F112=0,0,(F112/AE112)-1) -> -0.2630137 | AJ112: =IF(G112=0,0,(G112/AF112)-1) -> -0.27210691
A113: 11 | B113: REVESTIMENTOS | E113: 0 | F113: 0 | H113: =SUM(H114:H122) -> 25255.61 | I113: =SUM(I114:I122) -> 15740.2 | J113: =SUM(J114:J122) -> 40995.81 | AH113: =IF(E113=0,0,(E113/AD113)-1) -> 0 | AI113: =IF(F113=0,0,(F113/AE113)-1) -> 0 | AJ113: =IF(G113=0,0,(G113/AF113)-1) -> 0
A114: 11.1 | B114: Painéis de alumínio - ACM | C114: =V114 -> 1 | D114: =W114 -> m² | E114: 140.64 | F114: 47.05 | G114: =F114+E114 -> 187.69 | H114: =C114*E114 -> 140.64 | I114: =C114*F114 -> 47.05 | J114: =SUM(E114:F114)*C114 -> 187.69 | V114: 1 | W114: m² | X114: 169.67 | Y114: 49.43 | Z114: =SUM(X114:Y114) -> 219.1 | AB114: 1 | AC114: m² | AD114: 218.57 | AE114: 63.68 | AF114: =SUM(AD114:AE114) -> 282.25 | AH114: =IF(E114=0,0,(E114/AD114)-1) -> -0.35654481 | AI114: =IF(F114=0,0,(F114/AE114)-1) -> -0.2611495 | AJ114: =IF(G114=0,0,(G114/AF114)-1) -> -0.33502214
A115: 11.2 | B115: Chapisco para parede interna ou externa com argamassa de cimento e areia. | C115: =V115 -> 507 | D115: =W115 -> m² | E115: 2.4 | F115: 4.03 | G115: =F115+E115 -> 6.43 | H115: =C115*E115 -> 1216.8 | I115: =C115*F115 -> 2043.21 | J115: =SUM(E115:F115)*C115 -> 3260.01 | V115: 507 | W115: m² | X115: 2.59 | Y115: 4.25 | Z115: =SUM(X115:Y115) -> 6.84 | AB115: 507 | AC115: m² | AD115: 3.34 | AE115: 5.47 | AF115: =SUM(AD115:AE115) -> 8.81 | AH115: =IF(E115=0,0,(E115/AD115)-1) -> -0.28143713 | AI115: =IF(F115=0,0,(F115/AE115)-1) -> -0.26325411 | AJ115: =IF(G115=0,0,(G115/AF115)-1) -> -0.27014756
A116: 11.3 | B116: Emboço ou reboco para parede interna ou externa ou teto. | C116: =V116 -> 566 | D116: =W116 -> m² | E116: 17.53 | F116: 19.1 | G116: =F116+E116 -> 36.63 | H116: =C116*E116 -> 9921.98 | I116: =C116*F116 -> 10810.6 | J116: =SUM(E116:F116)*C116 -> 20732.58 | V116: 566 | W116: m² | X116: 18.8 | Y116: 20.05 | Z116: =SUM(X116:Y116) -> 38.85 | AB116: 566 | AC116: m² | AD116: 24.22 | AE116: 25.83 | AF116: =SUM(AD116:AE116) -> 50.05 | AH116: =IF(E116=0,0,(E116/AD116)-1) -> -0.276218 | AI116: =IF(F116=0,0,(F116/AE116)-1) -> -0.26054975 | AJ116: =IF(G116=0,0,(G116/AF116)-1) -> -0.26813187
A117: 11.4 | B117: Revestimento cerâmico assentado com argamassa pré-fabricada e rejuntado | C117: =V117 -> 56 | D117: =W117 -> m² | E117: 30.31 | F117: 32.16 | G117: =F117+E117 -> 62.47 | H117: =C117*E117 -> 1697.36 | I117: =C117*F117 -> 1800.96 | J117: =SUM(E117:F117)*C117 -> 3498.32 | V117: 56 | W117: m² | X117: 37.49 | Y117: 33.69 | Z117: =SUM(X117:Y117) -> 71.18 | AB117: 56 | AC117: m² | AD117: 48.29 | AE117: 43.4 | AF117: =SUM(AD117:AE117) -> 91.69 | AH117: =IF(E117=0,0,(E117/AD117)-1) -> -0.37233382 | AI117: =IF(F117=0,0,(F117/AE117)-1) -> -0.25898618 | AJ117: =IF(G117=0,0,(G117/AF117)-1) -> -0.31868252
A118: 11.5 | B118: Revestimento (parede) em Pastilha de vidro, assentada com argamassa colante e rejunte. | C118: =V118 -> 8 | D118: =W118 -> m² | E118: 237.69 | F118: 34.16 | G118: =F118+E118 -> 271.85 | H118: =C118*E118 -> 1901.52 | I118: =C118*F118 -> 273.28 | J118: =SUM(E118:F118)*C118 -> 2174.8 | V118: 8 | W118: m² | X118: 230.68 | Y118: 35.78 | Z118: =SUM(X118:Y118) -> 266.46 | AB118: 8 | AC118: m² | AD118: 297.16 | AE118: 46.09 | AF118: =SUM(AD118:AE118) -> 343.25 | AH118: =IF(E118=0,0,(E118/AD118)-1) -> -0.20012788 | AI118: =IF(F118=0,0,(F118/AE118)-1) -> -0.2588414 | AJ118: =IF(G118=0,0,(G118/AF118)-1) -> -0.20801165
A119: 11.6 | B119: Laminado melamínico para revestimento (piso ou parede) interno | C119: =V119 -> 86 | D119: =W119 -> m² | E119: 111.45 | F119: 7.72 | G119: =F119+E119 -> 119.17 | H119: =C119*E119 -> 9584.7 | I119: =C119*F119 -> 663.92 | J119: =SUM(E119:F119)*C119 -> 10248.62 | V119: 86 | W119: m² | X119: 160.96 | Y119: 8.12 | Z119: =SUM(X119:Y119) -> 169.08 | AB119: 86 | AC119: m² | AD119: 207.35 | AE119: 10.46 | AF119: =SUM(AD119:AE119) -> 217.81 | AH119: =IF(E119=0,0,(E119/AD119)-1) -> -0.46250301 | AI119: =IF(F119=0,0,(F119/AE119)-1) -> -0.26195029 | AJ119: =IF(G119=0,0,(G119/AF119)-1) -> -0.45287177
A120: 11.7 | B120: Revestimento de parede com pedra São Tomé filetada (tipo "canjiquinha") | C120: =V120 -> 1 | D120: =W120 -> m² | E120: 245.23 | F120: 28.04 | G120: =F120+E120 -> 273.27 | H120: =C120*E120 -> 245.23 | I120: =C120*F120 -> 28.04 | J120: =SUM(E120:F120)*C120 -> 273.27 | V120: 1 | W120: m² | X120: 238 | Y120: 29.41 | Z120: =SUM(X120:Y120) -> 267.41 | AB120: 1 | AC120: m² | AD120: 306.59 | AE120: 37.89 | AF120: =SUM(AD120:AE120) -> 344.48 | AH120: =IF(E120=0,0,(E120/AD120)-1) -> -0.20013699 | AI120: =IF(F120=0,0,(F120/AE120)-1) -> -0.25996305 | AJ120: =IF(G120=0,0,(G120/AF120)-1) -> -0.20671737
A121: 11.8 | B121: Revestimento em mármore branco (parede), assentado e rejuntado | C121: =V121 -> 1 | D121: =W121 -> m² | E121: 328.21 | F121: 38.98 | G121: =F121+E121 -> 367.19 | H121: =C121*E121 -> 328.21 | I121: =C121*F121 -> 38.98 | J121: =SUM(E121:F121)*C121 -> 367.19 | V121: 1 | W121: m² | X121: 361.67 | Y121: 40.82 | Z121: =SUM(X121:Y121) -> 402.49 | AB121: 1 | AC121: m² | AD121: 465.9 | AE121: 52.58 | AF121: =SUM(AD121:AE121) -> 518.48 | AH121: =IF(E121=0,0,(E121/AD121)-1) -> -0.29553552 | AI121: =IF(F121=0,0,(F121/AE121)-1) -> -0.25865348 | AJ121: =IF(G121=0,0,(G121/AF121)-1) -> -0.29179525
A122: 11.9 | B122: Revestimento em Pastilha Cerâmica, assentada com argamassa colante e rejunte. | C122: =V122 -> 1 | D122: =W122 -> m² | E122: 219.17 | F122: 34.16 | G122: =F122+E122 -> 253.33 | H122: =C122*E122 -> 219.17 | I122: =C122*F122 -> 34.16 | J122: =SUM(E122:F122)*C122 -> 253.33 | V122: 1 | W122: m² | X122: 212.7 | Y122: 35.78 | Z122: =SUM(X122:Y122) -> 248.48 | AB122: 1 | AC122: m² | AD122: 274 | AE122: 46.09 | AF122: =SUM(AD122:AE122) -> 320.09 | AH122: =IF(E122=0,0,(E122/AD122)-1) -> -0.20010949 | AI122: =IF(F122=0,0,(F122/AE122)-1) -> -0.2588414 | AJ122: =IF(G122=0,0,(G122/AF122)-1) -> -0.20856634
A123: 12 | B123: DIVISÓRIAS, FORROS E PISOS FALSOS | E123: 0 | F123: 0 | H123: =SUM(H124:H137) -> 462040.88 | I123: =SUM(I124:I137) -> 87205.16 | J123: =SUM(J124:J137) -> 549246.04 | AH123: =IF(E123=0,0,(E123/AD123)-1) -> 0 | AI123: =IF(F123=0,0,(F123/AE123)-1) -> 0 | AJ123: =IF(G123=0,0,(G123/AF123)-1) -> 0
A124: 12.1 | B124: Divisória texturizada cega | C124: =V124 -> 515 | D124: =W124 -> m² | E124: 146.63 | F124: 35.66 | G124: =F124+E124 -> 182.29 | H124: =C124*E124 -> 75514.45 | I124: =C124*F124 -> 18364.9 | J124: =SUM(E124:F124)*C124 -> 93879.35 | V124: 515 | W124: m² | X124: 142.3 | Y124: 37.48 | Z124: =SUM(X124:Y124) -> 179.78 | AB124: 515 | AC124: m² | AD124: 183.31 | AE124: 48.28 | AF124: =SUM(AD124:AE124) -> 231.59 | AH124: =IF(E124=0,0,(E124/AD124)-1) -> -0.20009819 | AI124: =IF(F124=0,0,(F124/AE124)-1) -> -0.26139188 | AJ124: =IF(G124=0,0,(G124/AF124)-1) -> -0.2128762
A125: 12.2 | B125: Divisória texturizada cega/vidro | C125: =V125 -> 1 | D125: =W125 -> m² | E125: 137.99 | F125: 50.73 | G125: =F125+E125 -> 188.72 | H125: =C125*E125 -> 137.99 | I125: =C125*F125 -> 50.73 | J125: =SUM(E125:F125)*C125 -> 188.72 | V125: 1 | W125: m² | X125: 142.19 | Y125: 53.28 | Z125: =SUM(X125:Y125) -> 195.47 | AB125: 1 | AC125: m² | AD125: 183.17 | AE125: 68.64 | AF125: =SUM(AD125:AE125) -> 251.81 | AH125: =IF(E125=0,0,(E125/AD125)-1) -> -0.24665611 | AI125: =IF(F125=0,0,(F125/AE125)-1) -> -0.26092657 | AJ125: =IF(G125=0,0,(G125/AF125)-1) -> -0.25054605
A126: 12.3 | B126: Porta de divisória, Inclui batente e guarnições. | C126: =V126 -> 33 | D126: =W126 -> un | E126: 395.71 | F126: 35.66 | G126: =F126+E126 -> 431.37 | H126: =C126*E126 -> 13058.43 | I126: =C126*F126 -> 1176.78 | J126: =SUM(E126:F126)*C126 -> 14235.21 | V126: 33 | W126: un | X126: 455.73 | Y126: 37.48 | Z126: =SUM(X126:Y126) -> 493.21 | AB126: 33 | AC126: un | AD126: 587.07 | AE126: 48.28 | AF126: =SUM(AD126:AE126) -> 635.35 | AH126: =IF(E126=0,0,(E126/AD126)-1) -> -0.32595772 | AI126: =IF(F126=0,0,(F126/AE126)-1) -> -0.26139188 | AJ126: =IF(G126=0,0,(G126/AF126)-1) -> -0.32105139
A127: 12.4 | B127: Forro de fibra mineral, incluindo fixação, com estrutura | C127: =V127 -> 735 | D127: =W127 -> m² | E127: 124.97 | F127: 10.98 | G127: =F127+E127 -> 135.95 | H127: =C127*E127 -> 91852.95 | I127: =C127*F127 -> 8070.3 | J127: =SUM(E127:F127)*C127 -> 99923.25 | V127: 735 | W127: m² | X127: 152.58 | Y127: 11.54 | Z127: =SUM(X127:Y127) -> 164.12 | AB127: 735 | AC127: m² | AD127: 196.55 | AE127: 14.87 | AF127: =SUM(AD127:AE127) -> 211.42 | AH127: =IF(E127=0,0,(E127/AD127)-1) -> -0.36418214 | AI127: =IF(F127=0,0,(F127/AE127)-1) -> -0.26160054 | AJ127: =IF(G127=0,0,(G127/AF127)-1) -> -0.35696717
A128: 12.5 | B128: Forro de gesso acartonado, estruturado ou aramado | C128: =V128 -> 1026 | D128: =W128 -> m² | E128: 47.97 | F128: 32.37 | G128: =F128+E128 -> 80.34 | H128: =C128*E128 -> 49217.22 | I128: =C128*F128 -> 33211.62 | J128: =SUM(E128:F128)*C128 -> 82428.84 | V128: 1026 | W128: m² | X128: 61.65 | Y128: 33.98 | Z128: =SUM(X128:Y128) -> 95.63 | AB128: 1026 | AC128: m² | AD128: 79.42 | AE128: 43.77 | AF128: =SUM(AD128:AE128) -> 123.19 | AH128: =IF(E128=0,0,(E128/AD128)-1) -> -0.39599597 | AI128: =IF(F128=0,0,(F128/AE128)-1) -> -0.26045236 | AJ128: =IF(G128=0,0,(G128/AF128)-1) -> -0.34783668
A129: 12.6 | B129: Forro de placa de gesso pre-moldada, incluindo fixação | C129: =V129 -> 116 | D129: =W129 -> m² | E129: 12.4 | F129: 20.35 | G129: =F129+E129 -> 32.75 | H129: =C129*E129 -> 1438.4 | I129: =C129*F129 -> 2360.6 | J129: =SUM(E129:F129)*C129 -> 3799 | V129: 116 | W129: m² | X129: 15.56 | Y129: 21.31 | Z129: =SUM(X129:Y129) -> 36.87 | AB129: 116 | AC129: m² | AD129: 20.04 | AE129: 27.45 | AF129: =SUM(AD129:AE129) -> 47.49 | AH129: =IF(E129=0,0,(E129/AD129)-1) -> -0.38123752 | AI129: =IF(F129=0,0,(F129/AE129)-1) -> -0.25865209 | AJ129: =IF(G129=0,0,(G129/AF129)-1) -> -0.31038113
...

Sheet Prefixos
A1: Relação das Dependências do Rot - Varginha
A4: PREFIXO | B4: DEPENDÊNCIAS | C4: DISTÂNCIA EM RELAÇÃO A CIDADE BASE - IDA E VOLTA (KM) | D4: CIDADE
A5: 8672 | B5: EMPRESA POUSO ALEGRE | C5: 252 | D5: POUSO ALEGRE
A6: 8675 | B6: EMPRESA POCOS CALDAS | C6: 308 | D6: POCOS DE CALDAS
A7: 12 | B7: TRES CORACOES | C7: 69 | D7: TRES CORACOES
A8: 32 | B8: VARGINHA | C8: 10 | D8: VARGINHA
A9: 64 | B9: GUAXUPE | C9: 328 | D9: GUAXUPE
A10: 168 | B10: ALFENAS | C10: 139 | D10: ALFENAS
A11: 168 | B11: UNIFAL | C11: 139 | D11: ALFENAS
A12: 205 | B12: OURO FINO | C12: 358 | D12: OURO FINO
A13: 308 | B13: FORUM WENCESLAU BRAZ | C13: 366 | D13: ITAJUBA
A14: 308 | B14: EFEI - ESC.FED.ENGEN | C14: 366 | D14: ITAJUBA
A15: 308 | B15: ITAJUBA | C15: 366 | D15: ITAJUBA
A16: 309 | B16: FORUM POCOS DE CALDA | C16: 308 | D16: POCOS DE CALDAS
... A71: 8220 | B71: BOM REPOUSO | C71: 348 | D71: BOM REPOUSO

Sheet BDI
B1: O interessado deverá preencher os campos em amarelo de forma a obter o valor do BDI. | E1: O BDI pode ser alterado pela interessada. A alteração do BDI afeta o valor final da proposta. O valor do BDI deverá ser igual ao da proposta a ser apresentada.
B3: COMPOSIÇÃO ESTIMADA DO BDI (DESONERADO)
B6: ÍNDICES BDI - Serviços, subcontratações e acionamentos de Serviços de Engenharia.
B9: CUSTOS INDIRETOS
B10: Administração Central (AC) | C10: 0.03
B11: Seguros (S) + Garantia (G) | C11: 0.008
B12: Riscos R) | C12: 0.0097
B13: Despesas Financeiras (DF) | C13: 0.0059
B14: BONIFICAÇÃO
B15: Lucro Bruto (LB) | C15: 0.0616
B16: TRIBUTOS (T)
B17: ISS | C17: 0.05
B18: PIS / PASEP | C18: 0.0065
B19: COFINS | C19: 0.03
B20: CPRB | C20: 0.045
B21: BDI SERVIÇOS | C21: =ROUND(((1+(C10+C11+C12))*(1+C13)*(1+C15))/(1-(C17+C18+C19+C20))-1,4) -> 0.2882
B22: BDI = [[(1+(AC+S+G+R))*(1+DF)*(1+LB)]/(1-T)]-1
B26: 1 - O cálculo do BDI segue a metodologia estabelecida no item 9.10 do Voto do Acórdão 2369/2011 - TCU - Plenário. O IR e a CSLL não fazem parte do cálculo. 2 - Valores Referenciais dados pelo Acórdão 2622/2013 - TCU - Plenário. 3 - A parcela referente aos Seguros (S) é inversa à parcela de Riscos (R), ou seja, quanto maior a cobertura dos seguros contratados, menor a taxa de risco a ser considerada no BDI. Sendo assim, optou-se por representá-las na planilha de forma unificada. Poderão estar contabilizados na parcela os Seguros de Risco de Engenharia e de Responsabilidade Civil, dentre outros. 4 - Conforme orientações do TCU, publicadas no guia ORIENTAÇÕES PARA ELABORAÇÃO DE PLANILHAS ORÇAMENTÁRIAS DE OBRAS PÚBLICAS, a CPRB (Contribuição Previdenciária Sobre a Receita Bruta) deve ser incluída no cálculo do BDI de orçamentos que consideram a desoneração da folha de pagamentos.
B28: Observação: O PROPONENTE utilizará a incidência da CPRB somente se estiver enquadrado como desonerado.
