Workbook

Sheet Memorial de cálculo
A1: ITENS M² COM DESCONTO | K1: ITENS M² SEM DESCONTO | S1: ITENS M³ - ENTULHO, ETC | AA1: PINTURA ESMALTE EM PORTA | AH1: ITENS UNITÁRIOS (M, UM,
A5: Itens | K5: Itens | S5: Itens | AA5: Itens | AH5: Itens
A6: 17.6 | B6: =VLOOKUP(A6,Itens!$A$7:$J$537,2,0) -> Pintura em látex acrílica premium fosca em paredes internas ou externas, exceto muros, com três demãos, sem emassamento, com aplicação de selador para alvenaria exterior. | L6: =VLOOKUP(K6,Itens!$A$7:$J$537,2,0) -> #N/A | S6: 2.18 | T6: =VLOOKUP(S6,Itens!$A$7:$J$537,2,0) -> Remoção de entulho com caçamba metálica, inclusive limpeza, transporte, carga, descarga e descarte conforme legislação ambiental - Material de descarte (alvenaria, estruturas metálicas, madeiramento, revestimentos cerâmicos, gesso, dry-wall, entre outros) | AB6: =VLOOKUP(AA6,Itens!$A$7:$J$537,2,0) -> #N/A | AH6: 13.12 | AI6: =VLOOKUP(AH6,Itens!$A$7:$J$537,2,0) -> Deslocamento ou remanejamento de mobiliário dentro da agência
A7: Foto | B7: Comp. (m) | C7: Altura (m) | D7: Desconto (m²) | E7: Subtotal | F7: Total (m) | K7: Foto | L7: Comp. (m) | M7: Altura (m) | N7: Total (m²) | S7: Foto | T7: Comp. (m) | U7: Altura (m) | V7: Total (m³) | AA7: Foto | AB7: Comp. (m) | AC7: Altura (m) Comprimento (m) | AD7: Total (m²) | AH7: Foto | AI7: Quantitativo | AJ7: Unidade
A8: 177 | B8: 8.1 | C8: 3 | D8: 1.89 | E8: =C8*B8 -> 24.3 | F8: =E8-D8 -> 22.41 | N8: =M8*L8 -> 0 | S8: 290 | T8: 3.94 | U8: 1 | V8: =U8*T8 -> 3.94 | AC8: 2.1 | AD8: =AB8*AC8 -> 0 | AH8: 167 | AI8: 2 | AJ8: =UPPER(VLOOKUP($AH$6,Itens!$A$7:$J$537,4,0)) -> UN
E9: =C9*B9 -> 0 | F9: =E9-D9 -> 0 | N9: =M9*L9 -> 0 | V9: =U9*T9 -> 0 | AC9: 2.1 | AD9: =AB9*AC9 -> 0 | AJ9: =UPPER(VLOOKUP($AH$6,Itens!$A$7:$J$537,4,0)) -> UN
E10: =C10*B10 -> 0 | F10: =E10-D10 -> 0 | N10: =M10*L10 -> 0 | V10: =U10*T10 -> 0 | AC10: 2.1 | AD10: =AB10*AC10 -> 0 | AJ10: =UPPER(VLOOKUP($AH$6,Itens!$A$7:$J$537,4,0)) -> UN
E11: =C11*B11 -> 0 | F11: =E11-D11 -> 0 | N11: =M11*L11 -> 0 | V11: =U11*T11 -> 0 | AC11: 2.1 | AD11: =AB11*AC11 -> 0 | AJ11: =UPPER(VLOOKUP($AH$6,Itens!$A$7:$J$537,4,0)) -> UN
E12: =C12*B12 -> 0 | F12: =E12-D12 -> 0 | N12: =M12*L12 -> 0 | V12: =U12*T12 -> 0 | AC12: 2.1 | AD12: =AB12*AC12 -> 0 | AJ12: =UPPER(VLOOKUP($AH$6,Itens!$A$7:$J$537,4,0)) -> UN
E13: =C13*B13 -> 0 | F13: =E13-D13 -> 0 | N13: =M13*L13 -> 0 | V13: =U13*T13 -> 0 | AC13: 2.1 | AD13: =AB13*AC13 -> 0 | AJ13: =UPPER(VLOOKUP($AH$6,Itens!$A$7:$J$537,4,0)) -> UN
E14: =C14*B14 -> 0 | F14: =E14-D14 -> 0 | N14: =M14*L14 -> 0 | V14: =U14*T14 -> 0 | AC14: 2.1 | AD14: =AB14*AC14 -> 0 | AJ14: =UPPER(VLOOKUP($AH$6,Itens!$A$7:$J$537,4,0)) -> UN
E15: =C15*B15 -> 0 | F15: =E15-D15 -> 0 | N15: =M15*L15 -> 0 | V15: =U15*T15 -> 0 | AC15: 2.1 | AD15: =AB15*AC15 -> 0 | AJ15: =UPPER(VLOOKUP($AH$6,Itens!$A$7:$J$537,4,0)) -> UN
E16: =C16*B16 -> 0 | F16: =E16-D16 -> 0 | N16: =M16*L16 -> 0 | V16: =U16*T16 -> 0 | AC16: 2.1 | AD16: =AB16*AC16 -> 0 | AJ16: =UPPER(VLOOKUP($AH$6,Itens!$A$7:$J$537,4,0)) -> UN
E17: =C17*B17 -> 0 | F17: =E17-D17 -> 0 | N17: =M17*L17 -> 0 | V17: =U17*T17 -> 0 | AC17: 2.1 | AD17: =AB17*AC17 -> 0 | AJ17: =UPPER(VLOOKUP($AH$6,Itens!$A$7:$J$537,4,0)) -> UN
E18: =C18*B18 -> 0 | F18: =E18-D18 -> 0 | N18: =M18*L18 -> 0 | V18: =U18*T18 -> 0 | AC18: 2.1 | AD18: =AB18*AC18 -> 0 | AJ18: =UPPER(VLOOKUP($AH$6,Itens!$A$7:$J$537,4,0)) -> UN
E19: =C19*B19 -> 0 | F19: =E19-D19 -> 0 | N19: =M19*L19 -> 0 | V19: =U19*T19 -> 0 | AC19: 2.1 | AD19: =AB19*AC19 -> 0 | AJ19: =UPPER(VLOOKUP($AH$6,Itens!$A$7:$J$537,4,0)) -> UN
E20: =C20*B20 -> 0 | F20: =E20-D20 -> 0 | N20: =M20*L20 -> 0 | V20: =U20*T20 -> 0 | AC20: 2.1 | AD20: =AB20*AC20 -> 0 | AJ20: =UPPER(VLOOKUP($AH$6,Itens!$A$7:$J$537,4,0)) -> UN
... E39: =C39*B39 -> 0 | F39: =E39-D39 -> 0 | N39: =M39*L39 -> 0 | V39: =U39*T39 -> 0 | AC39: 2.1 | AD39: =AB39*AC39 -> 0 | AJ39: =UPPER(VLOOKUP($AH$6,Itens!$A$7:$J$537,4,0)) -> UN
A40: Total | F40: =SUM(F8:F39) -> 22.41 | K40: Total | N40: =SUM(N8:N39) -> 0 | S40: Total (dividido por 10) | V40: =SUM(V8:V39)/10 -> 0.394 | AA40: Total (X3) | AD40: =SUM(AD8:AD39)*3 -> 0 | AH40: Total | AI40: =SUM(AI8:AI39) -> 2 | AJ40: =UPPER(AJ8) -> UN

Sheet Itens
B1: A interessada deverá prrencher os campos em amarelo abaixo.
C3: CONSERVAÇÃO PREDIAL | M3: Informar nos campos em amarelo abaixo o desconto para MA e MO. Poderá ser informado desconto diferente ou igual para MA e MO de forma a ajustar o desconto global ao desconto ofertado na licitação. O campo em verde, após o preenchimento do MA, MO e BDI (em sua respectiva aba), deverá refletir o valor de desconto ofertado na Licitação. O valor efetivo de desconto de MA e MO considerando BDI aparecerá nos campos em Azul.
B4: PROPONENTE : | G4: LOTE: | H4: 04 | M4: Material sem BDI | N4: Mão de obra sem BDI
B5: MAFFENG ENGENHARIA E MANUTENÇÃO LTDA | C5: CNPJ: | D5: 33.624.704/0001-94 | I5: DESCONTO: | J5: 0.3114 | M5: 0.2001 | N5: 0.2001 | V5: Não mexer nos dados abaixo. Dados Sem BDI. | AB5: Não mexer nos dados abaixo. Dados com BDI. | AH5: Descontos Calculados
A7: ITEM | C7: QTDE | D7: UN. | E7: UNITÁRIO MATERIAL | F7: UNITÁRIO MÃO DE OBRA | G7: TOTAL UNITÁRIO DO ITEM | H7: TOTAL MATERIAL ROTEIRO | I7: TOTAL MÃO DE OBRA ROTEIRO | J7: TOTAL GERAL ROTEIRO | M7: Desconto Global Calculado com BDI | N7: =1-(J537/AF537) -> -0.14969529 | V7: QTDE | W7: UN. | X7: UNITÁRIO MATERIAL Referência | Y7: UNITÁRIO MÃO DE OBRA Referência | Z7: TOTAL UNITÁRIO DO ITEM Referência | AB7: QTDE | AC7: UN. | AD7: UNITÁRIO MATERIAL Referência | AE7: UNITÁRIO MÃO DE OBRA Referência | AF7: TOTAL UNITÁRIO DO ITEM Referência | AH7: UNITÁRIO MATERIAL Referência | AI7: UNITÁRIO MÃO DE OBRA Referência | AJ7: TOTAL UNITÁRIO DO ITEM Referência
A8: 1 | B8: PRELIMINARES | H8: 805267.07 | I8: 312423.9 | J8: 1117691 | M8: O valor do campo em verde deverá ser igual ao da proposta apresentada.
A9: 1.1 | B9: Chamado | C9: 249 | D9: un | E9: 0 | F9: 86.69 | G9: 86.69 | H9: 0 | I9: 21585.81 | J9: 21585.81 | V9: 392 | W9: un | X9: 0 | Y9: 106.2 | Z9: =SUM(X9:Y9) -> 106.2 | AB9: 392 | AC9: un | AD9: 0 | AE9: 135.41 | AF9: =SUM(AD9:AE9) -> 135.41 | AH9: =IF(E9=0,0,(E9/AD9)-1) -> 0 | AI9: =IF(F9=0,0,(F9/AE9)-1) -> -0.35979617 | AJ9: =IF(G9=0,0,(G9/AF9)-1) -> -0.35979617
A10: 1.2 | B10: Deslocamento | C10: 299981 | D10: km | E10: 1.66 | F10: 0.73 | G10: 2.39 | H10: 497968.46 | I10: 218986.13 | J10: 716954.59 | V10: 200480 | W10: km | X10: 1.89 | Y10: 0.97 | Z10: =SUM(X10:Y10) -> 2.86 | AB10: 200480 | AC10: km | AD10: 2.41 | AE10: 1.24 | AF10: =SUM(AD10:AE10) -> 3.65 | AH10: =IF(E10=0,0,(E10/AD10)-1) -> -0.31120332 | AI10: =IF(F10=0,0,(F10/AE10)-1) -> -0.41129032 | AJ10: =IF(G10=0,0,(G10/AF10)-1) -> -0.34520548
A11: 1.3 | B11: Revisão de instalações | C11: 151 | D11: un | E11: 87.3 | F11: 468.71 | G11: 556.01 | H11: 13182.3 | I11: 70775.21 | J11: 83957.51 | V11: 168 | W11: un | X11: 99.64 | Y11: 430.84 | Z11: =SUM(X11:Y11) -> 530.48 | AB11: 168 | AC11: un | AD11: 127.04 | AE11: 549.32 | AF11: =SUM(AD11:AE11) -> 676.36 | AH11: =IF(E11=0,0,(E11/AD11)-1) -> -0.31281486 | AI11: =IF(F11=0,0,(F11/AE11)-1) -> -0.14674507 | AJ11: =IF(G11=0,0,(G11/AF11)-1) -> -0.17793778
A12: 1.4 | B12: Acompanhamento técnico em Segurança do Trabalho | C12: 1 | D12: un | E12: 0 | F12: 442.2 | G12: 442.2 | H12: 0 | I12: 442.2 | J12: 442.2 | V12: 40 | W12: un | X12: 0 | Y12: 285.92 | Z12: =SUM(X12:Y12) -> 285.92 | AB12: 40 | AC12: un | AD12: 0 | AE12: 364.55 | AF12: =SUM(AD12:AE12) -> 364.55 | AH12: =IF(E12=0,0,(E12/AD12)-1) -> 0 | AI12: =IF(F12=0,0,(F12/AE12)-1) -> 0.21300233 | AJ12: =IF(G12=0,0,(G12/AF12)-1) -> 0.21300233
A13: 1.5 | B13: Hospedagem de equipe técnica - Serviços prolongados | C13: 151 | D13: un | E13: 1947.18 | F13: 0 | G13: 1947.18 | H13: 294024.18 | I13: 0 | J13: 294024.18 | V13: 56 | W13: un | X13: 2222.54 | Y13: 0 | Z13: =SUM(X13:Y13) -> 2222.54 | AB13: 56 | AC13: un | AD13: 2833.74 | AE13: 0 | AF13: =SUM(AD13:AE13) -> 2833.74 | AH13: =IF(E13=0,0,(E13/AD13)-1) -> -0.31285862 | AI13: =IF(F13=0,0,(F13/AE13)-1) -> 0 | AJ13: =IF(G13=0,0,(G13/AF13)-1) -> -0.31285862
A14: 1.6 | B14: Deslocamento Fluvial | C14: 2 | D14: Km | E14: 0.82 | F14: 1.79 | G14: 2.61 | H14: 1.64 | I14: 3.58 | J14: 5.22 | M14: Desconto Calculado Material Efetivo | N14: =IF(M5=0,0,ROUND(AH540,4)) -> -0.3141 | V14: 1 | W14: Km | X14: 0.94 | Y14: 2.02 | Z14: =SUM(X14:Y14) -> 2.96 | AB14: 1 | AC14: Km | AD14: 1.2 | AE14: 2.58 | AF14: =SUM(AD14:AE14) -> 3.78 | AH14: =IF(E14=0,0,(E14/AD14)-1) -> -0.31666667 | AI14: =IF(F14=0,0,(F14/AE14)-1) -> -0.30620155 | AJ14: =IF(G14=0,0,(G14/AF14)-1) -> -0.30952381
A15: 1.7 | B15: Laudo técnico fotográfico - Elementos de Sinalização - Padrão BB | C15: 1 | D15: UN | E15: 90.49 | F15: 630.97 | G15: 721.46 | H15: 90.49 | I15: 630.97 | J15: 721.46 | M15: Desconto Calculado Mão de Obra Efetivo | N15: =IF(N5=0,0,ROUND(AI540,4)) -> -0.0901 | V15: 1 | W15: UN | X15: 103.29 | Y15: 734.85 | Z15: =SUM(X15:Y15) -> 838.14 | AB15: 1 | AC15: UN | AD15: 131.69 | AE15: 936.93 | AF15: =SUM(AD15:AE15) -> 1068.62 | AH15: =IF(E15=0,0,(E15/AD15)-1) -> -0.31285595 | AI15: =IF(F15=0,0,(F15/AE15)-1) -> -0.32655588 | AJ15: =IF(G15=0,0,(G15/AF15)-1) -> -0.32486759
A16: 2 | B16: IMPLANTAÇÃO / ADMINISTRAÇÃO | H16: 158849.08 | I16: 206579.93 | J16: 365429.01 | M16: Os valores acima consideram o valor informado na aba BDI. | AH16: =IF(E16=0,0,(E16/AD16)-1) -> 0 | AI16: =IF(F16=0,0,(F16/AE16)-1) -> 0 | AJ16: =IF(G16=0,0,(G16/AF16)-1) -> 0
A17: 2.1 | B17: Demolição manual de concreto simples | C17: 27 | D17: m³ | E17: 0 | F17: 347.88 | G17: 347.88 | H17: 0 | I17: 9392.76 | J17: 9392.76 | V17: 7 | W17: m³ | X17: 0 | Y17: 288.91 | Z17: =SUM(X17:Y17) -> 288.91 | AB17: 7 | AC17: m³ | AD17: 0 | AE17: 368.36 | AF17: =SUM(AD17:AE17) -> 368.36 | AH17: =IF(E17=0,0,(E17/AD17)-1) -> 0 | AI17: =IF(F17=0,0,(F17/AE17)-1) -> -0.055597785 | AJ17: =IF(G17=0,0,(G17/AF17)-1) -> -0.055597785
A18: 2.2 | B18: Demolição manual de alvenaria de elevação ou elemento vazado, incluindo revestimento | C18: 51 | D18: m³ | E18: 0 | F18: 80.28 | G18: 80.28 | H18: 0 | I18: 4094.28 | J18: 4094.28 | M18: A interessada pode alterar o BDI na respectiva aba da planilha eletrônica. A alteração do BDI afeta o desconto calculado efetivo de material e de mão de obra. O valor do BDI deverá ser igual ao da proposta a ser apresentada. | V18: 23 | W18: m³ | X18: 0 | Y18: 66.67 | Z18: =SUM(X18:Y18) -> 66.67 | AB18: 23 | AC18: m³ | AD18: 0 | AE18: 85 | AF18: =SUM(AD18:AE18) -> 85 | AH18: =IF(E18=0,0,(E18/AD18)-1) -> 0 | AI18: =IF(F18=0,0,(F18/AE18)-1) -> -0.055529412 | AJ18: =IF(G18=0,0,(G18/AF18)-1) -> -0.055529412
A19: 2.3 | B19: Demolição manual de revestimento em massa de parede ou teto ou Dry-Wall | C19: 362 | D19: m³ | E19: 0 | F19: 8.52 | G19: 8.52 | H19: 0 | I19: 3084.24 | J19: 3084.24 | V19: 116 | W19: m³ | X19: 0 | Y19: 7.43 | Z19: =SUM(X19:Y19) -> 7.43 | AB19: 116 | AC19: m³ | AD19: 0 | AE19: 9.47 | AF19: =SUM(AD19:AE19) -> 9.47 | AH19: =IF(E19=0,0,(E19/AD19)-1) -> 0 | AI19: =IF(F19=0,0,(F19/AE19)-1) -> -0.10031679 | AJ19: =IF(G19=0,0,(G19/AF19)-1) -> -0.10031679
A20: 2.4 | B20: Demolição de pisos em geral (ladrilho hidráulico, camada de enchimento, cerâmica, porcelanato, mármore, granito, pedra e madeira) - Manual | C20: 293 | D20: m² | E20: 0 | F20: 37.46 | G20: 37.46 | H20: 0 | I20: 10975.78 | J20: 10975.78 | V20: 35 | W20: m² | X20: 0 | Y20: 31.11 | Z20: =SUM(X20:Y20) -> 31.11 | AB20: 35 | AC20: m² | AD20: 0 | AE20: 39.67 | AF20: =SUM(AD20:AE20) -> 39.67 | AH20: =IF(E20=0,0,(E20/AD20)-1) -> 0 | AI20: =IF(F20=0,0,(F20/AE20)-1) -> -0.055709604 | AJ20: =IF(G20=0,0,(G20/AF20)-1) -> -0.055709604
A21: 2.5 | B21: Demolição de pisos em geral (ladrilho hidráulico, camada de enchimento, cerâmica, porcelanato, mármore, granito, pedra e madeira) - Mecanizado | C21: 139 | D21: m² | E21: 26.28 | F21: 18.73 | G21: 45.01 | H21: 3652.92 | I21: 2603.47 | J21: 6256.39 | V21: 73 | W21: m² | X21: 23.22 | Y21: 15.56 | Z21: =SUM(X21:Y21) -> 38.78 | AB21: 73 | AC21: m² | AD21: 29.61 | AE21: 19.84 | AF21: =SUM(AD21:AE21) -> 49.45 | AH21: =IF(E21=0,0,(E21/AD21)-1) -> -0.11246201 | AI21: =IF(F21=0,0,(F21/AE21)-1) -> -0.055947581 | AJ21: =IF(G21=0,0,(G21/AF21)-1) -> -0.089787664
A22: 2.6 | B22: Demolição de pavimentação com pré-moldado de concreto ou intertravado | C22: 6 | D22: m² | E22: 0 | F22: 18.73 | G22: 18.73 | H22: 0 | I22: 112.38 | J22: 112.38 | V22: 1 | W22: m² | X22: 0 | Y22: 15.56 | Z22: =SUM(X22:Y22) -> 15.56 | AB22: 1 | AC22: m² | AD22: 0 | AE22: 19.84 | AF22: =SUM(AD22:AE22) -> 19.84 | AH22: =IF(E22=0,0,(E22/AD22)-1) -> 0 | AI22: =IF(F22=0,0,(F22/AE22)-1) -> -0.055947581 | AJ22: =IF(G22=0,0,(G22/AF22)-1) -> -0.055947581
A23: 2.7 | B23: Demolição de piso cimentado sobre lastro de concreto | C23: 35 | D23: m² | E23: 0 | F23: 34.79 | G23: 34.79 | H23: 0 | I23: 1217.65 | J23: 1217.65 | V23: 1 | W23: m² | X23: 0 | Y23: 28.89 | Z23: =SUM(X23:Y23) -> 28.89 | AB23: 1 | AC23: m² | AD23: 0 | AE23: 36.83 | AF23: =SUM(AD23:AE23) -> 36.83 | AH23: =IF(E23=0,0,(E23/AD23)-1) -> 0 | AI23: =IF(F23=0,0,(F23/AE23)-1) -> -0.055389628 | AJ23: =IF(G23=0,0,(G23/AF23)-1) -> -0.055389628
A24: 2.8 | B24: Demolição manual de forro, inclusive sistema de fixação/tarugamento | C24: 939 | D24: m² | E24: 0 | F24: 10.71 | G24: 10.71 | H24: 0 | I24: 10056.69 | J24: 10056.69 | M24: A interessada pode utilizar modelo próprio de planilha para cálculo,entretanto,a planilha final a ser apresentada juntamente com a proposta, deverá ter a mesma formatação do orçamento estimado que compõe a licitação. | V24: 850 | W24: m² | X24: 0 | Y24: 8.89 | Z24: =SUM(X24:Y24) -> 8.89 | AB24: 850 | AC24: m² | AD24: 0 | AE24: 11.33 | AF24: =SUM(AD24:AE24) -> 11.33 | AH24: =IF(E24=0,0,(E24/AD24)-1) -> 0 | AI24: =IF(F24=0,0,(F24/AE24)-1) -> -0.054721977 | AJ24: =IF(G24=0,0,(G24/AF24)-1) -> -0.054721977
A25: 2.9 | B25: Demolição de contrapiso/argamassa regularizante, isolante ou protetora | C25: 203 | D25: m² | E25: 0 | F25: 13.38 | G25: 13.38 | H25: 0 | I25: 2716.14 | J25: 2716.14 | V25: 6 | W25: m² | X25: 0 | Y25: 11.11 | Z25: =SUM(X25:Y25) -> 11.11 | AB25: 6 | AC25: m² | AD25: 0 | AE25: 14.17 | AF25: =SUM(AD25:AE25) -> 14.17 | AH25: =IF(E25=0,0,(E25/AD25)-1) -> 0 | AI25: =IF(F25=0,0,(F25/AE25)-1) -> -0.055751588 | AJ25: =IF(G25=0,0,(G25/AF25)-1) -> -0.055751588
A26: 2.10 | B26: Demolição de estrutura em madeira para telhado | C26: 61 | D26: m² | E26: 0 | F26: 36.98 | G26: 36.98 | H26: 0 | I26: 2255.78 | J26: 2255.78 | V26: 1 | W26: m² | X26: 0 | Y26: 31.33 | Z26: =SUM(X26:Y26) -> 31.33 | AB26: 1 | AC26: m² | AD26: 0 | AE26: 39.95 | AF26: =SUM(AD26:AE26) -> 39.95 | AH26: =IF(E26=0,0,(E26/AD26)-1) -> 0 | AI26: =IF(F26=0,0,(F26/AE26)-1) -> -0.074342929 | AJ26: =IF(G26=0,0,(G26/AF26)-1) -> -0.074342929
A27: 2.11 | B27: Retirada de cumeeira, espigão, rufo, calha ou chapim, perfil qualquer | C27: 152 | D27: m | E27: 0 | F27: 17.27 | G27: 17.27 | H27: 0 | I27: 2625.04 | J27: 2625.04 | V27: 203 | W27: m | X27: 0 | Y27: 15.47 | Z27: =SUM(X27:Y27) -> 15.47 | AB27: 203 | AC27: m | AD27: 0 | AE27: 19.72 | AF27: =SUM(AD27:AE27) -> 19.72 | AH27: =IF(E27=0,0,(E27/AD27)-1) -> 0 | AI27: =IF(F27=0,0,(F27/AE27)-1) -> -0.12423935 | AJ27: =IF(G27=0,0,(G27/AF27)-1) -> -0.12423935
A28: 2.12 | B28: Retirada de piso tátil com limpeza | C28: 814 | D28: m² | E28: 11.07 | F28: 28.13 | G28: 39.2 | H28: 9010.98 | I28: 22897.82 | J28: 31908.8 | V28: 3400 | W28: m² | X28: 19.61 | Y28: 25.1 | Z28: =SUM(X28:Y28) -> 44.71 | AB28: 3400 | AC28: m² | AD28: 25 | AE28: 32 | AF28: =SUM(AD28:AE28) -> 57 | AH28: =IF(E28=0,0,(E28/AD28)-1) -> -0.5572 | AI28: =IF(F28=0,0,(F28/AE28)-1) -> -0.1209375 | AJ28: =IF(G28=0,0,(G28/AF28)-1) -> -0.3122807
A29: 2.13 | B29: Remoção de revestimento de piso de carpete ou manta vinílica | C29: 2344 | D29: m² | E29: 11.07 | F29: 14.23 | G29: 25.3 | H29: 25948.08 | I29: 33355.12 | J29: 59303.2 | V29: 1913 | W29: m² | X29: 19.61 | Y29: 12.91 | Z29: =SUM(X29:Y29) -> 32.52 | AB29: 1913 | AC29: m² | AD29: 25 | AE29: 16.46 | AF29: =SUM(AD29:AE29) -> 41.46 | AH29: =IF(E29=0,0,(E29/AD29)-1) -> -0.5572 | AI29: =IF(F29=0,0,(F29/AE29)-1) -> -0.13547995 | AJ29: =IF(G29=0,0,(G29/AF29)-1) -> -0.38977328
A30: 2.14 | B30: Ajuste de Piso Elevado (remoção e recolocação de revestimentos e placas do piso inclusive) | C30: 72 | D30: m² | E30: 7.86 | F30: 74.09 | G30: 81.95 | H30: 565.92 | I30: 5334.48 | J30: 5900.4 | V30: 375 | W30: m² | X30: 9.93 | Y30: 66.6 | Z30: =SUM(X30:Y30) -> 76.53 | AB30: 375 | AC30: m² | AD30: 12.66 | AE30: 84.92 | AF30: =SUM(AD30:AE30) -> 97.58 | AH30: =IF(E30=0,0,(E30/AD30)-1) -> -0.37914692 | AI30: =IF(F30=0,0,(F30/AE30)-1) -> -0.12753179 | AJ30: =IF(G30=0,0,(G30/AF30)-1) -> -0.16017627
A31: 2.15 | B31: Retirada de piso elevado, inclusive estrutura de sustentação | C31: 180 | D31: m² | E31: 0 | F31: 34.13 | G31: 34.13 | H31: 0 | I31: 6143.4 | J31: 6143.4 | V31: 410 | W31: m² | X31: 0 | Y31: 28.92 | Z31: =SUM(X31:Y31) -> 28.92 | AB31: 410 | AC31: m² | AD31: 0 | AE31: 36.87 | AF31: =SUM(AD31:AE31) -> 36.87 | AH31: =IF(E31=0,0,(E31/AD31)-1) -> 0 | AI31: =IF(F31=0,0,(F31/AE31)-1) -> -0.074315161 | AJ31: =IF(G31=0,0,(G31/AF31)-1) -> -0.074315161
A32: 2.16 | B32: Reinstalação de piso elevado proveniente de reaproveitamento, incluso material | C32: 18 | D32: m² | E32: 1.55 | F32: 80.31 | G32: 81.86 | H32: 27.9 | I32: 1445.58 | J32: 1473.48 | V32: 1 | W32: m² | X32: 1.78 | Y32: 72.09 | Z32: =SUM(X32:Y32) -> 73.87 | AB32: 1 | AC32: m² | AD32: 2.27 | AE32: 91.91 | AF32: =SUM(AD32:AE32) -> 94.18 | AH32: =IF(E32=0,0,(E32/AD32)-1) -> -0.31718062 | AI32: =IF(F32=0,0,(F32/AE32)-1) -> -0.12621042 | AJ32: =IF(G32=0,0,(G32/AF32)-1) -> -0.13081334
A33: 2.17 | B33: Retirada ou recolocação de vidro | C33: 517 | D33: m² | E33: 11.3 | F33: 19.12 | G33: 30.42 | H33: 5842.1 | I33: 9885.04 | J33: 15727.14 | V33: 235 | W33: m² | X33: 26.9 | Y33: 16.45 | Z33: =SUM(X33:Y33) -> 43.35 | AB33: 235 | AC33: m² | AD33: 34.3 | AE33: 20.97 | AF33: =SUM(AD33:AE33) -> 55.27 | AH33: =IF(E33=0,0,(E33/AD33)-1) -> -0.67055394 | AI33: =IF(F33=0,0,(F33/AE33)-1) -> -0.088221268 | AJ33: =IF(G33=0,0,(G33/AF33)-1) -> -0.449611
A34: 2.18 | B34: Remoção de entulho com caçamba metálica, inclusive limpeza, transporte, carga, descarga e descarte conforme legislação ambiental - Material de descarte (alvenaria, estruturas metálicas, madeiramento, revestimentos cerâmicos, gesso, dry-wall, entre outros) | C34: 1000 | D34: m³ | E34: 55.11 | F34: 16.81 | G34: 71.92 | H34: 55110 | I34: 16810 | J34: 71920 | V34: 17 | W34: m³ | X34: 62.9 | Y34: 13.69 | Z34: =SUM(X34:Y34) -> 76.59 | AB34: 17 | AC34: m³ | AD34: 80.2 | AE34: 17.45 | AF34: =SUM(AD34:AE34) -> 97.65 | AH34: =IF(E34=0,0,(E34/AD34)-1) -> -0.31284289 | AI34: =IF(F34=0,0,(F34/AE34)-1) -> -0.036676218 | AJ34: =IF(G34=0,0,(G34/AF34)-1) -> -0.26349206
A35: 2.19 | B35: Remoção / Remanejamento de placa aérea | C35: 215 | D35: un | E35: 3.43 | F35: 51.72 | G35: 55.15 | H35: 737.45 | I35: 11119.8 | J35: 11857.25 | V35: 72 | W35: un | X35: 6.88 | Y35: 43.2 | Z35: =SUM(X35:Y35) -> 50.08 | AB35: 72 | AC35: un | AD35: 8.77 | AE35: 55.08 | AF35: =SUM(AD35:AE35) -> 63.85 | AH35: =IF(E35=0,0,(E35/AD35)-1) -> -0.60889396 | AI35: =IF(F35=0,0,(F35/AE35)-1) -> -0.061002179 | AJ35: =IF(G35=0,0,(G35/AF35)-1) -> -0.13625685
A36: 2.20 | B36: Andaime tubular fachadeiro | C36: 291 | D36: m²/mês | E36: 18.95 | F36: 8.34 | G36: 27.29 | H36: 5514.45 | I36: 2426.94 | J36: 7941.39 | V36: 1033 | W36: m²/mês | X36: 17 | Y36: 8.01 | Z36: =SUM(X36:Y36) -> 25.01 | AB36: 1033 | AC36: m²/mês | AD36: 21.68 | AE36: 10.21 | AF36: =SUM(AD36:AE36) -> 31.89 | AH36: =IF(E36=0,0,(E36/AD36)-1) -> -0.12592251 | AI36: =IF(F36=0,0,(F36/AE36)-1) -> -0.18315377 | AJ36: =IF(G36=0,0,(G36/AF36)-1) -> -0.14424585
... A52: 2.36 | B52: Tela para Andaime | C52: 1 | D52: m² | E52: 2.3 | F52: 3.79 | G52: 6.09 | H52: 2.3 | I52: 3.79 | J52: 6.09 | V52: 1 | W52: m² | X52: 2.71 | Y52: 3.44 | Z52: =SUM(X52:Y52) -> 6.15 | AB52: 1 | AC52: m² | AD52: 3.46 | AE52: 4.39 | AF52: =SUM(AD52:AE52) -> 7.85 | AH52: =IF(E52=0,0,(E52/AD52)-1) -> -0.33526012 | AI52: =IF(F52=0,0,(F52/AE52)-1) -> -0.13667426 | AJ52: =IF(G52=0,0,(G52/AF52)-1) -> -0.22420382
A53: 3 | B53: MOVIMENTO DE TERRA | H53: 2.07 | I53: 117.21 | J53: 119.28 | AH53: =IF(E53=0,0,(E53/AD53)-1) -> 0 | AI53: =IF(F53=0,0,(F53/AE53)-1) -> 0 | AJ53: =IF(G53=0,0,(G53/AF53)-1) -> 0
A54: 3.1 | B54: Escavação Manual em Solo | C54: 1 | D54: m³ | E54: 0 | F54: 96.06 | G54: 96.06 | H54: 0 | I54: 96.06 | J54: 96.06 | V54: 1 | W54: m³ | X54: 0 | Y54: 78.2 | Z54: =SUM(X54:Y54) -> 78.2 | AB54: 1 | AC54: m³ | AD54: 0 | AE54: 99.71 | AF54: =SUM(AD54:AE54) -> 99.71 | AH54: =IF(E54=0,0,(E54/AD54)-1) -> 0 | AI54: =IF(F54=0,0,(F54/AE54)-1) -> -0.036606158 | AJ54: =IF(G54=0,0,(G54/AF54)-1) -> -0.036606158
A55: 3.2 | B55: Reaterro/Aterro Manual de Solo | C55: 1 | D55: m³ | E55: 2.07 | F55: 21.15 | G55: 23.22 | H55: 2.07 | I55: 21.15 | J55: 23.22 | V55: 1 | W55: m³ | X55: 2.3 | Y55: 17.22 | Z55: =SUM(X55:Y55) -> 19.52 | AB55: 1 | AC55: m³ | AD55: 2.93 | AE55: 21.96 | AF55: =SUM(AD55:AE55) -> 24.89 | AH55: =IF(E55=0,0,(E55/AD55)-1) -> -0.29351536 | AI55: =IF(F55=0,0,(F55/AE55)-1) -> -0.036885246 | AJ55: =IF(G55=0,0,(G55/AF55)-1) -> -0.067095219
A56: 4 | B56: FUNDAÇÃO | H56: 0 | I56: 0 | J56: 0 | AH56: =IF(E56=0,0,(E56/AD56)-1) -> 0 | AI56: =IF(F56=0,0,(F56/AE56)-1) -> 0 | AJ56: =IF(G56=0,0,(G56/AF56)-1) -> 0
A57: 5 | B57: ESTRUTURA | H57: 17598.69 | I57: 6394.02 | J57: 23992.71 | AH57: =IF(E57=0,0,(E57/AD57)-1) -> 0 | AI57: =IF(F57=0,0,(F57/AE57)-1) -> 0 | AJ57: =IF(G57=0,0,(G57/AF57)-1) -> 0
A58: 5.1 | B58: Base de concreto para fixação de TAA/TTE | C58: 9 | D58: m³ | E58: 705.92 | F58: 66.13 | G58: 772.05 | H58: 6353.28 | I58: 595.17 | J58: 6948.45 | V58: 1 | W58: m³ | X58: 991.66 | Y58: 55.57 | Z58: =SUM(X58:Y58) -> 1047.23 | AB58: 1 | AC58: m³ | AD58: 1264.37 | AE58: 70.85 | AF58: =SUM(AD58:AE58) -> 1335.22 | AH58: =IF(E58=0,0,(E58/AD58)-1) -> -0.44168242 | AI58: =IF(F58=0,0,(F58/AE58)-1) -> -0.066619619 | AJ58: =IF(G58=0,0,(G58/AF58)-1) -> -0.42178068
A59: 5.2 | B59: Montagem e Desmontagem de escoramento em madeira. | C59: 33 | D59: m² | E59: 132.78 | F59: 65.11 | G59: 197.89 | H59: 4381.74 | I59: 2148.63 | J59: 6530.37 | V59: 1 | W59: m² | X59: 169.24 | Y59: 62.02 | Z59: =SUM(X59:Y59) -> 231.26 | AB59: 1 | AC59: m² | AD59: 215.78 | AE59: 79.08 | AF59: =SUM(AD59:AE59) -> 294.86 | AH59: =IF(E59=0,0,(E59/AD59)-1) -> -0.38465103 | AI59: =IF(F59=0,0,(F59/AE59)-1) -> -0.17665655 | AJ59: =IF(G59=0,0,(G59/AF59)-1) -> -0.32886794
A60: 5.3 | B60: Montagem e Desmontagem de escoramento metálico. | C60: 27 | D60: m² | E60: 97.55 | F60: 56.28 | G60: 153.83 | H60: 2633.85 | I60: 1519.56 | J60: 4153.41 | V60: 1 | W60: m² | X60: 105.41 | Y60: 53.62 | Z60: =SUM(X60:Y60) -> 159.03 | AB60: 1 | AC60: m² | AD60: 134.4 | AE60: 68.37 | AF60: =SUM(AD60:AE60) -> 202.77 | AH60: =IF(E60=0,0,(E60/AD60)-1) -> -0.27418155 | AI60: =IF(F60=0,0,(F60/AE60)-1) -> -0.17683194 | AJ60: =IF(G60=0,0,(G60/AF60)-1) -> -0.2413572
A61: 5.4 | B61: Concreto fck = 15 MPa, controle tipo "B", e = 10 cm, e armado com tela de aço CA-60 | C61: 63 | D61: m² | E61: 67.14 | F61: 33.82 | G61: 100.96 | H61: 4229.82 | I61: 2130.66 | J61: 6360.48 | V61: 1 | W61: m² | X61: 89.86 | Y61: 28.72 | Z61: =SUM(X61:Y61) -> 118.58 | AB61: 1 | AC61: m² | AD61: 114.57 | AE61: 36.62 | AF61: =SUM(AD61:AE61) -> 151.19 | AH61: =IF(E61=0,0,(E61/AD61)-1) -> -0.41398272 | AI61: =IF(F61=0,0,(F61/AE61)-1) -> -0.07646095 | AJ61: =IF(G61=0,0,(G61/AF61)-1) -> -0.33223097
A62: 6 | B62: ALVENARIAS E OUTRAS VEDAÇÕES | H62: 24987.5 | I62: 10927.61 | J62: 35915.11 | AH62: =IF(E62=0,0,(E62/AD62)-1) -> 0 | AI62: =IF(F62=0,0,(F62/AE62)-1) -> 0 | AJ62: =IF(G62=0,0,(G62/AF62)-1) -> 0
A63: 6.1 | B63: Alvenaria com tijolo cerâmico furado | C63: 124 | D63: m² | E63: 25.27 | F63: 47.3 | G63: 72.57 | H63: 3133.48 | I63: 5865.2 | J63: 8998.68 | V63: 43 | W63: m² | X63: 28.24 | Y63: 43.13 | Z63: =SUM(X63:Y63) -> 71.37 | AB63: 43 | AC63: m² | AD63: 36.01 | AE63: 54.99 | AF63: =SUM(AD63:AE63) -> 91 | AH63: =IF(E63=0,0,(E63/AD63)-1) -> -0.29825049 | AI63: =IF(F63=0,0,(F63/AE63)-1) -> -0.13984361 | AJ63: =IF(G63=0,0,(G63/AF63)-1) -> -0.20252747
A64: 6.2 | B64: Parede de gesso em placas duplas acartonado dry wall - inclusive para ambientes úmidos - RU | C64: 167 | D64: m² | E64: 120.02 | F64: 14.23 | G64: 134.25 | H64: 20043.34 | I64: 2376.41 | J64: 22419.75 | V64: 70 | W64: m² | X64: 148.48 | Y64: 13.89 | Z64: =SUM(X64:Y64) -> 162.37 | AB64: 70 | AC64: m² | AD64: 189.31 | AE64: 17.71 | AF64: =SUM(AD64:AE64) -> 207.02 | AH64: =IF(E64=0,0,(E64/AD64)-1) -> -0.36601342 | AI64: =IF(F64=0,0,(F64/AE64)-1) -> -0.19649915 | AJ64: =IF(G64=0,0,(G64/AF64)-1) -> -0.35151193
A65: 6.3 | B65: Rasgo e fechamento em alvenaria e piso | C65: 79 | D65: m | E65: 22.92 | F65: 34 | G65: 56.92 | H65: 1810.68 | I65: 2686 | J65: 4496.68 | V65: 48 | W65: m | X65: 26.3 | Y65: 30.01 | Z65: =SUM(X65:Y65) -> 56.31 | AB65: 48 | AC65: m | AD65: 33.53 | AE65: 38.26 | AF65: =SUM(AD65:AE65) -> 71.79 | AH65: =IF(E65=0,0,(E65/AD65)-1) -> -0.31643305 | AI65: =IF(F65=0,0,(F65/AE65)-1) -> -0.11134344 | AJ65: =IF(G65=0,0,(G65/AF65)-1) -> -0.20713191
A66: 7 | B66: COBERTURA | H66: 65859.38 | I66: 25189.09 | J66: 91048.47 | AH66: =IF(E66=0,0,(E66/AD66)-1) -> 0 | AI66: =IF(F66=0,0,(F66/AE66)-1) -> 0 | AJ66: =IF(G66=0,0,(G66/AF66)-1) -> 0
A67: 7.1 | B67: Cobertura com telha de alumínio envernizada ou pintada, e=0,5 mm | C67: 266 | D67: m² | E67: 77.68 | F67: 14.53 | G67: 92.21 | H67: 20662.88 | I67: 3864.98 | J67: 24527.86 | V67: 40 | W67: m² | X67: 113.88 | Y67: 13.78 | Z67: =SUM(X67:Y67) -> 127.66 | AB67: 40 | AC67: m² | AD67: 145.2 | AE67: 17.57 | AF67: =SUM(AD67:AE67) -> 162.77 | AH67: =IF(E67=0,0,(E67/AD67)-1) -> -0.46501377 | AI67: =IF(F67=0,0,(F67/AE67)-1) -> -0.1730222 | AJ67: =IF(G67=0,0,(G67/AF67)-1) -> -0.43349512
A68: 7.2 | B68: Cobertura em telha com isolamento termoacustico em espuma rígida de poliuretano (PU) injetado | C68: 12 | D68: m² | E68: 149.3 | F68: 11.63 | G68: 160.93 | H68: 1791.6 | I68: 139.56 | J68: 1931.16 | V68: 38 | W68: m² | X68: 137.6 | Y68: 10.47 | Z68: =SUM(X68:Y68) -> 148.07 | AB68: 38 | AC68: m² | AD68: 175.44 | AE68: 13.35 | AF68: =SUM(AD68:AE68) -> 188.79 | AH68: =IF(E68=0,0,(E68/AD68)-1) -> -0.14899681 | AI68: =IF(F68=0,0,(F68/AE68)-1) -> -0.12883895 | AJ68: =IF(G68=0,0,(G68/AF68)-1) -> -0.14757138
A69: 7.3 | B69: Cumeeira em chapa metálica | C69: 1 | D69: m | E69: 110.07 | F69: 6.34 | G69: 116.41 | H69: 110.07 | I69: 6.34 | J69: 116.41 | V69: 1 | W69: m | X69: 126.88 | Y69: 5.71 | Z69: =SUM(X69:Y69) -> 132.59 | AB69: 1 | AC69: m | AD69: 161.77 | AE69: 7.28 | AF69: =SUM(AD69:AE69) -> 169.05 | AH69: =IF(E69=0,0,(E69/AD69)-1) -> -0.31958954 | AI69: =IF(F69=0,0,(F69/AE69)-1) -> -0.12912088 | AJ69: =IF(G69=0,0,(G69/AF69)-1) -> -0.31138716
A70: 7.4 | B70: Cobertura com telha cerâmica, incluso transporte vertical | C70: 33 | D70: m² | E70: 45.5 | F70: 12.51 | G70: 58.01 | H70: 1501.5 | I70: 412.83 | J70: 1914.33 | V70: 72 | W70: m² | X70: 41.46 | Y70: 10.97 | Z70: =SUM(X70:Y70) -> 52.43 | AB70: 72 | AC70: m² | AD70: 52.86 | AE70: 13.99 | AF70: =SUM(AD70:AE70) -> 66.85 | AH70: =IF(E70=0,0,(E70/AD70)-1) -> -0.13923572 | AI70: =IF(F70=0,0,(F70/AE70)-1) -> -0.10578985 | AJ70: =IF(G70=0,0,(G70/AF70)-1) -> -0.13223635
A71: 7.5 | B71: Cumeeira para telha cerâmica emboçada com argamassa | C71: 11 | D71: m | E71: 19.06 | F71: 26.93 | G71: 45.99 | H71: 209.66 | I71: 296.23 | J71: 505.89 | V71: 21 | W71: m | X71: 17.83 | Y71: 24.21 | Z71: =SUM(X71:Y71) -> 42.04 | AB71: 21 | AC71: m | AD71: 22.73 | AE71: 30.87 | AF71: =SUM(AD71:AE71) -> 53.6 | AH71: =IF(E71=0,0,(E71/AD71)-1) -> -0.16146062 | AI71: =IF(F71=0,0,(F71/AE71)-1) -> -0.12763201 | AJ71: =IF(G71=0,0,(G71/AF71)-1) -> -0.14197761
A72: 7.6 | B72: Cumeeira universal para telhado de fibrocimento, e=6mm | C72: 57 | D72: m | E72: 64.22 | F72: 30.37 | G72: 94.59 | H72: 3660.54 | I72: 1731.09 | J72: 5391.63 | V72: 57 | W72: m | X72: 72.92 | Y72: 25.66 | Z72: =SUM(X72:Y72) -> 98.58 | AB72: 57 | AC72: m | AD72: 92.97 | AE72: 32.72 | AF72: =SUM(AD72:AE72) -> 125.69 | AH72: =IF(E72=0,0,(E72/AD72)-1) -> -0.30923954 | AI72: =IF(F72=0,0,(F72/AE72)-1) -> -0.071821516 | AJ72: =IF(G72=0,0,(G72/AF72)-1) -> -0.24743416
A73: 7.7 | B73: Cobertura com telha de fibrocimento, e = 6 mm, | C73: 250 | D73: m² | E73: 34.63 | F73: 7.74 | G73: 42.37 | H73: 8657.5 | I73: 1935 | J73: 10592.5 | V73: 272 | W73: m² | X73: 38.05 | Y73: 6.9 | Z73: =SUM(X73:Y73) -> 44.95 | AB73: 272 | AC73: m² | AD73: 48.51 | AE73: 8.8 | AF73: =SUM(AD73:AE73) -> 57.31 | AH73: =IF(E73=0,0,(E73/AD73)-1) -> -0.28612657 | AI73: =IF(F73=0,0,(F73/AE73)-1) -> -0.12045455 | AJ73: =IF(G73=0,0,(G73/AF73)-1) -> -0.26068749
A74: 7.8 | B74: Calha de chapa galvanizada nº 24 desenvolvimento 33 cm | C74: 144 | D74: m | E74: 44.55 | F74: 12.35 | G74: 56.9 | H74: 6415.2 | I74: 1778.4 | J74: 8193.6 | V74: 68 | W74: m | X74: 55.48 | Y74: 10.96 | Z74: =SUM(X74:Y74) -> 66.44 | AB74: 68 | AC74: m | AD74: 70.74 | AE74: 13.97 | AF74: =SUM(AD74:AE74) -> 84.71 | AH74: =IF(E74=0,0,(E74/AD74)-1) -> -0.37022901 | AI74: =IF(F74=0,0,(F74/AE74)-1) -> -0.11596278 | AJ74: =IF(G74=0,0,(G74/AF74)-1) -> -0.32829654
A75: 7.9 | B75: Rufo de chapa de aço galvanizado com desenvolvimento até 50 cm | C75: 93 | D75: m | E75: 38.97 | F75: 8.36 | G75: 47.33 | H75: 3624.21 | I75: 777.48 | J75: 4401.69 | V75: 184 | W75: m | X75: 48.39 | Y75: 7.37 | Z75: =SUM(X75:Y75) -> 55.76 | AB75: 184 | AC75: m | AD75: 61.7 | AE75: 9.4 | AF75: =SUM(AD75:AE75) -> 71.1 | AH75: =IF(E75=0,0,(E75/AD75)-1) -> -0.36839546 | AI75: =IF(F75=0,0,(F75/AE75)-1) -> -0.1106383 | AJ75: =IF(G75=0,0,(G75/AF75)-1) -> -0.33431786
A76: 7.10 | B76: Chapim de chapa de aço galvanizado nº 24 desenvolvimento 33 cm | C76: 18 | D76: m | E76: 47.67 | F76: 11.87 | G76: 59.54 | H76: 858.06 | I76: 213.66 | J76: 1071.72 | V76: 1 | W76: m | X76: 61.49 | Y76: 10.42 | Z76: =SUM(X76:Y76) -> 71.91 | AB76: 1 | AC76: m | AD76: 78.4 | AE76: 13.29 | AF76: =SUM(AD76:AE76) -> 91.69 | AH76: =IF(E76=0,0,(E76/AD76)-1) -> -0.39196429 | AI76: =IF(F76=0,0,(F76/AE76)-1) -> -0.10684725 | AJ76: =IF(G76=0,0,(G76/AF76)-1) -> -0.35063802
A77: 7.11 | B77: Cobertura com telha de fibrocimento estrutural, com recobrimento longitudinal | C77: 162 | D77: m² | E77: 80.86 | F77: 31.3 | G77: 112.16 | H77: 13099.32 | I77: 5070.6 | J77: 18169.92 | V77: 5 | W77: m² | X77: 85.91 | Y77: 27.15 | Z77: =SUM(X77:Y77) -> 113.06 | AB77: 5 | AC77: m² | AD77: 109.54 | AE77: 34.62 | AF77: =SUM(AD77:AE77) -> 144.16 | AH77: =IF(E77=0,0,(E77/AD77)-1) -> -0.26182217 | AI77: =IF(F77=0,0,(F77/AE77)-1) -> -0.095898325 | AJ77: =IF(G77=0,0,(G77/AF77)-1) -> -0.22197558
A78: 7.12 | B78: Estrutura de madeira para telha cerâmica, fibrocimento ou de concreto | C78: 73 | D78: m² | E78: 70.16 | F78: 122.06 | G78: 192.22 | H78: 5121.68 | I78: 8910.38 | J78: 14032.06 | V78: 1 | W78: m² | X78: 84.07 | Y78: 110.51 | Z78: =SUM(X78:Y78) -> 194.58 | AB78: 1 | AC78: m² | AD78: 107.19 | AE78: 140.9 | AF78: =SUM(AD78:AE78) -> 248.09 | AH78: =IF(E78=0,0,(E78/AD78)-1) -> -0.34546133 | AI78: =IF(F78=0,0,(F78/AE78)-1) -> -0.13371185 | AJ78: =IF(G78=0,0,(G78/AF78)-1) -> -0.22520053
... A81: 7.15 | B81: Reparo emergencial de telhado e calhas | C81: 1 | D81: un | E81: 10.35 | F81: 7.74 | G81: 18.09 | H81: 10.35 | I81: 7.74 | J81: 18.09 | V81: 1 | W81: un | X81: 11.68 | Y81: 6.9 | Z81: =SUM(X81:Y81) -> 18.58 | AB81: 1 | AC81: un | AD81: 14.89 | AE81: 8.8 | AF81: =SUM(AD81:AE81) -> 23.69 | AH81: =IF(E81=0,0,(E81/AD81)-1) -> -0.30490262 | AI81: =IF(F81=0,0,(F81/AE81)-1) -> -0.12045455 | AJ81: =IF(G81=0,0,(G81/AF81)-1) -> -0.23638666
A82: 8 | B82: IMPERMEABILIZAÇÃO | H82: 121102.31 | I82: 69455.66 | J82: 190557.97 | AH82: =IF(E82=0,0,(E82/AD82)-1) -> 0 | AI82: =IF(F82=0,0,(F82/AE82)-1) -> 0 | AJ82: =IF(G82=0,0,(G82/AF82)-1) -> 0
A83: 8.1 | B83: Proteção mecânica de superfície com argamassa de cimento e areia | C83: 196 | D83: m² | E83: 19.46 | F83: 21.28 | G83: 40.74 | H83: 3814.16 | I83: 4170.88 | J83: 7985.04 | V83: 54 | W83: m² | X83: 26.67 | Y83: 20.22 | Z83: =SUM(X83:Y83) -> 46.89 | AB83: 54 | AC83: m² | AD83: 34 | AE83: 25.78 | AF83: =SUM(AD83:AE83) -> 59.78 | AH83: =IF(E83=0,0,(E83/AD83)-1) -> -0.42764706 | AI83: =IF(F83=0,0,(F83/AE83)-1) -> -0.17455392 | AJ83: =IF(G83=0,0,(G83/AF83)-1) -> -0.31850117
A84: 8.2 | B84: Impermeabilização com manta asfáltica modificada com polímeros aluminizada | C84: 596 | D84: m² | E84: 70.91 | F84: 20.72 | G84: 91.63 | H84: 42262.36 | I84: 12349.12 | J84: 54611.48 | V84: 7 | W84: m² | X84: 66.05 | Y84: 19.37 | Z84: =SUM(X84:Y84) -> 85.42 | AB84: 7 | AC84: m² | AD84: 84.21 | AE84: 24.7 | AF84: =SUM(AD84:AE84) -> 108.91 | AH84: =IF(E84=0,0,(E84/AD84)-1) -> -0.15793849 | AI84: =IF(F84=0,0,(F84/AE84)-1) -> -0.1611336 | AJ84: =IF(G84=0,0,(G84/AF84)-1) -> -0.15866312
A85: 8.3 | B85: Impermeabilização utilizando manta asfáltica polimérica (cobertura, lajes, banheiros, jardins, Reservatórios e similares) | C85: 376 | D85: m² | E85: 80.46 | F85: 30.81 | G85: 111.27 | H85: 30252.96 | I85: 11584.56 | J85: 41837.52 | V85: 261 | W85: m² | X85: 74.99 | Y85: 29.71 | Z85: =SUM(X85:Y85) -> 104.7 | AB85: 261 | AC85: m² | AD85: 95.61 | AE85: 37.88 | AF85: =SUM(AD85:AE85) -> 133.49 | AH85: =IF(E85=0,0,(E85/AD85)-1) -> -0.15845623 | AI85: =IF(F85=0,0,(F85/AE85)-1) -> -0.18664203 | AJ85: =IF(G85=0,0,(G85/AF85)-1) -> -0.16645442
A86: 8.4 | B86: Impermeabilização de calha ou lajes descobertas com emulsão asfáltica com elastômeros, 3 demãos, com tela de poliéster | C86: 302 | D86: m² | E86: 45.97 | F86: 20.43 | G86: 66.4 | H86: 13882.94 | I86: 6169.86 | J86: 20052.8 | V86: 14 | W86: m² | X86: 47.44 | Y86: 19.42 | Z86: =SUM(X86:Y86) -> 66.86 | AB86: 14 | AC86: m² | AD86: 60.49 | AE86: 24.76 | AF86: =SUM(AD86:AE86) -> 85.25 | AH86: =IF(E86=0,0,(E86/AD86)-1) -> -0.24003968 | AI86: =IF(F86=0,0,(F86/AE86)-1) -> -0.17487884 | AJ86: =IF(G86=0,0,(G86/AF86)-1) -> -0.22111437
A87: 8.5 | B87: Impermeabilização de superfície com impermeabilizante flexível à base acrílica | C87: 612 | D87: m² | E87: 49.05 | F87: 55.23 | G87: 104.28 | H87: 30018.6 | I87: 33800.76 | J87: 63819.36 | V87: 24 | W87: m² | X87: 49.32 | Y87: 51.12 | Z87: =SUM(X87:Y87) -> 100.44 | AB87: 24 | AC87: m² | AD87: 62.88 | AE87: 65.18 | AF87: =SUM(AD87:AE87) -> 128.06 | AH87: =IF(E87=0,0,(E87/AD87)-1) -> -0.21994275 | AI87: =IF(F87=0,0,(F87/AE87)-1) -> -0.15265419 | AJ87: =IF(G87=0,0,(G87/AF87)-1) -> -0.18569421
A88: 8.6 | B88: Impermeabilização com argamassa polimérica impermeabilizante | C88: 86 | D88: m² | E88: 8.65 | F88: 15.78 | G88: 24.43 | H88: 743.9 | I88: 1357.08 | J88: 2100.98 | V88: 184 | W88: m² | X88: 8.82 | Y88: 14.61 | Z88: =SUM(X88:Y88) -> 23.43 | AB88: 184 | AC88: m² | AD88: 11.25 | AE88: 18.63 | AF88: =SUM(AD88:AE88) -> 29.88 | AH88: =IF(E88=0,0,(E88/AD88)-1) -> -0.23111111 | AI88: =IF(F88=0,0,(F88/AE88)-1) -> -0.15297907 | AJ88: =IF(G88=0,0,(G88/AF88)-1) -> -0.18239625
A89: 8.7 | B89: Impermeabilização com membrana de poliuretano (PU) | C89: 1 | D89: m² | E89: 127.39 | F89: 23.4 | G89: 150.79 | H89: 127.39 | I89: 23.4 | J89: 150.79 | V89: 1 | W89: m² | X89: 130.18 | Y89: 21.95 | Z89: =SUM(X89:Y89) -> 152.13 | AB89: 1 | AC89: m² | AD89: 165.98 | AE89: 27.99 | AF89: =SUM(AD89:AE89) -> 193.97 | AH89: =IF(E89=0,0,(E89/AD89)-1) -> -0.23249789 | AI89: =IF(F89=0,0,(F89/AE89)-1) -> -0.16398714 | AJ89: =IF(G89=0,0,(G89/AF89)-1) -> -0.22261174
A90: 9 | B90: TRATAMENTO TÉRMICO E ACÚSTICO | H90: 0 | I90: 0 | J90: 0 | AH90: =IF(E90=0,0,(E90/AD90)-1) -> 0 | AI90: =IF(F90=0,0,(F90/AE90)-1) -> 0 | AJ90: =IF(G90=0,0,(G90/AF90)-1) -> 0
A91: 10 | B91: PAVIMENTAÇÃO | H91: 649442.11 | I91: 48616.57 | J91: 698058.68 | AH91: =IF(E91=0,0,(E91/AD91)-1) -> 0 | AI91: =IF(F91=0,0,(F91/AE91)-1) -> 0 | AJ91: =IF(G91=0,0,(G91/AF91)-1) -> 0
A92: 10.1 | B92: Regularização de base ou contrapiso | C92: 599 | D92: m² | E92: 11.77 | F92: 12.86 | G92: 24.63 | H92: 7050.23 | I92: 7703.14 | J92: 14753.37 | V92: 139 | W92: m² | X92: 16.53 | Y92: 11.57 | Z92: =SUM(X92:Y92) -> 28.1 | AB92: 139 | AC92: m² | AD92: 21.08 | AE92: 14.75 | AF92: =SUM(AD92:AE92) -> 35.83 | AH92: =IF(E92=0,0,(E92/AD92)-1) -> -0.44165085 | AI92: =IF(F92=0,0,(F92/AE92)-1) -> -0.12813559 | AJ92: =IF(G92=0,0,(G92/AF92)-1) -> -0.31258722
A93: 10.2 | B93: Regularização de piso para piso vinílico ou tátil em borracha | C93: 484 | D93: m² | E93: 15.88 | F93: 20.58 | G93: 36.46 | H93: 7685.92 | I93: 9960.72 | J93: 17646.64 | V93: 6 | W93: m² | X93: 19.95 | Y93: 18.52 | Z93: =SUM(X93:Y93) -> 38.47 | AB93: 6 | AC93: m² | AD93: 25.44 | AE93: 23.61 | AF93: =SUM(AD93:AE93) -> 49.05 | AH93: =IF(E93=0,0,(E93/AD93)-1) -> -0.37578616 | AI93: =IF(F93=0,0,(F93/AE93)-1) -> -0.12833545 | AJ93: =IF(G93=0,0,(G93/AF93)-1) -> -0.25667686
A94: 10.3 | B94: Granito para revestimento (piso ou parede) Cinza Andorinha, assente com argamassa | C94: 24 | D94: m² | E94: 395.62 | F94: 47.54 | G94: 443.16 | H94: 9494.88 | I94: 1140.96 | J94: 10635.84 | V94: 8 | W94: m² | X94: 307.59 | Y94: 44.63 | Z94: =SUM(X94:Y94) -> 352.22 | AB94: 8 | AC94: m² | AD94: 392.18 | AE94: 56.9 | AF94: =SUM(AD94:AE94) -> 449.08 | AH94: =IF(E94=0,0,(E94/AD94)-1) -> 0.0087714825 | AI94: =IF(F94=0,0,(F94/AE94)-1) -> -0.16449912 | AJ94: =IF(G94=0,0,(G94/AF94)-1) -> -0.013182506
A95: 10.4 | B95: Rodapé em granito Cinza Andorinha, assentado e rejuntado | C95: 36 | D95: m | E95: 65.41 | F95: 11.98 | G95: 77.39 | H95: 2354.76 | I95: 431.28 | J95: 2786.04 | V95: 41 | W95: m | X95: 50.65 | Y95: 11.24 | Z95: =SUM(X95:Y95) -> 61.89 | AB95: 41 | AC95: m | AD95: 64.58 | AE95: 14.33 | AF95: =SUM(AD95:AE95) -> 78.91 | AH95: =IF(E95=0,0,(E95/AD95)-1) -> 0.012852276 | AI95: =IF(F95=0,0,(F95/AE95)-1) -> -0.16399163 | AJ95: =IF(G95=0,0,(G95/AF95)-1) -> -0.019262451
A96: 10.5 | B96: Peitoril ou soleira de granito, assentado e rejuntado | C96: 10 | D96: m | E96: 89.02 | F96: 21.88 | G96: 110.9 | H96: 890.2 | I96: 218.8 | J96: 1109 | V96: 10 | W96: m | X96: 68.92 | Y96: 20.54 | Z96: =SUM(X96:Y96) -> 89.46 | AB96: 10 | AC96: m | AD96: 87.87 | AE96: 26.19 | AF96: =SUM(AD96:AE96) -> 114.06 | AH96: =IF(E96=0,0,(E96/AD96)-1) -> 0.013087516 | AI96: =IF(F96=0,0,(F96/AE96)-1) -> -0.16456663 | AJ96: =IF(G96=0,0,(G96/AF96)-1) -> -0.027704717
A97: 10.6 | B97: Granito branco para revestimento (piso ou parede), assente com argamassa | C97: 1 | D97: m² | E97: 732.46 | F97: 47.54 | G97: 780 | H97: 732.46 | I97: 47.54 | J97: 780 | V97: 1 | W97: m² | X97: 565.22 | Y97: 44.63 | Z97: =SUM(X97:Y97) -> 609.85 | AB97: 1 | AC97: m² | AD97: 720.66 | AE97: 56.9 | AF97: =SUM(AD97:AE97) -> 777.56 | AH97: =IF(E97=0,0,(E97/AD97)-1) -> 0.016373879 | AI97: =IF(F97=0,0,(F97/AE97)-1) -> -0.16449912 | AJ97: =IF(G97=0,0,(G97/AF97)-1) -> 0.0031380215
A98: 10.7 | B98: Rodapé em granito branco, assentado e rejuntado | C98: 1 | D98: m | E98: 69.99 | F98: 11.98 | G98: 81.97 | H98: 69.99 | I98: 11.98 | J98: 81.97 | V98: 1 | W98: m | X98: 54.15 | Y98: 11.24 | Z98: =SUM(X98:Y98) -> 65.39 | AB98: 1 | AC98: m | AD98: 69.04 | AE98: 14.33 | AF98: =SUM(AD98:AE98) -> 83.37 | AH98: =IF(E98=0,0,(E98/AD98)-1) -> 0.013760139 | AI98: =IF(F98=0,0,(F98/AE98)-1) -> -0.16399163 | AJ98: =IF(G98=0,0,(G98/AF98)-1) -> -0.016792611
A99: 10.8 | B99: Bloco de concreto intertravado | C99: 18 | D99: m² | E99: 59.93 | F99: 8.17 | G99: 68.1 | H99: 1078.74 | I99: 147.06 | J99: 1225.8 | V99: 1 | W99: m² | X99: 60.92 | Y99: 6.42 | Z99: =SUM(X99:Y99) -> 67.34 | AB99: 1 | AC99: m² | AD99: 77.67 | AE99: 8.19 | AF99: =SUM(AD99:AE99) -> 85.86 | AH99: =IF(E99=0,0,(E99/AD99)-1) -> -0.22840221 | AI99: =IF(F99=0,0,(F99/AE99)-1) -> -0.0024420024 | AJ99: =IF(G99=0,0,(G99/AF99)-1) -> -0.20684836
A100: 10.9 | B100: Piso em pedra portuguesa, basalto, calcário ou granito sem polimento. | C100: 61 | D100: m² | E100: 155.42 | F100: 51.23 | G100: 206.65 | H100: 9480.62 | I100: 3125.03 | J100: 12605.65 | V100: 12 | W100: m² | X100: 181.19 | Y100: 40.25 | Z100: =SUM(X100:Y100) -> 221.44 | AB100: 12 | AC100: m² | AD100: 231.02 | AE100: 51.32 | AF100: =SUM(AD100:AE100) -> 282.34 | AH100: =IF(E100=0,0,(E100/AD100)-1) -> -0.32724439 | AI100: =IF(F100=0,0,(F100/AE100)-1) -> -0.0017537023 | AJ100: =IF(G100=0,0,(G100/AF100)-1) -> -0.26808104
A101: 10.10 | B101: Piso mármore branco, assentado e rejuntado | C101: 1 | D101: m² | E101: 496.09 | F101: 47.54 | G101: 543.63 | H101: 496.09 | I101: 47.54 | J101: 543.63 | V101: 1 | W101: m² | X101: 385.83 | Y101: 44.63 | Z101: =SUM(X101:Y101) -> 430.46 | AB101: 1 | AC101: m² | AD101: 491.93 | AE101: 56.9 | AF101: =SUM(AD101:AE101) -> 548.83 | AH101: =IF(E101=0,0,(E101/AD101)-1) -> 0.0084564877 | AI101: =IF(F101=0,0,(F101/AE101)-1) -> -0.16449912 | AJ101: =IF(G101=0,0,(G101/AF101)-1) -> -0.0094747007
A102: 10.11 | B102: Piso em ladrilho hidráulico, assentado com argamassa | C102: 61 | D102: m² | E102: 90.79 | F102: 86.46 | G102: 177.25 | H102: 5538.19 | I102: 5274.06 | J102: 10812.25 | V102: 5 | W102: m² | X102: 78.93 | Y102: 83.74 | Z102: =SUM(X102:Y102) -> 162.67 | AB102: 5 | AC102: m² | AD102: 100.64 | AE102: 106.77 | AF102: =SUM(AD102:AE102) -> 207.41 | AH102: =IF(E102=0,0,(E102/AD102)-1) -> -0.097873609 | AI102: =IF(F102=0,0,(F102/AE102)-1) -> -0.19022197 | AJ102: =IF(G102=0,0,(G102/AF102)-1) -> -0.14541247
A103: 10.12 | B103: Piso cimentado com argamassa e com junta plástica para dilatação. | C103: 58 | D103: m² | E103: 26.05 | F103: 15.36 | G103: 41.41 | H103: 1510.9 | I103: 890.88 | J103: 2401.78 | V103: 27 | W103: m² | X103: 36.09 | Y103: 14.21 | Z103: =SUM(X103:Y103) -> 50.3 | AB103: 27 | AC103: m² | AD103: 46.01 | AE103: 18.12 | AF103: =SUM(AD103:AE103) -> 64.13 | AH103: =IF(E103=0,0,(E103/AD103)-1) -> -0.43381874 | AI103: =IF(F103=0,0,(F103/AE103)-1) -> -0.15231788 | AJ103: =IF(G103=0,0,(G103/AF103)-1) -> -0.35428037
... A115: 10.24 | B115: Aplicação de Solução Antiderrapante em Pisos Frios, Inclusive mão de obra especializada | C115: 2 | D115: m² | E115: 43.65 | F115: 0 | G115: 43.65 | H115: 87.3 | I115: 0 | J115: 87.3 | V115: 1 | W115: m² | X115: 47.08 | Y115: 0 | Z115: =SUM(X115:Y115) -> 47.08 | AB115: 1 | AC115: m² | AD115: 60.03 | AE115: 0 | AF115: =SUM(AD115:AE115) -> 60.03 | AH115: =IF(E115=0,0,(E115/AD115)-1) -> -0.27286357 | AI115: =IF(F115=0,0,(F115/AE115)-1) -> 0 | AJ115: =IF(G115=0,0,(G115/AF115)-1) -> -0.27286357
A116: 11 | B116: REVESTIMENTOS | H116: 35029.12 | I116: 18675.6 | J116: 53704.72 | AH116: =IF(E116=0,0,(E116/AD116)-1) -> 0 | AI116: =IF(F116=0,0,(F116/AE116)-1) -> 0 | AJ116: =IF(G116=0,0,(G116/AF116)-1) -> 0
A117: 11.1 | B117: Painéis de alumínio - ACM | C117: 1 | D117: m² | E117: 129.42 | F117: 59.97 | G117: 189.39 | H117: 129.42 | I117: 59.97 | J117: 189.39 | V117: 1 | W117: m² | X117: 162.72 | Y117: 53.86 | Z117: =SUM(X117:Y117) -> 216.58 | AB117: 1 | AC117: m² | AD117: 207.47 | AE117: 68.67 | AF117: =SUM(AD117:AE117) -> 276.14 | AH117: =IF(E117=0,0,(E117/AD117)-1) -> -0.37619897 | AI117: =IF(F117=0,0,(F117/AE117)-1) -> -0.12669288 | AJ117: =IF(G117=0,0,(G117/AF117)-1) -> -0.31415224
A118: 11.2 | B118: Chapisco para parede interna ou externa com argamassa de cimento e areia. | C118: 259 | D118: m² | E118: 1.96 | F118: 5.14 | G118: 7.1 | H118: 507.64 | I118: 1331.26 | J118: 1838.9 | V118: 288 | W118: m² | X118: 2.76 | Y118: 4.63 | Z118: =SUM(X118:Y118) -> 7.39 | AB118: 288 | AC118: m² | AD118: 3.52 | AE118: 5.9 | AF118: =SUM(AD118:AE118) -> 9.42 | AH118: =IF(E118=0,0,(E118/AD118)-1) -> -0.44318182 | AI118: =IF(F118=0,0,(F118/AE118)-1) -> -0.12881356 | AJ118: =IF(G118=0,0,(G118/AF118)-1) -> -0.2462845
A119: 11.3 | B119: Emboço ou reboco para parede interna ou externa ou teto. | C119: 462 | D119: m² | E119: 15.88 | F119: 23.81 | G119: 39.69 | H119: 7336.56 | I119: 11000.22 | J119: 18336.78 | V119: 321 | W119: m² | X119: 19.95 | Y119: 21.89 | Z119: =SUM(X119:Y119) -> 41.84 | AB119: 321 | AC119: m² | AD119: 25.44 | AE119: 27.91 | AF119: =SUM(AD119:AE119) -> 53.35 | AH119: =IF(E119=0,0,(E119/AD119)-1) -> -0.37578616 | AI119: =IF(F119=0,0,(F119/AE119)-1) -> -0.14690075 | AJ119: =IF(G119=0,0,(G119/AF119)-1) -> -0.25604499
A120: 11.4 | B120: Revestimento cerâmico assentado com argamassa pré-fabricada e rejuntado | C120: 66 | D120: m² | E120: 31.43 | F120: 38.01 | G120: 69.44 | H120: 2074.38 | I120: 2508.66 | J120: 4583.04 | V120: 32 | W120: m² | X120: 36.53 | Y120: 36.84 | Z120: =SUM(X120:Y120) -> 73.37 | AB120: 32 | AC120: m² | AD120: 46.58 | AE120: 46.97 | AF120: =SUM(AD120:AE120) -> 93.55 | AH120: =IF(E120=0,0,(E120/AD120)-1) -> -0.32524689 | AI120: =IF(F120=0,0,(F120/AE120)-1) -> -0.19076006 | AJ120: =IF(G120=0,0,(G120/AF120)-1) -> -0.25772314
A121: 11.5 | B121: Revestimento (parede) em Pastilha de vidro, assentada com argamassa colante e rejunte. | C121: 83 | D121: m² | E121: 256.41 | F121: 40.38 | G121: 296.79 | H121: 21282.03 | I121: 3351.54 | J121: 24633.57 | V121: 5 | W121: m² | X121: 302.69 | Y121: 39.12 | Z121: =SUM(X121:Y121) -> 341.81 | AB121: 5 | AC121: m² | AD121: 385.93 | AE121: 49.88 | AF121: =SUM(AD121:AE121) -> 435.81 | AH121: =IF(E121=0,0,(E121/AD121)-1) -> -0.3356049 | AI121: =IF(F121=0,0,(F121/AE121)-1) -> -0.1904571 | AJ121: =IF(G121=0,0,(G121/AF121)-1) -> -0.31899222
A122: 11.6 | B122: Laminado melamínico para revestimento (piso ou parede) interno | C122: 21 | D122: m² | E122: 90.11 | F122: 9.39 | G122: 99.5 | H122: 1892.31 | I122: 197.19 | J122: 2089.5 | V122: 49 | W122: m² | X122: 165.07 | Y122: 8.85 | Z122: =SUM(X122:Y122) -> 173.92 | AB122: 49 | AC122: m² | AD122: 210.46 | AE122: 11.28 | AF122: =SUM(AD122:AE122) -> 221.74 | AH122: =IF(E122=0,0,(E122/AD122)-1) -> -0.57184263 | AI122: =IF(F122=0,0,(F122/AE122)-1) -> -0.16755319 | AJ122: =IF(G122=0,0,(G122/AF122)-1) -> -0.55127627
A123: 11.7 | B123: Revestimento de parede com pedra São Tomé filetada (tipo "canjiquinha") | C123: 4 | D123: m² | E123: 268.58 | F123: 34.71 | G123: 303.29 | H123: 1074.32 | I123: 138.84 | J123: 1213.16 | V123: 1 | W123: m² | X123: 304.06 | Y123: 32.13 | Z123: =SUM(X123:Y123) -> 336.19 | AB123: 1 | AC123: m² | AD123: 387.68 | AE123: 40.97 | AF123: =SUM(AD123:AE123) -> 428.65 | AH123: =IF(E123=0,0,(E123/AD123)-1) -> -0.30721213 | AI123: =IF(F123=0,0,(F123/AE123)-1) -> -0.15279473 | AJ123: =IF(G123=0,0,(G123/AF123)-1) -> -0.29245305
A124: 11.8 | B124: Revestimento em mármore branco (parede), assentado e rejuntado | C124: 1 | D124: m² | E124: 496.09 | F124: 47.54 | G124: 543.63 | H124: 496.09 | I124: 47.54 | J124: 543.63 | V124: 1 | W124: m² | X124: 385.83 | Y124: 44.63 | Z124: =SUM(X124:Y124) -> 430.46 | AB124: 1 | AC124: m² | AD124: 491.93 | AE124: 56.9 | AF124: =SUM(AD124:AE124) -> 548.83 | AH124: =IF(E124=0,0,(E124/AD124)-1) -> 0.0084564877 | AI124: =IF(F124=0,0,(F124/AE124)-1) -> -0.16449912 | AJ124: =IF(G124=0,0,(G124/AF124)-1) -> -0.0094747007
A125: 11.9 | B125: Revestimento em Pastilha Cerâmica, assentada com argamassa colante e rejunte. | C125: 1 | D125: m² | E125: 236.37 | F125: 40.38 | G125: 276.75 | H125: 236.37 | I125: 40.38 | J125: 276.75 | V125: 1 | W125: m² | X125: 278.86 | Y125: 39.12 | Z125: =SUM(X125:Y125) -> 317.98 | AB125: 1 | AC125: m² | AD125: 355.55 | AE125: 49.88 | AF125: =SUM(AD125:AE125) -> 405.43 | AH125: =IF(E125=0,0,(E125/AD125)-1) -> -0.33519899 | AI125: =IF(F125=0,0,(F125/AE125)-1) -> -0.1904571 | AJ125: =IF(G125=0,0,(G125/AF125)-1) -> -0.31739141
A126: 12 | B126: DIVISÓRIAS, FORROS E PISOS FALSOS | H126: 193660.12 | I126: 61421.68 | J126: 255081.8 | AH126: =IF(E126=0,0,(E126/AD126)-1) -> 0 | AI126: =IF(F126=0,0,(F126/AE126)-1) -> 0 | AJ126: =IF(G126=0,0,(G126/AF126)-1) -> 0
A127: 12.1 | B127: Divisória texturizada cega | C127: 104 | D127: m² | E127: 171.02 | F127: 42.33 | G127: 213.35 | H127: 17786.08 | I127: 4402.32 | J127: 22188.4 | V127: 292 | W127: m² | X127: 200.68 | Y127: 40.93 | Z127: =SUM(X127:Y127) -> 241.61 | AB127: 292 | AC127: m² | AD127: 255.87 | AE127: 52.19 | AF127: =SUM(AD127:AE127) -> 308.06 | AH127: =IF(E127=0,0,(E127/AD127)-1) -> -0.33161371 | AI127: =IF(F127=0,0,(F127/AE127)-1) -> -0.18892508 | AJ127: =IF(G127=0,0,(G127/AF127)-1) -> -0.30744011
A128: 12.2 | B128: Divisória texturizada cega/vidro | C128: 1 | D128: m² | E128: 166.07 | F128: 61.37 | G128: 227.44 | H128: 166.07 | I128: 61.37 | J128: 227.44 | V128: 1 | W128: m² | X128: 159.79 | Y128: 58.19 | Z128: =SUM(X128:Y128) -> 217.98 | AB128: 1 | AC128: m² | AD128: 203.73 | AE128: 74.19 | AF128: =SUM(AD128:AE128) -> 277.92 | AH128: =IF(E128=0,0,(E128/AD128)-1) -> -0.1848525 | AI128: =IF(F128=0,0,(F128/AE128)-1) -> -0.17279957 | AJ128: =IF(G128=0,0,(G128/AF128)-1) -> -0.181635
A129: 12.3 | B129: Porta de divisória, Inclui batente e guarnições. | C129: 17 | D129: un | E129: 459.98 | F129: 42.33 | G129: 502.31 | H129: 7819.66 | I129: 719.61 | J129: 8539.27 | V129: 19 | W129: un | X129: 457.93 | Y129: 40.93 | Z129: =SUM(X129:Y129) -> 498.86 | AB129: 19 | AC129: un | AD129: 583.86 | AE129: 52.19 | AF129: =SUM(AD129:AE129) -> 636.05 | AH129: =IF(E129=0,0,(E129/AD129)-1) -> -0.21217415 | AI129: =IF(F129=0,0,(F129/AE129)-1) -> -0.18892508 | AJ129: =IF(G129=0,0,(G129/AF129)-1) -> -0.21026649
A130: 12.4 | B130: Forro de fibra mineral, incluindo fixação, com estrutura | C130: 745 | D130: m² | E130: 118.98 | F130: 14.01 | G130: 132.99 | H130: 88640.1 | I130: 10437.45 | J130: 99077.55 | V130: 416 | W130: m² | X130: 139.83 | Y130: 12.57 | Z130: =SUM(X130:Y130) -> 152.4 | AB130: 416 | AC130: m² | AD130: 178.28 | AE130: 16.03 | AF130: =SUM(AD130:AE130) -> 194.31 | AH130: =IF(E130=0,0,(E130/AD130)-1) -> -0.33262284 | AI130: =IF(F130=0,0,(F130/AE130)-1) -> -0.12601372 | AJ130: =IF(G130=0,0,(G130/AF130)-1) -> -0.3155782
...
