Workbook

Sheet RAT 
A1: RAT - RELATÓRIO DE ATENDIMENTO
A2: EXECUÇÃO DOS SERVIÇOS
A3: Número da solicitação | C3: Data/hora Abertura | F3: Contrato de Manutenção | I3: Contratada
F4: 2024.7421.6122 | I4: MAFFENG ENGENHARIA E MANUTENÇÃO
A5: Sinistro | C5: Prazo de atendimento | F5: Tipo de Manutenção | I5: Nível de Ocorrência
A6: (Sim/Não) | F6: (Preventiva/Corretiva) | I6: (Emergencial/Urgente/Normal)
A7: Não | F7: Preventiva | I7: Normal
A8: Prefixo / SB - Dependência Beneficiada | F8: Endereço
B9: =IFERROR(UPPER(VLOOKUP(A9,Prefixos!A5:E69,2,0)),"") | F9: =IFERROR(UPPER(VLOOKUP(A9,Prefixos!A5:E69,5,0)),"")
A10: Informações de Contato | F10: Matrícula / Nome - Funcionário Solicitante
A11: Responsável | F11: F2190439 - SISTEMA
A12: SERVIÇOS SOLICITADOS - Portal de Manutenção
A13: Descrição do serviço, Tipo, Quantidade, Local de Atendimento e Prioridade* | J13: Situação (Código**)
A14: Levantamento Preventivo | J14: 4
A15: * Preencher com as informações do Portal de Manutenção da DISEC. ** Preencher o campo situação com os códigos a seguir: 1. Serviço concluído sem pendências; 2. Serviço cancelado pelo demandante; 3. Atendimento Parcial; 4. Confecção de orçamento, para execução do serviço demanda autorização por parte do CESUP Suprimentos; 5. Não Atendido. 6. Mitigação de Riscos ou primeiro atendimento
A16: ORÇAMENTO DOS SERVIÇOS REALIZADOS
A17: ITEM | B17: DESCRIÇÃO | H17: QTD. | I17: UND. | J17: VALOR UNITÁRIO | L17: MAT UNIT | M17: MAO. UNIT | N17: MAT TOTAL | O17: MAO TOTAL | P17: VALOR TOTAL
A18: 1.2 | B18: =IFERROR(UPPER(VLOOKUP(A18,Tabela3[#All],2,0)),"") -> DESLOCAMENTO | I18: =IFERROR(VLOOKUP(A18,Tabela3[#All],4,0),"") -> km | J18: =IFERROR(VLOOKUP(A18,Tabela3[#All],7,0),"") -> 2.6 | L18: =IFERROR(VLOOKUP(A18,Tabela3[#All],5,0),"") -> 2.12 | M18: =IFERROR(VLOOKUP(A18,Tabela3[#All],6,0),"") -> 0.48 | N18: =L18*H18 -> 0 | O18: =M18*H18 -> 0 | P18: =IFERROR(J18*H18,"") -> 0
B19: =IFERROR(UPPER(VLOOKUP(A19,Tabela3[#All],2,0)),"") | I19: =IFERROR(VLOOKUP(A19,Tabela3[#All],4,0),"") | J19: =IFERROR(VLOOKUP(A19,Tabela3[#All],7,0),"") | L19: =IFERROR(VLOOKUP(A19,Tabela3[#All],5,0),"") | M19: =IFERROR(VLOOKUP(A19,Tabela3[#All],6,0),"") | N19: =L19*H19 -> #VALUE! | O19: =M19*H19 -> #VALUE! | P19: =IFERROR(J19*H19,"")
B20: =IFERROR(UPPER(VLOOKUP(A20,Tabela3[#All],2,0)),"") | I20: =IFERROR(VLOOKUP(A20,Tabela3[#All],4,0),"") | J20: =IFERROR(VLOOKUP(A20,Tabela3[#All],7,0),"") | L20: =IFERROR(VLOOKUP(A20,Tabela3[#All],5,0),"") | M20: =IFERROR(VLOOKUP(A20,Tabela3[#All],6,0),"") | N20: =L20*H20 -> #VALUE! | O20: =M20*H20 -> #VALUE! | P20: =IFERROR(J20*H20,"")
B21: =IFERROR(UPPER(VLOOKUP(A21,Tabela3[#All],2,0)),"") | I21: =IFERROR(VLOOKUP(A21,Tabela3[#All],4,0),"") | J21: =IFERROR(VLOOKUP(A21,Tabela3[#All],7,0),"") | L21: =IFERROR(VLOOKUP(A21,Tabela3[#All],5,0),"") | M21: =IFERROR(VLOOKUP(A21,Tabela3[#All],6,0),"") | N21: =L21*H21 -> #VALUE! | O21: =M21*H21 -> #VALUE! | P21: =IFERROR(J21*H21,"")
B22: =IFERROR(UPPER(VLOOKUP(A22,Tabela3[#All],2,0)),"") | I22: =IFERROR(VLOOKUP(A22,Tabela3[#All],4,0),"") | J22: =IFERROR(VLOOKUP(A22,Tabela3[#All],7,0),"") | L22: =IFERROR(VLOOKUP(A22,Tabela3[#All],5,0),"") | M22: =IFERROR(VLOOKUP(A22,Tabela3[#All],6,0),"") | N22: =L22*H22 -> #VALUE! | O22: =M22*H22 -> #VALUE! | P22: =IFERROR(J22*H22,"")
B23: =IFERROR(UPPER(VLOOKUP(A23,Tabela3[#All],2,0)),"") | I23: =IFERROR(VLOOKUP(A23,Tabela3[#All],4,0),"") | J23: =IFERROR(VLOOKUP(A23,Tabela3[#All],7,0),"") | L23: =IFERROR(VLOOKUP(A23,Tabela3[#All],5,0),"") | M23: =IFERROR(VLOOKUP(A23,Tabela3[#All],6,0),"") | N23: =L23*H23 -> #VALUE! | O23: =M23*H23 -> #VALUE! | P23: =IFERROR(J23*H23,"")
B24: =IFERROR(UPPER(VLOOKUP(A24,Tabela3[#All],2,0)),"") | I24: =IFERROR(VLOOKUP(A24,Tabela3[#All],4,0),"") | J24: =IFERROR(VLOOKUP(A24,Tabela3[#All],7,0),"") | L24: =IFERROR(VLOOKUP(A24,Tabela3[#All],5,0),"") | M24: =IFERROR(VLOOKUP(A24,Tabela3[#All],6,0),"") | N24: =L24*H24 -> #VALUE! | O24: =M24*H24 -> #VALUE! | P24: =IFERROR(J24*H24,"")
B25: =IFERROR(UPPER(VLOOKUP(A25,Tabela3[#All],2,0)),"") | I25: =IFERROR(VLOOKUP(A25,Tabela3[#All],4,0),"") | J25: =IFERROR(VLOOKUP(A25,Tabela3[#All],7,0),"") | L25: =IFERROR(VLOOKUP(A25,Tabela3[#All],5,0),"") | M25: =IFERROR(VLOOKUP(A25,Tabela3[#All],6,0),"") | N25: =L25*H25 -> #VALUE! | O25: =M25*H25 -> #VALUE! | P25: =IFERROR(J25*H25,"")
B26: =IFERROR(UPPER(VLOOKUP(A26,Tabela3[#All],2,0)),"") | I26: =IFERROR(VLOOKUP(A26,Tabela3[#All],4,0),"") | J26: =IFERROR(VLOOKUP(A26,Tabela3[#All],7,0),"") | L26: =IFERROR(VLOOKUP(A26,Tabela3[#All],5,0),"") | M26: =IFERROR(VLOOKUP(A26,Tabela3[#All],6,0),"") | N26: =L26*H26 -> #VALUE! | O26: =M26*H26 -> #VALUE! | P26: =IFERROR(J26*H26,"")
B27: =IFERROR(UPPER(VLOOKUP(A27,Tabela3[#All],2,0)),"") | I27: =IFERROR(VLOOKUP(A27,Tabela3[#All],4,0),"") | J27: =IFERROR(VLOOKUP(A27,Tabela3[#All],7,0),"") | L27: =IFERROR(VLOOKUP(A27,Tabela3[#All],5,0),"") | M27: =IFERROR(VLOOKUP(A27,Tabela3[#All],6,0),"") | N27: =L27*H27 -> #VALUE! | O27: =M27*H27 -> #VALUE! | P27: =IFERROR(J27*H27,"")
B28: =IFERROR(UPPER(VLOOKUP(A28,Tabela3[#All],2,0)),"") | I28: =IFERROR(VLOOKUP(A28,Tabela3[#All],4,0),"") | J28: =IFERROR(VLOOKUP(A28,Tabela3[#All],7,0),"") | L28: =IFERROR(VLOOKUP(A28,Tabela3[#All],5,0),"") | M28: =IFERROR(VLOOKUP(A28,Tabela3[#All],6,0),"") | N28: =L28*H28 -> #VALUE! | O28: =M28*H28 -> #VALUE! | P28: =IFERROR(J28*H28,"")
B29: =IFERROR(UPPER(VLOOKUP(A29,Tabela3[#All],2,0)),"") | I29: =IFERROR(VLOOKUP(A29,Tabela3[#All],4,0),"") | J29: =IFERROR(VLOOKUP(A29,Tabela3[#All],7,0),"") | L29: =IFERROR(VLOOKUP(A29,Tabela3[#All],5,0),"") | M29: =IFERROR(VLOOKUP(A29,Tabela3[#All],6,0),"") | N29: =L29*H29 -> #VALUE! | O29: =M29*H29 -> #VALUE! | P29: =IFERROR(J29*H29,"")
B30: =IFERROR(UPPER(VLOOKUP(A30,Tabela3[#All],2,0)),"") | I30: =IFERROR(VLOOKUP(A30,Tabela3[#All],4,0),"") | J30: =IFERROR(VLOOKUP(A30,Tabela3[#All],7,0),"") | L30: =IFERROR(VLOOKUP(A30,Tabela3[#All],5,0),"") | M30: =IFERROR(VLOOKUP(A30,Tabela3[#All],6,0),"") | N30: =L30*H30 -> #VALUE! | O30: =M30*H30 -> #VALUE! | P30: =IFERROR(J30*H30,"")
... B57: =IFERROR(UPPER(VLOOKUP(A57,Tabela3[#All],2,0)),"") | I57: =IFERROR(VLOOKUP(A57,Tabela3[#All],4,0),"") | J57: =IFERROR(VLOOKUP(A57,Tabela3[#All],7,0),"") | L57: =IFERROR(VLOOKUP(A57,Tabela3[#All],5,0),"") | M57: =IFERROR(VLOOKUP(A57,Tabela3[#All],6,0),"") | N57: =L57*H57 -> #VALUE! | O57: =M57*H57 -> #VALUE! | P57: =IFERROR(J57*H57,"")
A58: RESUMO DO ORÇAMENTO DOS SERVIÇOS SOLICITADOS
A59: Data / Hora Conclusão | F59: Valor de Materiais + Mão de Obra | I59: Valor Total
A60: =E75 -> 0 | F60: =SUM(N18:N57) -> #VALUE! | G60: + | H60: =SUM(O18:O57) -> #VALUE! | I60: =H60+F60 -> #VALUE!
A61: Observações
B65: ________________________________________________ | H65: ___________________________________________________________________________________
B69: VISTO REPRESENTANTE DA EMPRESA CONTRATADA | H69: CARIMBO E VISTO DA DEPENDÊNCIA
A71: TÉCNICO | I71: ENGENHEIRO
A72: Laura
A73: AUXILIAR
A75: Data e hora | D75: Data e hora | I75: RESPONSÁVEL TÉCNICO
A76: CHEGADA | D76: SAÍDA | I76: CARIMBO - NÚMERO / VISTO DO CREA
A78: O RAT deverá ser emitido em 3 vias sendo, a 1º para a dependência beneficiada, a 2º para a empresa contratada e a 3º CESUP Suprimentos

Sheet Conformidade
A1: RAT - RELATÓRIO DE ATENDIMENTO
A2: Conformidade do atendimento no local dos serviços
A3: Número da solicitação | C3: Data/hora Abertura | F3: Contrato de Manutenção | I3: Contratada
A4: ='RAT '!A4 -> 0 | C4: ='RAT '!C4 -> 0 | F4: 2024.7421.6122 | I4: MAFFENG ENGENHARIA E MANUTENÇÃO
A5: Sinistro | C5: Prazo de atendimento | F5: Tipo de Manutenção | I5: Nível de Ocorrência
A6: (Sim/Não) | F6: (Preventiva/Corretiva) | I6: (Emergencial/Urgente/Normal)
A7: ='RAT '!A7 -> Não | C7: ='RAT '!C7 -> 0 | F7: ='RAT '!F7 -> Preventiva | I7: ='RAT '!I7 -> Normal
A8: Prefixo / SB - Dependência Beneficiada | F8: Endereço
A9: ='RAT '!A9 -> 0 | B9: ='RAT '!B9 | F9: ='RAT '!F9
A10: Informações de Contato | F10: Matrícula / Nome - Funcionário Solicitante
A11: ='RAT '!A11 -> Responsável | F11: ='RAT '!F11 -> F2190439 - SISTEMA
A12: MÓDULO DEMANDANTE / BENEFICIÁRIO / CONTRATANTE PREENCHIMENTO PELO PREPOSTO DO BANCO DO BRASIL
A13: Matrícula | C13: Nome Funcionário Preposto
A15: Questionário | I15: Atendeu | K15: Não Atendeu
A16: Prazo de Atendimento
A17: Qualidade dos serviços executados
A18: Discrição e Presteza dos funcionários
A19: RESUMO DO ORÇAMENTO DOS SERVIÇOS EXECUTADOS
A20: Data / Hora Conclusão | F20: Valor de Materiais + Mão de Obra | I20: Valor Total
A21: ='RAT '!E75 -> 0 | F21: ='RAT '!F60 -> #VALUE! | G21: + | H21: ='RAT '!H60 -> #VALUE! | I21: ='RAT '!I60 -> #VALUE!
A22: Observações
A24: Sr. ADMINISTRADOR PREDIAL, antes de assinar o RAT (Relatório de Atendimento), deve-se observar que:
A25: 1. A Situação (código, em "Serviços Solicitados") foi preenchida adequadamente para cada serviço solicitado e que os serviços
A26: registrados como concluídos, ficaram sem pendências;
A27: 2. Os serviços solicitados, porém não executados ou executados parcialmente, tiveram um valor descontado no campo "Resumo do Orçamento dos
A28: Serviços Executados".
A29: 3. O documento deverá ser totalmente preenchido, em todos os campos e sem rasuras. Inutilizar os espaços em branco;
A30: 4. A segunda via do RAT deverá ficar arquivada na dependência beneficiária para consultas futuras;
A31: 5. Deve-se registrar no Portal de Manutenção da DISEC as informações contidas no RAT.
A32: Dúvidas quanto aos itens, quantitativos e valores aplicados aos serviços, deverão ser sanadas com a CONTRATADA durante o atendimento. Caso não
A33: ocorra o esclarecimento, consultar o CESUP SUPRIMENTOS.
A34: Lembramos que o ADMINISTRADOR PREDIAL é o responsável pela fiscalização dos serviços executados na dependência e que a
... A36: dos serviços
B38: ________________________________________________ | H38: ___________________________________________________________________________________
B39: VISTO REPRESENTANTE DA EMPRESA CONTRATADA | H39: CARIMBO E VISTO DA DEPENDÊNCIA
A41: Parecer do Responsável Técnico / Contratada | I41: ENGENHEIRO
I47: CARIMBO - NÚMERO / VISTO DO CREA
A48: O RAT deverá ser emitido em 3 vias, sendo: a 1° Depêndencia Beneficiária, 2° Empresa Contratada, e em 3° CESUP Suprimentos

Sheet Valores Unitários
B1: A interessada deverá prrencher os campos em amarelo abaixo.
C3: CONSERVAÇÃO PREDIAL
B4: PROPONENTE : | G4: LOTE: | H4: 07
B5: MAFFENG ENGENHARIA E MANUTENÇÃO LTDA | D5: CNPJ: | E5: 33.624.704/0001-94 | I5: DESCONTO: | J5: 0.1589
A7: Nº ITEM | B7: DESCRIÇÃO ITEM | C7: QTDE | D7: UN. | E7: UNITÁRIO MATERIAL | F7: UNITÁRIO MÃO DE OBRA | G7: TOTAL UNITÁRIO DO ITEM | H7: TOTAL MATERIAL ROTEIRO | I7: TOTAL MÃO DE OBRA ROTEIRO | J7: TOTAL GERAL ROTEIRO | P7: UNITÁRIO MATERIAL | Q7: UNITÁRIO MÃO DE OBRA
A8: 1 | B8: PRELIMINARES | G8: =SUBTOTAL(109,G9:G15) -> 3887.78 | H8: =SUBTOTAL(109,H9:H15) -> 375777 | I8: =SUBTOTAL(109,I9:I15) -> 155002.43 | J8: =SUBTOTAL(109,J9:J15) -> 530779.43 | N8: Desconto | O8: 0.1589
A9: 1.1 | B9: Chamado | C9: 860 | D9: un | E9: =ROUND(P9,2) -> 0 | F9: =ROUND(Q9,2) -> 78.47 | G9: =SUM(E9:F9) -> 78.47 | H9: =C9*E9 -> 0 | I9: =C9*F9 -> 67484.2 | J9: =SUM(E9:F9)*C9 -> 67484.2 | O9: =1-0.1589 -> 0.8411 | P9: 0 | Q9: 78.466219
A10: 1.2 | B10: Deslocamento | C10: 120000 | D10: km | E10: =ROUND(P10,2) -> 2.12 | F10: =ROUND(Q10,2) -> 0.48 | G10: =SUM(E10:F10) -> 2.6 | H10: =C10*E10 -> 254400 | I10: =C10*F10 -> 57600 | J10: =SUM(E10:F10)*C10 -> 312000 | P10: 2.119572 | Q10: 0.479427
A11: 1.3 | B11: Revisão de instalações | C11: 80 | D11: un | E11: =ROUND(P11,2) -> 96.2 | F11: =ROUND(Q11,2) -> 361.77 | G11: =SUM(E11:F11) -> 457.97 | H11: =C11*E11 -> 7696 | I11: =C11*F11 -> 28941.6 | J11: =SUM(E11:F11)*C11 -> 36637.6 | P11: 96.196607 | Q11: 361.77393
A12: 1.4 | B12: Acompanhamento técnico em Segurança do Trabalho | C12: 1 | D12: un | E12: =ROUND(P12,2) -> 0 | F12: =ROUND(Q12,2) -> 196.33 | G12: =SUM(E12:F12) -> 196.33 | H12: =C12*E12 -> 0 | I12: =C12*F12 -> 196.33 | J12: =SUM(E12:F12)*C12 -> 196.33 | P12: 0 | Q12: 196.32956
A13: 1.5 | B13: Chamado Preventivo | C13: 50 | D13: un | E13: =ROUND(P13,2) -> 2271.61 | F13: =ROUND(Q13,2) -> 0 | G13: =SUM(E13:F13) -> 2271.61 | H13: =C13*E13 -> 113580.5 | I13: =C13*F13 -> 0 | J13: =SUM(E13:F13)*C13 -> 113580.5 | P13: 2271.6092 | Q13: 0
A14: 1.6 | B14: Deslocamento Fluvial | C14: 1 | D14: Km | E14: =ROUND(P14,2) -> 0.84 | F14: =ROUND(Q14,2) -> 1.05 | G14: =SUM(E14:F14) -> 1.89 | H14: =C14*E14 -> 0.84 | I14: =C14*F14 -> 1.05 | J14: =SUM(E14:F14)*C14 -> 1.89 | P14: 0.8411 | Q14: 1.051375
A15: 1.7 | B15: Laudo técnico fotográfico - Elementos de Sinalização - Padrão BB | C15: 1 | D15: UN | E15: =ROUND(P15,2) -> 99.66 | F15: =ROUND(Q15,2) -> 779.25 | G15: =SUM(E15:F15) -> 878.91 | H15: =C15*E15 -> 99.66 | I15: =C15*F15 -> 779.25 | J15: =SUM(E15:F15)*C15 -> 878.91 | P15: 99.661939 | Q15: 779.25392
A16: 2 | B16: IMPLANTAÇÃO / ADMINISTRAÇÃO | E16: =ROUND(P16,2) -> 0 | F16: =ROUND(Q16,2) -> 0 | G16: =SUBTOTAL(109,G17:G52) -> 2313.03 | H16: =SUBTOTAL(109,H17:H52) -> 81930.18 | I16: =SUBTOTAL(109,I17:I52) -> 68493.47 | J16: =SUBTOTAL(109,J17:J52) -> 150423.65
A17: 2.1 | B17: Demolição manual de concreto simples | C17: 42 | D17: m³ | E17: =ROUND(P17,2) -> 0 | F17: =ROUND(Q17,2) -> 269.82 | G17: =SUM(E17:F17) -> 269.82 | H17: =C17*E17 -> 0 | I17: =C17*F17 -> 11332.44 | J17: =SUM(E17:F17)*C17 -> 11332.44 | P17: 0 | Q17: 269.81647
A18: 2.2 | B18: Demolição manual de alvenaria de elevação ou elemento vazado, incluindo revestimento | C18: 1 | D18: m³ | E18: =ROUND(P18,2) -> 0 | F18: =ROUND(Q18,2) -> 62.27 | G18: =SUM(E18:F18) -> 62.27 | H18: =C18*E18 -> 0 | I18: =C18*F18 -> 62.27 | J18: =SUM(E18:F18)*C18 -> 62.27 | P18: 0 | Q18: 62.266633
A19: 2.3 | B19: Demolição manual de revestimento em massa de parede ou teto ou Dry-Wall | C19: 535 | D19: m³ | E19: =ROUND(P19,2) -> 0 | F19: =ROUND(Q19,2) -> 7.14 | G19: =SUM(E19:F19) -> 7.14 | H19: =C19*E19 -> 0 | I19: =C19*F19 -> 3819.9 | J19: =SUM(E19:F19)*C19 -> 3819.9 | P19: 0 | Q19: 7.140939
A20: 2.4 | B20: Demolição de pisos em geral (ladrilho hidráulico, camada de enchimento, cerâmica, porcelanato, mármore, granito, pedra e madeira) - Manual | C20: 1 | D20: m² | E20: =ROUND(P20,2) -> 0 | F20: =ROUND(Q20,2) -> 29.06 | G20: =SUM(E20:F20) -> 29.06 | H20: =C20*E20 -> 0 | I20: =C20*F20 -> 29.06 | J20: =SUM(E20:F20)*C20 -> 29.06 | P20: 0 | Q20: 29.060005
A21: 2.5 | B21: Demolição de pisos em geral (ladrilho hidráulico, camada de enchimento, cerâmica, porcelanato, mármore, granito, pedra e madeira) - Mecanizado | C21: 207 | D21: m² | E21: =ROUND(P21,2) -> 23.95 | F21: =ROUND(Q21,2) -> 14.53 | G21: =SUM(E21:F21) -> 38.48 | H21: =C21*E21 -> 4957.65 | I21: =C21*F21 -> 3007.71 | J21: =SUM(E21:F21)*C21 -> 7965.36 | P21: 23.946117 | Q21: 14.525797
A22: 2.6 | B22: Demolição de pavimentação com pré-moldado de concreto ou intertravado | C22: 1 | D22: m² | E22: =ROUND(P22,2) -> 0 | F22: =ROUND(Q22,2) -> 14.53 | G22: =SUM(E22:F22) -> 14.53 | H22: =C22*E22 -> 0 | I22: =C22*F22 -> 14.53 | J22: =SUM(E22:F22)*C22 -> 14.53 | P22: 0 | Q22: 14.525797
A23: 2.7 | B23: Demolição de piso cimentado sobre lastro de concreto | C23: 1 | D23: m² | E23: =ROUND(P23,2) -> 0 | F23: =ROUND(Q23,2) -> 26.98 | G23: =SUM(E23:F23) -> 26.98 | H23: =C23*E23 -> 0 | I23: =C23*F23 -> 26.98 | J23: =SUM(E23:F23)*C23 -> 26.98 | P23: 0 | Q23: 26.982488
A24: 2.8 | B24: Demolição manual de forro, inclusive sistema de fixação/tarugamento | C24: 108 | D24: m² | E24: =ROUND(P24,2) -> 0 | F24: =ROUND(Q24,2) -> 8.3 | G24: =SUM(E24:F24) -> 8.3 | H24: =C24*E24 -> 0 | I24: =C24*F24 -> 896.4 | J24: =SUM(E24:F24)*C24 -> 896.4 | P24: 0 | Q24: 8.301657
A25: 2.9 | B25: Demolição de contrapiso/argamassa regularizante, isolante ou protetora | C25: 1 | D25: m² | E25: =ROUND(P25,2) -> 0 | F25: =ROUND(Q25,2) -> 10.38 | G25: =SUM(E25:F25) -> 10.38 | H25: =C25*E25 -> 0 | I25: =C25*F25 -> 10.38 | J25: =SUM(E25:F25)*C25 -> 10.38 | P25: 0 | Q25: 10.379174
A26: 2.10 | B26: Demolição de estrutura em madeira para telhado | C26: 1 | D26: m² | E26: =ROUND(P26,2) -> 0 | F26: =ROUND(Q26,2) -> 28.13 | G26: =SUM(E26:F26) -> 28.13 | H26: =C26*E26 -> 0 | I26: =C26*F26 -> 28.13 | J26: =SUM(E26:F26)*C26 -> 28.13 | P26: 0 | Q26: 28.126384
A27: 2.11 | B27: Retirada de cumeeira, espigão, rufo, calha ou chapim, perfil qualquer | C27: 41 | D27: m | E27: =ROUND(P27,2) -> 0 | F27: =ROUND(Q27,2) -> 13.6 | G27: =SUM(E27:F27) -> 13.6 | H27: =C27*E27 -> 0 | I27: =C27*F27 -> 557.6 | J27: =SUM(E27:F27)*C27 -> 557.6 | P27: 0 | Q27: 13.600587
A28: 2.12 | B28: Retirada de piso tátil com limpeza | C28: 133 | D28: m² | E28: =ROUND(P28,2) -> 14.28 | F28: =ROUND(Q28,2) -> 22.53 | G28: =SUM(E28:F28) -> 36.81 | H28: =C28*E28 -> 1899.24 | I28: =C28*F28 -> 2996.49 | J28: =SUM(E28:F28)*C28 -> 4895.73 | P28: 14.281878 | Q28: 22.533069
... A52: 2.36 | B52: Tela para Andaime | C52: 1 | D52: m² | E52: =ROUND(P52,2) -> 3.9 | F52: =ROUND(Q52,2) -> 3.01 | G52: =SUM(E52:F52) -> 6.91 | H52: =C52*E52 -> 3.9 | I52: =C52*F52 -> 3.01 | J52: =SUM(E52:F52)*C52 -> 6.91 | P52: 3.902704 | Q52: 3.011138
A53: 3 | B53: MOVIMENTO DE TERRA | E53: =ROUND(P53,2) -> 0 | F53: =ROUND(Q53,2) -> 0 | G53: 0 | H53: 0 | I53: 0 | J53: 0
A54: 4 | B54: FUNDAÇÃO | E54: =ROUND(P54,2) -> 0 | F54: =ROUND(Q54,2) -> 0 | G54: 0 | H54: 0 | I54: 0 | J54: 0
A55: 5 | B55: ESTRUTURA | E55: =ROUND(P55,2) -> 0 | F55: =ROUND(Q55,2) -> 0 | G55: =SUBTOTAL(109,G56:G59) -> 1556.33 | H55: =SUBTOTAL(109,H56:H59) -> 1378.65 | I55: =SUBTOTAL(109,I56:I59) -> 177.68 | J55: =SUBTOTAL(109,J56:J59) -> 1556.33
A56: 5.1 | B56: Base de concreto para fixação de TAA/TTE | C56: 1 | D56: m³ | E56: =ROUND(P56,2) -> 1011.06 | F56: =ROUND(Q56,2) -> 51.57 | G56: =SUM(E56:F56) -> 1062.63 | H56: =C56*E56 -> 1011.06 | I56: =C56*F56 -> 51.57 | J56: =SUM(E56:F56)*C56 -> 1062.63 | P56: 1011.0611 | Q56: 51.567841
A57: 5.2 | B57: Montagem e Desmontagem de escoramento em madeira. | C57: 1 | D57: m² | E57: =ROUND(P57,2) -> 157.71 | F57: =ROUND(Q57,2) -> 53.43 | G57: =SUM(E57:F57) -> 211.14 | H57: =C57*E57 -> 157.71 | I57: =C57*F57 -> 53.43 | J57: =SUM(E57:F57)*C57 -> 211.14 | P57: 157.71466 | Q57: 53.426672
A58: 5.3 | B58: Montagem e Desmontagem de escoramento metálico. | C58: 1 | D58: m² | E58: =ROUND(P58,2) -> 123.98 | F58: =ROUND(Q58,2) -> 46.19 | G58: =SUM(E58:F58) -> 170.17 | H58: =C58*E58 -> 123.98 | I58: =C58*F58 -> 46.19 | J58: =SUM(E58:F58)*C58 -> 170.17 | P58: 123.97814 | Q58: 46.193212
A59: 5.4 | B59: Concreto fck = 15 MPa, controle tipo "B", e = 10 cm, e armado com tela de aço CA-60 | C59: 1 | D59: m² | E59: =ROUND(P59,2) -> 85.9 | F59: =ROUND(Q59,2) -> 26.49 | G59: =SUM(E59:F59) -> 112.39 | H59: =C59*E59 -> 85.9 | I59: =C59*F59 -> 26.49 | J59: =SUM(E59:F59)*C59 -> 112.39 | P59: 85.901543 | Q59: 26.49465
A60: 6 | B60: ALVENARIAS E OUTRAS VEDAÇÕES | E60: =ROUND(P60,2) -> 0 | F60: =ROUND(Q60,2) -> 0 | G60: =SUBTOTAL(109,G61:G63) -> 311.58 | H60: =SUBTOTAL(109,H61:H63) -> 9523.53 | I60: =SUBTOTAL(109,I61:I63) -> 3803.2 | J60: =SUBTOTAL(109,J61:J63) -> 13326.73
A61: 6.1 | B61: Alvenaria com tijolo cerâmico furado | C61: 69 | D61: m² | E61: =ROUND(P61,2) -> 33.27 | F61: =ROUND(Q61,2) -> 38.28 | G61: =SUM(E61:F61) -> 71.55 | H61: =C61*E61 -> 2295.63 | I61: =C61*F61 -> 2641.32 | J61: =SUM(E61:F61)*C61 -> 4936.95 | P61: 33.273916 | Q61: 38.278461
A62: 6.2 | B62: Parede de gesso em placas duplas acartonado dry wall - inclusive para ambientes úmidos - RU | C62: 38 | D62: m² | E62: =ROUND(P62,2) -> 174.33 | F62: =ROUND(Q62,2) -> 13.46 | G62: =SUM(E62:F62) -> 187.79 | H62: =C62*E62 -> 6624.54 | I62: =C62*F62 -> 511.48 | J62: =SUM(E62:F62)*C62 -> 7136.02 | P62: 174.3348 | Q62: 13.4576
A63: 6.3 | B63: Rasgo e fechamento em alvenaria e piso | C63: 24 | D63: m | E63: =ROUND(P63,2) -> 25.14 | F63: =ROUND(Q63,2) -> 27.1 | G63: =SUM(E63:F63) -> 52.24 | H63: =C63*E63 -> 603.36 | I63: =C63*F63 -> 650.4 | J63: =SUM(E63:F63)*C63 -> 1253.76 | P63: 25.140479 | Q63: 27.100242
A64: 7 | B64: COBERTURA | E64: =ROUND(P64,2) -> 0 | F64: =ROUND(Q64,2) -> 0 | G64: =SUBTOTAL(109,G65:G79) -> 1457.33 | H64: =SUBTOTAL(109,H65:H79) -> 96390.6 | I64: =SUBTOTAL(109,I65:I79) -> 15889.46 | J64: =SUBTOTAL(109,J65:J79) -> 112280.06
A65: 7.1 | B65: Cobertura com telha de alumínio envernizada ou pintada, e=0,5 mm | C65: 17 | D65: m² | E65: =ROUND(P65,2) -> 89.24 | F65: =ROUND(Q65,2) -> 12.72 | G65: =SUM(E65:F65) -> 101.96 | H65: =C65*E65 -> 1517.08 | I65: =C65*F65 -> 216.24 | J65: =SUM(E65:F65)*C65 -> 1733.32 | P65: 89.24071 | Q65: 12.717432
A66: 7.2 | B66: Cobertura em telha com isolamento termoacustico em espuma rígida de poliuretano (PU) injetado | C66: 1 | D66: m² | E66: =ROUND(P66,2) -> 212.33 | F66: =ROUND(Q66,2) -> 9.18 | G66: =SUM(E66:F66) -> 221.51 | H66: =C66*E66 -> 212.33 | I66: =C66*F66 -> 9.18 | J66: =SUM(E66:F66)*C66 -> 221.51 | P66: 212.32728 | Q66: 9.176401
A67: 7.3 | B67: Cumeeira em chapa metálica | C67: 1 | D67: m | E67: =ROUND(P67,2) -> 139.7 | F67: =ROUND(Q67,2) -> 5 | G67: =SUM(E67:F67) -> 144.7 | H67: =C67*E67 -> 139.7 | I67: =C67*F67 -> 5 | J67: =SUM(E67:F67)*C67 -> 144.7 | P67: 139.6983 | Q67: 5.004545
A68: 7.4 | B68: Cobertura com telha cerâmica, incluso transporte vertical | C68: 26 | D68: m² | E68: =ROUND(P68,2) -> 31.93 | F68: =ROUND(Q68,2) -> 9.72 | G68: =SUM(E68:F68) -> 41.65 | H68: =C68*E68 -> 830.18 | I68: =C68*F68 -> 252.72 | J68: =SUM(E68:F68)*C68 -> 1082.9 | P68: 31.928156 | Q68: 9.723116
A69: 7.5 | B69: Cumeeira para telha cerâmica emboçada com argamassa | C69: 1 | D69: m | E69: =ROUND(P69,2) -> 14.17 | F69: =ROUND(Q69,2) -> 21.25 | G69: =SUM(E69:F69) -> 35.42 | H69: =C69*E69 -> 14.17 | I69: =C69*F69 -> 21.25 | J69: =SUM(E69:F69)*C69 -> 35.42 | P69: 14.172535 | Q69: 21.254597
A70: 7.6 | B70: Cumeeira universal para telhado de fibrocimento, e=6mm | C70: 84 | D70: m | E70: =ROUND(P70,2) -> 85.72 | F70: =ROUND(Q70,2) -> 23.05 | G70: =SUM(E70:F70) -> 108.77 | H70: =C70*E70 -> 7200.48 | I70: =C70*F70 -> 1936.2 | J70: =SUM(E70:F70)*C70 -> 9136.68 | P70: 85.724912 | Q70: 23.054551
A71: 7.7 | B71: Cobertura com telha de fibrocimento, e = 6 mm, | C71: 87 | D71: m² | E71: =ROUND(P71,2) -> 48.81 | F71: =ROUND(Q71,2) -> 6.08 | G71: =SUM(E71:F71) -> 54.89 | H71: =C71*E71 -> 4246.47 | I71: =C71*F71 -> 528.96 | J71: =SUM(E71:F71)*C71 -> 4775.43 | P71: 48.809033 | Q71: 6.081153
A72: 7.8 | B72: Calha de chapa galvanizada nº 24 desenvolvimento 33 cm | C72: 695 | D72: m | E72: =ROUND(P72,2) -> 56.29 | F72: =ROUND(Q72,2) -> 9.66 | G72: =SUM(E72:F72) -> 65.95 | H72: =C72*E72 -> 39121.55 | I72: =C72*F72 -> 6713.7 | J72: =SUM(E72:F72)*C72 -> 45835.25 | P72: 56.286412 | Q72: 9.664239
A73: 7.9 | B73: Rufo de chapa de aço galvanizado com desenvolvimento até 50 cm | C73: 540 | D73: m | E73: =ROUND(P73,2) -> 49.24 | F73: =ROUND(Q73,2) -> 6.51 | G73: =SUM(E73:F73) -> 55.75 | H73: =C73*E73 -> 26589.6 | I73: =C73*F73 -> 3515.4 | J73: =SUM(E73:F73)*C73 -> 30105 | P73: 49.237994 | Q73: 6.510114
A74: 7.10 | B74: Chapim de chapa de aço galvanizado nº 24 desenvolvimento 33 cm | C74: 269 | D74: m | E74: =ROUND(P74,2) -> 59.94 | F74: =ROUND(Q74,2) -> 9.4 | G74: =SUM(E74:F74) -> 69.34 | H74: =C74*E74 -> 16123.86 | I74: =C74*F74 -> 2528.6 | J74: =SUM(E74:F74)*C74 -> 18652.46 | P74: 59.936786 | Q74: 9.403498
A75: 7.11 | B75: Cobertura com telha de fibrocimento estrutural, com recobrimento longitudinal | C75: 1 | D75: m² | E75: =ROUND(P75,2) -> 120.01 | F75: =ROUND(Q75,2) -> 24.15 | G75: =SUM(E75:F75) -> 144.16 | H75: =C75*E75 -> 120.01 | I75: =C75*F75 -> 24.15 | J75: =SUM(E75:F75)*C75 -> 144.16 | P75: 120.00815 | Q75: 24.147981
A76: 7.12 | B76: Estrutura de madeira para telha cerâmica, fibrocimento ou de concreto | C76: 1 | D76: m² | E76: =ROUND(P76,2) -> 89.33 | F76: =ROUND(Q76,2) -> 96.89 | G76: =SUM(E76:F76) -> 186.22 | H76: =C76*E76 -> 89.33 | I76: =C76*F76 -> 96.89 | J76: =SUM(E76:F76)*C76 -> 186.22 | P76: 89.333231 | Q76: 96.886309
... A79: 7.15 | B79: Reparo emergencial de telhado e calhas | C79: 1 | D79: un | E79: =ROUND(P79,2) -> 14.29 | F79: =ROUND(Q79,2) -> 6.08 | G79: =SUM(E79:F79) -> 20.37 | H79: =C79*E79 -> 14.29 | I79: =C79*F79 -> 6.08 | J79: =SUM(E79:F79)*C79 -> 20.37 | P79: 14.290289 | Q79: 6.081153
A80: 8 | B80: IMPERMEABILIZAÇÃO | E80: =ROUND(P80,2) -> 0 | F80: =ROUND(Q80,2) -> 0 | G80: =SUBTOTAL(109,G81:G87) -> 755.71 | H80: =SUBTOTAL(109,H81:H87) -> 133007.15 | I80: =SUBTOTAL(109,I81:I87) -> 73505.14 | J80: =SUBTOTAL(109,J81:J87) -> 206512.29
A81: 8.1 | B81: Proteção mecânica de superfície com argamassa de cimento e areia | C81: 36 | D81: m² | E81: =ROUND(P81,2) -> 29.21 | F81: =ROUND(Q81,2) -> 17.55 | G81: =SUM(E81:F81) -> 46.76 | H81: =C81*E81 -> 1051.56 | I81: =C81*F81 -> 631.8 | J81: =SUM(E81:F81)*C81 -> 1683.36 | P81: 29.211403 | Q81: 17.553757
A82: 8.2 | B82: Impermeabilização com manta asfáltica modificada com polímeros aluminizada | C82: 148 | D82: m² | E82: =ROUND(P82,2) -> 120.02 | F82: =ROUND(Q82,2) -> 16.51 | G82: =SUM(E82:F82) -> 136.53 | H82: =C82*E82 -> 17762.96 | I82: =C82*F82 -> 2443.48 | J82: =SUM(E82:F82)*C82 -> 20206.44 | P82: 120.01656 | Q82: 16.510793
A83: 8.3 | B83: Impermeabilização utilizando manta asfáltica polimérica (cobertura, lajes, banheiros, jardins, Reservatórios e similares) | C83: 118 | D83: m² | E83: =ROUND(P83,2) -> 135.87 | F83: =ROUND(Q83,2) -> 25.29 | G83: =SUM(E83:F83) -> 161.16 | H83: =C83*E83 -> 16032.66 | I83: =C83*F83 -> 2984.22 | J83: =SUM(E83:F83)*C83 -> 19016.88 | P83: 135.87129 | Q83: 25.291877
A84: 8.4 | B84: Impermeabilização de calha ou lajes descobertas com emulsão asfáltica com elastômeros, 3 demãos, com tela de poliéster | C84: 1 | D84: m² | E84: =ROUND(P84,2) -> 71.52 | F84: =ROUND(Q84,2) -> 16.76 | G84: =SUM(E84:F84) -> 88.28 | H84: =C84*E84 -> 71.52 | I84: =C84*F84 -> 16.76 | J84: =SUM(E84:F84)*C84 -> 88.28 | P84: 71.518733 | Q84: 16.763123
A85: 8.5 | B85: Impermeabilização de superfície com impermeabilizante flexível à base acrílica | C85: 1352 | D85: m² | E85: =ROUND(P85,2) -> 67.96 | F85: =ROUND(Q85,2) -> 44.78 | G85: =SUM(E85:F85) -> 112.74 | H85: =C85*E85 -> 91881.92 | I85: =C85*F85 -> 60542.56 | J85: =SUM(E85:F85)*C85 -> 152424.48 | P85: 67.96088 | Q85: 44.780164
A86: 8.6 | B86: Impermeabilização com argamassa polimérica impermeabilizante | C86: 534 | D86: m² | E86: =ROUND(P86,2) -> 11.31 | F86: =ROUND(Q86,2) -> 12.86 | G86: =SUM(E86:F86) -> 24.17 | H86: =C86*E86 -> 6039.54 | I86: =C86*F86 -> 6867.24 | J86: =SUM(E86:F86)*C86 -> 12906.78 | P86: 11.312795 | Q86: 12.860419
A87: 8.7 | B87: Impermeabilização com membrana de poliuretano (PU) | C87: 1 | D87: m² | E87: =ROUND(P87,2) -> 166.99 | F87: =ROUND(Q87,2) -> 19.08 | G87: =SUM(E87:F87) -> 186.07 | H87: =C87*E87 -> 166.99 | I87: =C87*F87 -> 19.08 | J87: =SUM(E87:F87)*C87 -> 186.07 | P87: 166.99199 | Q87: 19.084559
A88: 9 | B88: TRATAMENTO TÉRMICO E ACÚSTICO | E88: =ROUND(P88,2) -> 0 | F88: =ROUND(Q88,2) -> 0 | G88: 0 | H88: 0 | I88: 0 | J88: 0
A89: 10 | B89: PAVIMENTAÇÃO | E89: =ROUND(P89,2) -> 0 | F89: =ROUND(Q89,2) -> 0 | G89: =SUBTOTAL(109,G90:G112) -> 4252.2 | H89: =SUBTOTAL(109,H90:H112) -> 190205.92 | I89: =SUBTOTAL(109,I90:I112) -> 27993.46 | J89: =SUBTOTAL(109,J90:J112) -> 218199.38
A90: 10.1 | B90: Regularização de base ou contrapiso | C90: 753 | D90: m² | E90: =ROUND(P90,2) -> 16.88 | F90: =ROUND(Q90,2) -> 10.35 | G90: =SUM(E90:F90) -> 27.23 | H90: =C90*E90 -> 12710.64 | I90: =C90*F90 -> 7793.55 | J90: =SUM(E90:F90)*C90 -> 20504.19 | P90: 16.880877 | Q90: 10.34553
A91: 10.2 | B91: Regularização de piso para piso vinílico ou tátil em borracha | C91: 50 | D91: m² | E91: =ROUND(P91,2) -> 20.6 | F91: =ROUND(Q91,2) -> 16.55 | G91: =SUM(E91:F91) -> 37.15 | H91: =C91*E91 -> 1030 | I91: =C91*F91 -> 827.5 | J91: =SUM(E91:F91)*C91 -> 1857.5 | P91: 20.598539 | Q91: 16.552848
A92: 10.3 | B92: Granito para revestimento (piso ou parede) Cinza Andorinha, assente com argamassa | C92: 1 | D92: m² | E92: =ROUND(P92,2) -> 475.13 | F92: =ROUND(Q92,2) -> 38.06 | G92: =SUM(E92:F92) -> 513.19 | H92: =C92*E92 -> 475.13 | I92: =C92*F92 -> 38.06 | J92: =SUM(E92:F92)*C92 -> 513.19 | P92: 475.12898 | Q92: 38.059775
A93: 10.4 | B93: Rodapé em granito Cinza Andorinha, assentado e rejuntado | C93: 1 | D93: m | E93: =ROUND(P93,2) -> 78.49 | F93: =ROUND(Q93,2) -> 9.59 | G93: =SUM(E93:F93) -> 88.08 | H93: =C93*E93 -> 78.49 | I93: =C93*F93 -> 9.59 | J93: =SUM(E93:F93)*C93 -> 88.08 | P93: 78.491452 | Q93: 9.58854
A94: 10.5 | B94: Peitoril ou soleira de granito, assentado e rejuntado | C94: 88 | D94: m | E94: =ROUND(P94,2) -> 106.82 | F94: =ROUND(Q94,2) -> 17.52 | G94: =SUM(E94:F94) -> 124.34 | H94: =C94*E94 -> 9400.16 | I94: =C94*F94 -> 1541.76 | J94: =SUM(E94:F94)*C94 -> 10941.92 | P94: 106.8197 | Q94: 17.520113
A95: 10.6 | B95: Granito branco para revestimento (piso ou parede), assente com argamassa | C95: 1 | D95: m² | E95: =ROUND(P95,2) -> 878.27 | F95: =ROUND(Q95,2) -> 38.06 | G95: =SUM(E95:F95) -> 916.33 | H95: =C95*E95 -> 878.27 | I95: =C95*F95 -> 38.06 | J95: =SUM(E95:F95)*C95 -> 916.33 | P95: 878.26821 | Q95: 38.059775
A96: 10.7 | B96: Rodapé em granito branco, assentado e rejuntado | C96: 1 | D96: m | E96: =ROUND(P96,2) -> 83.98 | F96: =ROUND(Q96,2) -> 9.59 | G96: =SUM(E96:F96) -> 93.57 | H96: =C96*E96 -> 83.98 | I96: =C96*F96 -> 9.59 | J96: =SUM(E96:F96)*C96 -> 93.57 | P96: 83.975424 | Q96: 9.58854
A97: 10.8 | B97: Bloco de concreto intertravado | C97: 1 | D97: m² | E97: =ROUND(P97,2) -> 62.65 | F97: =ROUND(Q97,2) -> 6.32 | G97: =SUM(E97:F97) -> 68.97 | H97: =C97*E97 -> 62.65 | I97: =C97*F97 -> 6.32 | J97: =SUM(E97:F97)*C97 -> 68.97 | P97: 62.645128 | Q97: 6.316661
A98: 10.9 | B98: Piso em pedra portuguesa, basalto, calcário ou granito sem polimento. | C98: 1 | D98: m² | E98: =ROUND(P98,2) -> 161.91 | F98: =ROUND(Q98,2) -> 39.62 | G98: =SUM(E98:F98) -> 201.53 | H98: =C98*E98 -> 161.91 | I98: =C98*F98 -> 39.62 | J98: =SUM(E98:F98)*C98 -> 201.53 | P98: 161.91175 | Q98: 39.624221
A99: 10.10 | B99: Piso mármore branco, assentado e rejuntado | C99: 1 | D99: m² | E99: =ROUND(P99,2) -> 758.23 | F99: =ROUND(Q99,2) -> 38.06 | G99: =SUM(E99:F99) -> 796.29 | H99: =C99*E99 -> 758.23 | I99: =C99*F99 -> 38.06 | J99: =SUM(E99:F99)*C99 -> 796.29 | P99: 758.23483 | Q99: 38.059775
A100: 10.11 | B100: Piso em ladrilho hidráulico, assentado com argamassa | C100: 91 | D100: m² | E100: =ROUND(P100,2) -> 109.03 | F100: =ROUND(Q100,2) -> 70.46 | G100: =SUM(E100:F100) -> 179.49 | H100: =C100*E100 -> 9921.73 | I100: =C100*F100 -> 6411.86 | J100: =SUM(E100:F100)*C100 -> 16333.59 | P100: 109.03179 | Q100: 70.458947
A101: 10.12 | B101: Piso cimentado com argamassa e com junta plástica para dilatação. | C101: 103 | D101: m² | E101: =ROUND(P101,2) -> 33.68 | F101: =ROUND(Q101,2) -> 12.52 | G101: =SUM(E101:F101) -> 46.2 | H101: =C101*E101 -> 3469.04 | I101: =C101*F101 -> 1289.56 | J101: =SUM(E101:F101)*C101 -> 4758.6 | P101: 33.677644 | Q101: 12.515568
... A112: 10.23 | B112: Regularização de piso carpete | C112: 1 | D112: m² | E112: =ROUND(P112,2) -> 20.6 | F112: =ROUND(Q112,2) -> 8.28 | G112: =SUM(E112:F112) -> 28.88 | H112: =C112*E112 -> 20.6 | I112: =C112*F112 -> 8.28 | J112: =SUM(E112:F112)*C112 -> 28.88 | P112: 20.598539 | Q112: 8.276424
A113: 11 | B113: REVESTIMENTOS | E113: =ROUND(P113,2) -> 0 | F113: =ROUND(Q113,2) -> 0 | G113: =SUBTOTAL(109,G114:G122) -> 2233.43 | H113: =SUBTOTAL(109,H114:H122) -> 33112.31 | I113: =SUBTOTAL(109,I114:I122) -> 27840.42 | J113: =SUBTOTAL(109,J114:J122) -> 60952.73
A114: 11.1 | B114: Painéis de alumínio - ACM | C114: 1 | D114: m² | E114: =ROUND(P114,2) -> 240.26 | F114: =ROUND(Q114,2) -> 47.81 | G114: =SUM(E114:F114) -> 288.07 | H114: =C114*E114 -> 240.26 | I114: =C114*F114 -> 47.81 | J114: =SUM(E114:F114)*C114 -> 288.07 | P114: 240.26021 | Q114: 47.808124
A115: 11.2 | B115: Chapisco para parede interna ou externa com argamassa de cimento e areia. | C115: 573 | D115: m² | E115: =ROUND(P115,2) -> 2.82 | F115: =ROUND(Q115,2) -> 4.14 | G115: =SUM(E115:F115) -> 6.96 | H115: =C115*E115 -> 1615.86 | I115: =C115*F115 -> 2372.22 | J115: =SUM(E115:F115)*C115 -> 3988.08 | P115: 2.817685 | Q115: 4.138212
A116: 11.3 | B116: Emboço ou reboco para parede interna ou externa ou teto. | C116: 1298 | D116: m² | E116: =ROUND(P116,2) -> 20.6 | F116: =ROUND(Q116,2) -> 19.34 | G116: =SUM(E116:F116) -> 39.94 | H116: =C116*E116 -> 26738.8 | I116: =C116*F116 -> 25103.32 | J116: =SUM(E116:F116)*C116 -> 51842.12 | P116: 20.598539 | Q116: 19.336889
A117: 11.4 | B117: Revestimento cerâmico assentado com argamassa pré-fabricada e rejuntado | C117: 1 | D117: m² | E117: =ROUND(P117,2) -> 43.38 | F117: =ROUND(Q117,2) -> 30.99 | G117: =SUM(E117:F117) -> 74.37 | H117: =C117*E117 -> 43.38 | I117: =C117*F117 -> 30.99 | J117: =SUM(E117:F117)*C117 -> 74.37 | P117: 43.375527 | Q117: 30.986124
A118: 11.5 | B118: Revestimento (parede) em Pastilha de vidro, assentada com argamassa colante e rejunte. | C118: 1 | D118: m² | E118: =ROUND(P118,2) -> 262.83 | F118: =ROUND(Q118,2) -> 32.9 | G118: =SUM(E118:F118) -> 295.73 | H118: =C118*E118 -> 262.83 | I118: =C118*F118 -> 32.9 | J118: =SUM(E118:F118)*C118 -> 295.73 | P118: 262.82693 | Q118: 32.903832
A119: 11.6 | B119: Laminado melamínico para revestimento (piso ou parede) interno | C119: 21 | D119: m² | E119: =ROUND(P119,2) -> 139.47 | F119: =ROUND(Q119,2) -> 7.33 | G119: =SUM(E119:F119) -> 146.8 | H119: =C119*E119 -> 2928.87 | I119: =C119*F119 -> 153.93 | J119: =SUM(E119:F119)*C119 -> 3082.8 | P119: 139.4712 | Q119: 7.334392
A120: 11.7 | B120: Revestimento de parede com pedra São Tomé filetada (tipo "canjiquinha") | C120: 1 | D120: m² | E120: =ROUND(P120,2) -> 281.49 | F120: =ROUND(Q120,2) -> 28.29 | G120: =SUM(E120:F120) -> 309.78 | H120: =C120*E120 -> 281.49 | I120: =C120*F120 -> 28.29 | J120: =SUM(E120:F120)*C120 -> 309.78 | P120: 281.49094 | Q120: 28.286193
A121: 11.8 | B121: Revestimento em mármore branco (parede), assentado e rejuntado | C121: 1 | D121: m² | E121: =ROUND(P121,2) -> 758.23 | F121: =ROUND(Q121,2) -> 38.06 | G121: =SUM(E121:F121) -> 796.29 | H121: =C121*E121 -> 758.23 | I121: =C121*F121 -> 38.06 | J121: =SUM(E121:F121)*C121 -> 796.29 | P121: 758.23483 | Q121: 38.059775
A122: 11.9 | B122: Revestimento em Pastilha Cerâmica, assentada com argamassa colante e rejunte. | C122: 1 | D122: m² | E122: =ROUND(P122,2) -> 242.59 | F122: =ROUND(Q122,2) -> 32.9 | G122: =SUM(E122:F122) -> 275.49 | H122: =C122*E122 -> 242.59 | I122: =C122*F122 -> 32.9 | J122: =SUM(E122:F122)*C122 -> 275.49 | P122: 242.59006 | Q122: 32.903832
A123: 12 | B123: DIVISÓRIAS, FORROS E PISOS FALSOS | E123: =ROUND(P123,2) -> 0 | F123: =ROUND(Q123,2) -> 0 | G123: =SUBTOTAL(109,G124:G137) -> 2486.96 | H123: =SUBTOTAL(109,H124:H137) -> 59871.66 | I123: =SUBTOTAL(109,I124:I137) -> 13199.41 | J123: =SUBTOTAL(109,J124:J137) -> 73071.07
A124: 12.1 | B124: Divisória texturizada cega | C124: 1 | D124: m² | E124: =ROUND(P124,2) -> 161.77 | F124: =ROUND(Q124,2) -> 32.82 | G124: =SUM(E124:F124) -> 194.59 | H124: =C124*E124 -> 161.77 | I124: =C124*F124 -> 32.82 | J124: =SUM(E124:F124)*C124 -> 194.59 | P124: 161.76876 | Q124: 32.819722
A125: 12.2 | B125: Divisória texturizada cega/vidro | C125: 1 | D125: m² | E125: =ROUND(P125,2) -> 169.6 | F125: =ROUND(Q125,2) -> 49.21 | G125: =SUM(E125:F125) -> 218.81 | H125: =C125*E125 -> 169.6 | I125: =C125*F125 -> 49.21 | J125: =SUM(E125:F125)*C125 -> 218.81 | P125: 169.5994 | Q125: 49.212761
A126: 12.3 | B126: Porta de divisória, Inclui batente e guarnições. | C126: 1 | D126: un | E126: =ROUND(P126,2) -> 642.53 | F126: =ROUND(Q126,2) -> 32.82 | G126: =SUM(E126:F126) -> 675.35 | H126: =C126*E126 -> 642.53 | I126: =C126*F126 -> 32.82 | J126: =SUM(E126:F126)*C126 -> 675.35 | P126: 642.53311 | Q126: 32.819722
A127: 12.4 | B127: Forro de fibra mineral, incluindo fixação, com estrutura | C127: 67 | D127: m² | E127: =ROUND(P127,2) -> 190.45 | F127: =ROUND(Q127,2) -> 11.16 | G127: =SUM(E127:F127) -> 201.61 | H127: =C127*E127 -> 12760.15 | I127: =C127*F127 -> 747.72 | J127: =SUM(E127:F127)*C127 -> 13507.87 | P127: 190.45027 | Q127: 11.161397
A128: 12.5 | B128: Forro de gesso acartonado, estruturado ou aramado | C128: 215 | D128: m² | E128: =ROUND(P128,2) -> 72.63 | F128: =ROUND(Q128,2) -> 32.77 | G128: =SUM(E128:F128) -> 105.4 | H128: =C128*E128 -> 15615.45 | I128: =C128*F128 -> 7045.55 | J128: =SUM(E128:F128)*C128 -> 22661 | P128: 72.628985 | Q128: 32.769256
A129: 12.6 | B129: Forro de placa de gesso pre-moldada, incluindo fixação | C129: 40 | D129: m² | E129: =ROUND(P129,2) -> 17.49 | F129: =ROUND(Q129,2) -> 21.52 | G129: =SUM(E129:F129) -> 39.01 | H129: =C129*E129 -> 699.6 | I129: =C129*F129 -> 860.8 | J129: =SUM(E129:F129)*C129 -> 1560.4 | P129: 17.49488 | Q129: 21.515338
A130: 12.7 | B130: Junta de dilatação para forro de gesso | C130: 1 | D130: m | E130: =ROUND(P130,2) -> 12.29 | F130: =ROUND(Q130,2) -> 6.59 | G130: =SUM(E130:F130) -> 18.88 | H130: =C130*E130 -> 12.29 | I130: =C130*F130 -> 6.59 | J130: =SUM(E130:F130)*C130 -> 18.88 | P130: 12.288471 | Q130: 6.585813
A131: 12.8 | B131: Piso elevado com estrutura | C131: 48 | D131: m² | E131: =ROUND(P131,2) -> 493.52 | F131: =ROUND(Q131,2) -> 24.97 | G131: =SUM(E131:F131) -> 518.49 | H131: =C131*E131 -> 23688.96 | I131: =C131*F131 -> 1198.56 | J131: =SUM(E131:F131)*C131 -> 24887.52 | P131: 493.52384 | Q131: 24.972259
A132: 12.9 | B132: Forro de gesso, incluindo fixação, sem estrutura | C132: 236 | D132: m² | E132: =ROUND(P132,2) -> 15.53 | F132: =ROUND(Q132,2) -> 10.76 | G132: =SUM(E132:F132) -> 26.29 | H132: =C132*E132 -> 3665.08 | I132: =C132*F132 -> 2539.36 | J132: =SUM(E132:F132)*C132 -> 6204.44 | P132: 15.526706 | Q132: 10.757669
A133: 12.10 | B133: Forro de fibra mineral, incluindo fixação, sem estrutura | C133: 25 | D133: m² | E133: =ROUND(P133,2) -> 84.82 | F133: =ROUND(Q133,2) -> 25.75 | G133: =SUM(E133:F133) -> 110.57 | H133: =C133*E133 -> 2120.5 | I133: =C133*F133 -> 643.75 | J133: =SUM(E133:F133)*C133 -> 2764.25 | P133: 84.816524 | Q133: 25.754482
A134: 12.11 | B134: Piso elevado sem estrutura | C134: 1 | D134: m² | E134: =ROUND(P134,2) -> 240.5 | F134: =ROUND(Q134,2) -> 12.49 | G134: =SUM(E134:F134) -> 252.99 | H134: =C134*E134 -> 240.5 | I134: =C134*F134 -> 12.49 | J134: =SUM(E134:F134)*C134 -> 252.99 | P134: 240.50413 | Q134: 12.490335
A135: 12.12 | B135: Ajuste do forro de fibra mineral | C135: 1 | D135: m² | E135: =ROUND(P135,2) -> 14.26 | F135: =ROUND(Q135,2) -> 5.58 | G135: =SUM(E135:F135) -> 19.84 | H135: =C135*E135 -> 14.26 | I135: =C135*F135 -> 5.58 | J135: =SUM(E135:F135)*C135 -> 19.84 | P135: 14.256645 | Q135: 5.576493
... A137: 12.14 | B137: Forro de gesso (RU), incluindo fixação, sem estrutura | C137: 1 | D137: m² | E137: =ROUND(P137,2) -> 36.07 | F137: =ROUND(Q137,2) -> 12.08 | G137: =SUM(E137:F137) -> 48.15 | H137: =C137*E137 -> 36.07 | I137: =C137*F137 -> 12.08 | J137: =SUM(E137:F137)*C137 -> 48.15 | P137: 36.066368 | Q137: 12.078196
A138: 13 | B138: CARPINTARIA / MARCENARIA | E138: =ROUND(P138,2) -> 0 | F138: =ROUND(Q138,2) -> 0 | G138: =SUBTOTAL(109,G139:G160) -> 3749.86 | H138: =SUBTOTAL(109,H139:H160) -> 21415.55 | I138: =SUBTOTAL(109,I139:I160) -> 20696.45 | J138: =SUBTOTAL(109,J139:J160) -> 42112
...

Sheet Prefixos
A1: LOTE 07: MATO GROSSO DO SUL – Campo Grande e Aquidauana
A2: Relação das Dependências do Rot - Campo Grande (MS)
A5: PREFIXO | B5: DEPENDÊNCIAS | C5: MUNICÍPIO | D5: DISTÂNCIA EM RELAÇÃO A CIDADE BASE - IDA E VOLTA (KM) | E5: ENDEREÇO
A6: 48 | B6: AFONSO PENA | C6: CAMPO GRANDE | D6: 20 | E6: AV.AFONSO PENA,2202
A7: 552 | B7: COXIM | C7: COXIM | D7: 504 | E7: R.ANTONIO DE ALBUQUERQUE,248
A8: 753 | B8: RIO VERDE M.GROSSO | C8: RIO VERDE DE MATO GROSSO | D8: 402 | E8: R.BARAO DO RIO BRANCO,173
A9: 1147 | B9: SIDROLANDIA | C9: SIDROLANDIA | D9: 142 | E9: R.RIO GRANDE DO NORTE,160
A10: 1872 | B10: COSTA RICA | C10: COSTA RICA | D10: 652 | E10: AV.JOSE FERREIRA DA COSTA,1480
A11: 1873 | B11: CIDADE MORENA | C11: CAMPO GRANDE | D11: 20 | E11: R.JOAO PEDRO DE SOUZA,1275
A12: 1881 | B12: ESTILO CAMPO GRANDE | C12: CAMPO GRANDE | D12: 20 | E12: AV.DR.PAULO COELHO MACHADO,164
A13: 1997 | B13: ESTILO PANTANAL | C13: CAMPO GRANDE | D13: 20 | E13: AV.AFONSO PENA,2202
A14: 2431 | B14: PEDRO GOMES | C14: PEDRO GOMES | D14: 608 | E14: R.BAHIA,545
A15: 2576 | B15: S.PUBLICO C.GRANDE | C15: CAMPO GRANDE | D15: 20 | E15: AV.WALDIR DOS SANTOS PEREIRA,S/N
A16: 2609 | B16: CORP BANK MS | C16: CAMPO GRANDE | D16: 20 | E16: R.QUINZE DE NOVEMBRO,2550
A17: 2620 | B17: SAO GABRIEL DO OESTE | C17: SAO GABRIEL DO OESTE | D17: 272 | E17: R.MINAS GERAIS,1305
... A38: 3929 | B38: BANDEIRANTES | C38: BANDEIRANTES | D38: 137 | E38: R.DRA.JACIRA ONORIO LYRIO,1340 - - - - CEP: 0
A57: Relação das Dependências do Rot - Aquidauana (MS)
A60: PREFIXO | B60: DEPENDÊNCIAS | C60: MUNICÍPIO | D60: DISTÂNCIA EM RELAÇÃO A CIDADE BASE - IDA E VOLTA (KM) | E60: ENDEREÇO
A61: 14 | B61: CORUMBA | C61: CORUMBA | D61: 594 | E61: R.TREZE DE JUNHO,914
A62: 123 | B62: AQUIDAUANA | C62: AQUIDAUANA | D62: 10 | E62: R.MANOEL A.PAES DE BARROS,535
A63: 543 | B63: GUIA LOPES DA LAGUNA | C63: GUIA LOPES DA LAGUNA | D63: 278 | E63: AV.VISC.DE TAUNAY,608
A64: 623 | B64: MIRANDA | C64: MIRANDA | D64: 154 | E64: R.TIRADENTES,364
A65: 742 | B65: PORTO MURTINHO | C65: PORTO MURTINHO | D65: 694 | E65: PCA.THOMAZ LARANJEIRAS,34
A66: 1031 | B66: BONITO-MS | C66: BONITO | D66: 258 | E66: R.LUIZ DA COSTA LEITE,2279
A67: 2340 | B67: NIOAQUE | C67: NIOAQUE | D67: 186 | E67: R.BENJAMIN CONSTANT,342
A68: 3093 | B68: DOIS IRMAOS BURITI | C68: DOIS IRMAOS DO BURITI | D68: 144 | E68: AV.REGINALDO LEMES DA SILVA,564
A69: 3930 | B69: BODOQUENA | C69: BODOQUENA | D69: 268 | E69: R.TREZE DE MAIO,305
